Workbook

Sheet 1
A1: DINERO EXPRESS #8 (512) 8015655 | H1: =A1 -> DINERO EXPRESS #8 (512) 8015655 | M1: DATE
A2: Daily Report | D2: Date: | H2: OTHER REPORTS | M2: 45269 | O2: Lottery Sale
D3: Day: | M3: =F3 -> 0 | O3: Game # | P3: Open | Q3: Close | R3: Tic.Sold | S3: $ Value | T3: T. Sale
A4: Reciepts | C4: Amount | D4: Disbursments | F4: Amount | H4: MONEY TRANSFER | N4: 1 | R4: =Q4-P4 -> 0 | S4: 50 | T4: =R4*S4 -> 0
A5: Taxable Sale | C5: 12 | D5: Cash Purchases | F5: =C40 -> 0 | H5: Company | I5: Amount | J5: Fees | K5: Commission | L5: Individual Total Amount | N5: 2 | R5: =Q5-P5 -> 0 | S5: 20 | T5: =R5*S5 -> 0
A6: Comm & Fee | C6: 12 | D6: Cash Expense | F6: =F40 -> 0 | H6: DINEX | L6: =SUM(I6:K6) -> 0 | N6: 3 | R6: =Q6-P6 -> 0 | S6: 20 | T6: =R6*S6 -> 0
A7: Sales Tax | D7: Check Purchases | F7: =C53 -> 0 | H7: INTERMEX | I7: 7254.97 | J7: 169 | L7: =SUM(I7:K7) -> 7423.97 | N7: 4 | R7: =Q7-P7 -> 0 | S7: 10 | T7: =R7*S7 -> 0
A8: Money Transfers | C8: =L14 -> 9830.3 | D8: Check Expense | F8: =F47 -> 0 | H8: SIGUE | L8: =SUM(I8:K8) -> 0 | N8: 5 | R8: =Q8-P8 -> 0 | S8: 10 | T8: =R8*S8 -> 0
A9: Lottery Sales | C9: =S52 -> 0 | D9: Lotto Paid Out | H9: AFEX | L9: =SUM(I9:K9) -> 0 | N9: 6 | R9: =Q9-P9 -> 0 | S9: 20 | T9: =R9*S9 -> 0
A10: Lotto Net Sales | D10: Lottery Paid Out | H10: MONEYGRAM | L10: =SUM(I10:K10) -> 0 | N10: 7 | R10: =Q10-P10 -> 0 | S10: 20 | T10: =R10*S10 -> 0
A11: PhoneCard | D11: ATM Drop | H11: BARRI | I11: 1316.03 | J11: 30 | L11: =SUM(I11:K11) -> 1346.03 | N11: 8 | R11: =Q11-P11 -> 0 | S11: 20 | T11: =R11*S11 -> 0
A12: Boss Revolution | D12: Credit Card | H12: MAXI | I12: 1010.3 | J12: 50 | L12: =SUM(I12:K12) -> 1060.3 | N12: 9 | R12: =Q12-P12 -> 0 | S12: 10 | T12: =R12*S12 -> 0
A13: Bill Payment | D13: Outside Cash & Drops | F13: =L40 -> 9830 | H13: AMIGO SIN PIN | L13: =SUM(I13:K13) -> 0 | N13: 10 | R13: =Q13-P13 -> 0 | S13: 10 | T13: =R13*S13 -> 0
A14: VidaPay | D14: Cash Deposit | H14: TOTAL | I14: =SUM(I6:I13) -> 9581.3 | J14: =SUM(J6:J13) -> 249 | K14: =SUM(K6:K13) -> 0 | L14: =SUM(L6:M13) -> 9830.3 | N14: 11 | R14: =Q14-P14 -> 0 | S14: 5 | T14: =R14*S14 -> 0
A15: Boost Epay | D15: Money Gram Payment | N15: 12 | R15: =Q15-P15 -> 0 | S15: 5 | T15: =R15*S15 -> 0
A16: Epay | D16: Vigo Payment | N16: 13 | R16: =Q16-P16 -> 0 | S16: 5 | T16: =R16*S16 -> 0
A17: Check Cashing Fees | C17: 131.48 | D17: Ria Payment | N17: 14 | R17: =Q17-P17 -> 0 | S17: 5 | T17: =R17*S17 -> 0
A18: Money Order | C18: 2958.51 | D18: Checks Deposit | F18: =J25 -> 26296.19 | H18: CHECK DEPOSITS | K18: DROPS | L18: AMOUNT | M18: TIME | N18: 15 | R18: =Q18-P18 -> 0 | S18: 5 | T18: =R18*S18 -> 0
A19: Return Check Paid | C19: =F33 -> 0 | D19: Safe Balance | F19: 50613 | H19: CHECK DEPOSITS TO BANK | J19: AMOUNT | K19: 1 | L19: 3000 | M19: 0.57083333 | N19: 16 | R19: =Q19-P19 -> 0 | S19: 5 | T19: =R19*S19 -> 0
A20: Forward Balance | C20: 55994 | D20: Payroll Expense | F20: =J40 -> 0 | H20: NIZARI (29 Checks) | J20: 26296.19 | K20: 2 | L20: 6830 | M20: 0.87708333 | N20: 17 | R20: =Q20-P20 -> 0 | S20: 5 | T20: =R20*S20 -> 0
A21: Cash From Bank | C21: 20000 | D21: Other Cash Out | F21: =M53 -> 2400 | K21: 3 | N21: 18 | R21: =Q21-P21 -> 0 | S21: 5 | T21: =R21*S21 -> 0
A22: Other Cash In | C22: =J53 -> 200 | D22: TOTAL PAYOUTS | F22: =SUM(F5:F21)-F7-F8 -> 89139.19 | K22: 4 | N22: 19 | R22: =Q22-P22 -> 0 | S22: 5 | T22: =R22*S22 -> 0
A23: Rebates & Commissions | C23: =F53 -> 0 | D23: Inside Over - (Short) | F23: =(F11+F14+F15+F16+F17+F18+F19+F20+F21+F5+F6)-(C17+C19+C20+C21+C22+C23) -> 2983.71 | K23: 5 | N23: 20 | R23: =Q23-P23 -> 0 | S23: 5 | T23: =R23*S23 -> 0
A24: TOTAL RECEIPTS | C24: =SUM(C5:C23) -> 89138.29 | D24: Over All Over - (Short) | F24: =SUM(F22-C24) -> 0.9 | K24: 6 | N24: 21 | R24: =Q24-P24 -> 0 | S24: 5 | T24: =R24*S24 -> 0
A25: Out Side Over - (Short) | C25: =(F9+F10+F12+F13)-(C5+C6+C7+C8+C9+C10+C11+C12+C13+C14+C15+C16+C18) -> -2982.81 | H25: TOTAL | J25: =SUM(J20:J24) -> 26296.19 | K25: 7 | N25: 22 | R25: =Q25-P25 -> 0 | S25: 5 | T25: =R25*S25 -> 0
A26: Cash Purchases | D26: Return Check Paid | K26: 8 | N26: 23 | R26: =Q26-P26 -> 0 | S26: 3 | T26: =R26*S26 -> 0
A27: Description | C27: Amount | D27: Description | F27: Amount | K27: 9 | N27: 24 | R27: =Q27-P27 -> 0 | S27: 3 | T27: =R27*S27 -> 0
H28: CASH PAYROLL EXPENSE | K28: 10 | N28: 25 | R28: =Q28-P28 -> 0 | S28: 2 | T28: =R28*S28 -> 0
H29: CASH PAYROLL PAID TO | J29: AMOUNT | K29: 11 | N29: 26 | R29: =Q29-P29 -> 0 | S29: 5 | T29: =R29*S29 -> 0
K30: 12 | N30: 27 | R30: =Q30-P30 -> 0 | S30: 3 | T30: =R30*S30 -> 0
K31: 13 | N31: 28 | R31: =Q31-P31 -> 0 | S31: 3 | T31: =R31*S31 -> 0
K32: 14 | N32: 29 | R32: =Q32-P32 -> 0 | S32: 2 | T32: =R32*S32 -> 0
D33: Total | F33: =SUM(F28:F32) -> 0 | K33: 15 | N33: 30 | R33: =Q33-P33 -> 0 | S33: 2 | T33: =R33*S33 -> 0
D34: Cash Expense | K34: 16 | N34: 31 | R34: =Q34-P34 -> 0 | S34: 2 | T34: =R34*S34 -> 0
D35: Description | F35: Amount | K35: 17 | N35: 32 | R35: =Q35-P35 -> 0 | S35: 2 | T35: =R35*S35 -> 0
K36: 18 | N36: 33 | R36: =Q36-P36 -> 0 | S36: 2 | T36: =R36*S36 -> 0
K37: 19 | N37: 34 | R37: =Q37-P37 -> 0 | S37: 1 | T37: =R37*S37 -> 0
K38: 20 | N38: 35 | R38: =Q38-P38 -> 0 | S38: 1 | T38: =R38*S38 -> 0
K39: 21 | N39: 36 | R39: =Q39-P39 -> 0 | S39: 2 | T39: =R39*S39 -> 0
A40: Total | C40: =SUM(C28:C39) -> 0 | D40: Total | F40: =SUM(F36:F39) -> 0 | H40: TOTAL | J40: =SUM(J30:J39) -> 0 | K40: TOTAL | L40: =SUM(L19:L39) -> 9830 | N40: 37 | R40: =Q40-P40 -> 0 | S40: 2 | T40: =R40*S40 -> 0
N41: 38 | R41: =Q41-P41 -> 0 | S41: 2 | T41: =R41*S41 -> 0
A42: Check Purchases | D42: Check Expenses | N42: 39 | R42: =Q42-P42 -> 0 | S42: 1 | T42: =R42*S42 -> 0
A43: Description | B43: Check | C43: Amount | D43: Description | E43: Check | F43: Amount | H43: CASH IN | K43: CASH OUT TO OTHER | N43: 40 | R43: =Q43-P43 -> 0 | S43: 1 | T43: =R43*S43 -> 0
H44: CASH IN FROM | J44: AMOUNT | K44: OTHER CASH OUT | M44: AMOUNT | N44: 41 | R44: =Q44-P44 -> 0 | S44: 10 | T44: =R44*S44 -> 0
H45: Paco $200 28th March | J45: 200 | K45: ATM Loading | M45: 2000 | N45: 42 | R45: =Q45-P45 -> 0 | S45: 1 | T45: =R45*S45 -> 0
K46: Noel Out | M46: 400 | N46: 43 | R46: =Q46-P46 -> 0 | S46: 1 | T46: =R46*S46 -> 0
D47: Total | F47: =SUM(F44:F46) -> 0 | N47: 44 | R47: =Q47-P47 -> 0 | S47: 1 | T47: =R47*S47 -> 0
D48: Rebates and Commissions | N48: 45 | R48: =Q48-P48 -> 0 | S48: 1 | T48: =R48*S48 -> 0
D49: Description | F49: Amount | N49: 46 | R49: =Q49-P49 -> 0 | S49: 1 | T49: =R49*S49 -> 0
N50: 47 | R50: =Q50-P50 -> 0 | S50: 1 | T50: =R50*S50 -> 0
N51: 48 | R51: =Q51-P51 -> 0 | S51: 1 | T51: =R51*S51 -> 0
O52: Total Lottery Sale | S52: =SUM(T4:T51) -> 0
A53: Total | C53: =SUM(C44:C52) -> 0 | D53: Total | F53: =SUM(F50:F52) -> 0 | H53: TOTAL | J53: =SUM(J45:J52) -> 200 | K53: TOTAL | M53: =SUM(M45:M52) -> 2400

Sheet 2
A1: ='1'!A1:F1 -> DINERO EXPRESS #8 (512) 8015655 | H1: =A1 -> DINERO EXPRESS #8 (512) 8015655 | M1: DATE
A2: Daily Report | D2: Date: | F2: ='1'!F2+1 -> 1 | H2: OTHER REPORTS | M2: =F2 -> 1 | O2: Lottery Sale
D3: Day: | M3: =F3 -> 0 | O3: Game # | P3: Open | Q3: Close | R3: Tic.Sold | S3: $ Value | T3: T. Sale
A4: Reciepts | C4: Amount | D4: Disbursments | F4: Amount | H4: MONEY TRANSFER | N4: 1 | P4: ='1'!Q4 -> 0 | R4: =Q4-P4 -> 0 | S4: 50 | T4: =R4*S4 -> 0
A5: ='1'!A5:B5 -> Taxable Sale | C5: 16 | D5: ='1'!D5:E5 -> Cash Purchases | F5: =C40 -> 0 | H5: Company | I5: Amount | J5: Fees | K5: Commission | L5: Individual Total Amount | N5: 2 | P5: ='1'!Q5 -> 0 | R5: =Q5-P5 -> 0 | S5: 20 | T5: =R5*S5 -> 0
A6: ='1'!A6:B6 -> Comm & Fee | D6: ='1'!D6:E6 -> Cash Expense | F6: =F40 -> 0 | H6: ='1'!H6 -> DINEX | L6: =SUM(I6:K6) -> 0 | N6: 3 | P6: ='1'!Q6 -> 0 | R6: =Q6-P6 -> 0 | S6: 20 | T6: =R6*S6 -> 0
A7: ='1'!A7:B7 -> Sales Tax | D7: ='1'!D7:E7 -> Check Purchases | F7: =C53 -> 0 | H7: ='1'!H7 -> INTERMEX | I7: 3308.31 | J7: 77.76 | L7: =SUM(I7:K7) -> 3386.07 | N7: 4 | P7: ='1'!Q7 -> 0 | R7: =Q7-P7 -> 0 | S7: 10 | T7: =R7*S7 -> 0
A8: ='1'!A8:B8 -> Money Transfers | C8: =L14 -> 4393.4 | D8: ='1'!D8:E8 -> Check Expense | F8: =F47 -> 0 | H8: ='1'!H8 -> SIGUE | L8: =SUM(I8:K8) -> 0 | N8: 5 | P8: ='1'!Q8 -> 0 | R8: =Q8-P8 -> 0 | S8: 10 | T8: =R8*S8 -> 0
A9: ='1'!A9:B9 -> Lottery Sales | C9: =S52 -> 0 | D9: ='1'!D9:E9 -> Lotto Paid Out | H9: ='1'!H9 -> AFEX | L9: =SUM(I9:K9) -> 0 | N9: 6 | P9: ='1'!Q9 -> 0 | R9: =Q9-P9 -> 0 | S9: 20 | T9: =R9*S9 -> 0
A10: ='1'!A10:B10 -> Lotto Net Sales | D10: ='1'!D10:E10 -> Lottery Paid Out | H10: ='1'!H10 -> MONEYGRAM | L10: =SUM(I10:K10) -> 0 | N10: 7 | P10: ='1'!Q10 -> 0 | R10: =Q10-P10 -> 0 | S10: 20 | T10: =R10*S10 -> 0
A11: ='1'!A11:B11 -> PhoneCard | D11: ='1'!D11:E11 -> ATM Drop | H11: ='1'!H11 -> BARRI | I11: 190.01 | J11: 12 | L11: =SUM(I11:K11) -> 202.01 | N11: 8 | P11: ='1'!Q11 -> 0 | R11: =Q11-P11 -> 0 | S11: 20 | T11: =R11*S11 -> 0
A12: ='1'!A12:B12 -> Boss Revolution | D12: ='1'!D12:E12 -> Credit Card | H12: ='1'!H12 -> MAXI | I12: 745.32 | J12: 60 | L12: =SUM(I12:K12) -> 805.32 | N12: 9 | P12: ='1'!Q12 -> 0 | R12: =Q12-P12 -> 0 | S12: 10 | T12: =R12*S12 -> 0
A13: ='1'!A13:B13 -> Bill Payment | D13: ='1'!D13:E13 -> Outside Cash & Drops | F13: =L40 -> 4393 | H13: ='1'!H13 -> AMIGO SIN PIN | L13: =SUM(I13:K13) -> 0 | N13: 10 | P13: ='1'!Q13 -> 0 | R13: =Q13-P13 -> 0 | S13: 10 | T13: =R13*S13 -> 0
A14: ='1'!A14:B14 -> VidaPay | D14: ='1'!D14:E14 -> Cash Deposit | H14: TOTAL | I14: =SUM(I6:I13) -> 4243.64 | J14: =SUM(J6:J13) -> 149.76 | K14: =SUM(K6:K13) -> 0 | L14: =SUM(L6:M13) -> 4393.4 | N14: 11 | P14: ='1'!Q14 -> 0 | R14: =Q14-P14 -> 0 | S14: 5 | T14: =R14*S14 -> 0
A15: ='1'!A15:B15 -> Boost Epay | D15: ='1'!D15:E15 -> Money Gram Payment | N15: 12 | P15: ='1'!Q15 -> 0 | R15: =Q15-P15 -> 0 | S15: 5 | T15: =R15*S15 -> 0
A16: ='1'!A16:B16 -> Epay | D16: ='1'!D16:E16 -> Vigo Payment | N16: 13 | P16: ='1'!Q16 -> 0 | R16: =Q16-P16 -> 0 | S16: 5 | T16: =R16*S16 -> 0
A17: ='1'!A17:B17 -> Check Cashing Fees | C17: 76.83 | D17: ='1'!D17:E17 -> Ria Payment | N17: 14 | P17: ='1'!Q17 -> 0 | R17: =Q17-P17 -> 0 | S17: 5 | T17: =R17*S17 -> 0
A18: ='1'!A18:B18 -> Money Order | C18: 9372.08 | D18: ='1'!D18:E18 -> Checks Deposit | F18: =J25 -> 15365.97 | H18: CHECK DEPOSITS | K18: DROPS | L18: AMOUNT | M18: TIME | N18: 15 | P18: ='1'!Q18 -> 0 | R18: =Q18-P18 -> 0 | S18: 5 | T18: =R18*S18 -> 0
A19: ='1'!A19:B19 -> Return Check Paid | C19: =F33 -> 1835 | D19: ='1'!D19:E19 -> Safe Balance | F19: 69478 | H19: CHECK DEPOSITS TO BANK | J19: AMOUNT | K19: 1 | L19: 3460 | M19: 0.62569444 | N19: 16 | P19: ='1'!Q19 -> 0 | R19: =Q19-P19 -> 0 | S19: 5 | T19: =R19*S19 -> 0
A20: ='1'!A20:B20 -> Forward Balance | C20: ='1'!F19+'1'!F13 -> 60443 | D20: ='1'!D20:E20 -> Payroll Expense | F20: =J40 -> 0 | H20: NIZARI (18 Checks) | J20: 15365.97 | K20: 2 | L20: 933 | M20: 0.87569444 | N20: 17 | P20: ='1'!Q20 -> 0 | R20: =Q20-P20 -> 0 | S20: 5 | T20: =R20*S20 -> 0
A21: ='1'!A21:B21 -> Cash From Bank | C21: 13000 | D21: ='1'!D21:E21 -> Other Cash Out | F21: =M53 -> 2300 | K21: 3 | N21: 18 | P21: ='1'!Q21 -> 0 | R21: =Q21-P21 -> 0 | S21: 5 | T21: =R21*S21 -> 0
A22: ='1'!A22:B22 -> Other Cash In | C22: =J53 -> 2400 | D22: TOTAL PAYOUTS | F22: =SUM(F5:F21)-F7-F8 -> 91536.97 | K22: 4 | N22: 19 | P22: ='1'!Q22 -> 0 | R22: =Q22-P22 -> 0 | S22: 5 | T22: =R22*S22 -> 0
A23: ='1'!A23:B23 -> Rebates & Commissions | C23: =F53 -> 0 | D23: Inside Over - (Short) | F23: =(F11+F14+F15+F16+F17+F18+F19+F20+F21+F5+F6)-(C17+C19+C20+C21+C22+C23) -> 9389.14 | K23: 5 | N23: 20 | P23: ='1'!Q23 -> 0 | R23: =Q23-P23 -> 0 | S23: 5 | T23: =R23*S23 -> 0
A24: TOTAL RECEIPTS | C24: =SUM(C5:C23) -> 91536.31 | D24: Over All Over - (Short) | F24: =SUM(F22-C24) -> 0.66 | K24: 6 | N24: 21 | P24: ='1'!Q24 -> 0 | R24: =Q24-P24 -> 0 | S24: 5 | T24: =R24*S24 -> 0
A25: Out Side Over - (Short) | C25: =(F9+F10+F12+F13)-(C5+C6+C7+C8+C9+C10+C11+C12+C13+C14+C15+C16+C18) -> -9388.48 | H25: TOTAL | J25: =SUM(J20:J24) -> 15365.97 | K25: 7 | N25: 22 | P25: ='1'!Q25 -> 0 | R25: =Q25-P25 -> 0 | S25: 5 | T25: =R25*S25 -> 0
A26: Cash Purchases | D26: Return Check Paid | K26: 8 | N26: 23 | P26: ='1'!Q26 -> 0 | R26: =Q26-P26 -> 0 | S26: 3 | T26: =R26*S26 -> 0
A27: Description | C27: Amount | D27: Description | F27: Amount | K27: 9 | N27: 24 | P27: ='1'!Q27 -> 0 | R27: =Q27-P27 -> 0 | S27: 3 | T27: =R27*S27 -> 0
D28: Barbara N Lampart | F28: 1835 | H28: CASH PAYROLL EXPENSE | K28: 10 | N28: 25 | P28: ='1'!Q28 -> 0 | R28: =Q28-P28 -> 0 | S28: 2 | T28: =R28*S28 -> 0
H29: CASH PAYROLL PAID TO | J29: AMOUNT | K29: 11 | N29: 26 | P29: ='1'!Q29 -> 0 | R29: =Q29-P29 -> 0 | S29: 5 | T29: =R29*S29 -> 0
K30: 12 | N30: 27 | P30: ='1'!Q30 -> 0 | R30: =Q30-P30 -> 0 | S30: 3 | T30: =R30*S30 -> 0
K31: 13 | N31: 28 | P31: ='1'!Q31 -> 0 | R31: =Q31-P31 -> 0 | S31: 3 | T31: =R31*S31 -> 0
K32: 14 | N32: 29 | P32: ='1'!Q32 -> 0 | R32: =Q32-P32 -> 0 | S32: 2 | T32: =R32*S32 -> 0
D33: Total | F33: =SUM(F28:F32) -> 1835 | K33: 15 | N33: 30 | P33: ='1'!Q33 -> 0 | R33: =Q33-P33 -> 0 | S33: 2 | T33: =R33*S33 -> 0
D34: Cash Expense | K34: 16 | N34: 31 | P34: ='1'!Q34 -> 0 | R34: =Q34-P34 -> 0 | S34: 2 | T34: =R34*S34 -> 0
D35: Description | F35: Amount | K35: 17 | N35: 32 | P35: ='1'!Q35 -> 0 | R35: =Q35-P35 -> 0 | S35: 2 | T35: =R35*S35 -> 0
K36: 18 | N36: 33 | P36: ='1'!Q36 -> 0 | R36: =Q36-P36 -> 0 | S36: 2 | T36: =R36*S36 -> 0
K37: 19 | N37: 34 | P37: ='1'!Q37 -> 0 | R37: =Q37-P37 -> 0 | S37: 1 | T37: =R37*S37 -> 0
K38: 20 | N38: 35 | P38: ='1'!Q38 -> 0 | R38: =Q38-P38 -> 0 | S38: 1 | T38: =R38*S38 -> 0
K39: 21 | N39: 36 | P39: ='1'!Q39 -> 0 | R39: =Q39-P39 -> 0 | S39: 2 | T39: =R39*S39 -> 0
A40: Total | C40: =SUM(C28:C39) -> 0 | D40: Total | F40: =SUM(F36:F39) -> 0 | H40: TOTAL | J40: =SUM(J30:J39) -> 0 | K40: TOTAL | L40: =SUM(L19:L39) -> 4393 | N40: 37 | P40: ='1'!Q40 -> 0 | R40: =Q40-P40 -> 0 | S40: 2 | T40: =R40*S40 -> 0
N41: 38 | P41: ='1'!Q41 -> 0 | R41: =Q41-P41 -> 0 | S41: 2 | T41: =R41*S41 -> 0
A42: Check Purchases | D42: Check Expenses | N42: 39 | P42: ='1'!Q42 -> 0 | R42: =Q42-P42 -> 0 | S42: 1 | T42: =R42*S42 -> 0
A43: Description | B43: Check | C43: Amount | D43: Description | E43: Check | F43: Amount | H43: CASH IN | K43: CASH OUT TO OTHER | N43: 40 | P43: ='1'!Q43 -> 0 | R43: =Q43-P43 -> 0 | S43: 1 | T43: =R43*S43 -> 0
H44: CASH IN FROM | J44: AMOUNT | K44: OTHER CASH OUT | M44: AMOUNT | N44: 41 | P44: ='1'!Q44 -> 0 | R44: =Q44-P44 -> 0 | S44: 10 | T44: =R44*S44 -> 0
H45: Take ATM Back $2K | J45: 2000 | K45: ATM Out | M45: 2000 | N45: 42 | P45: ='1'!Q45 -> 0 | R45: =Q45-P45 -> 0 | S45: 1 | T45: =R45*S45 -> 0
H46: Take Noel $400 | J46: 400 | K46: Paco Out $300 | M46: 300 | N46: 43 | P46: ='1'!Q46 -> 0 | R46: =Q46-P46 -> 0 | S46: 1 | T46: =R46*S46 -> 0
D47: Total | F47: =SUM(F44:F46) -> 0 | N47: 44 | P47: ='1'!Q47 -> 0 | R47: =Q47-P47 -> 0 | S47: 1 | T47: =R47*S47 -> 0
D48: Rebates and Commissions | N48: 45 | P48: ='1'!Q48 -> 0 | R48: =Q48-P48 -> 0 | S48: 1 | T48: =R48*S48 -> 0
D49: Description | F49: Amount | N49: 46 | P49: ='1'!Q49 -> 0 | R49: =Q49-P49 -> 0 | S49: 1 | T49: =R49*S49 -> 0
N50: 47 | P50: ='1'!Q50 -> 0 | R50: =Q50-P50 -> 0 | S50: 1 | T50: =R50*S50 -> 0
N51: 48 | P51: ='1'!Q51 -> 0 | R51: =Q51-P51 -> 0 | S51: 1 | T51: =R51*S51 -> 0
O52: Total Lottery Sale | S52: =SUM(T4:T51) -> 0
A53: Total | C53: =SUM(C44:C52) -> 0 | D53: Total | F53: =SUM(F50:F52) -> 0 | H53: TOTAL | J53: =SUM(J45:J52) -> 2400 | K53: TOTAL | M53: =SUM(M45:M52) -> 2300

Sheet 3
A1: ='1'!A1:F1 -> DINERO EXPRESS #8 (512) 8015655 | H1: =A1 -> DINERO EXPRESS #8 (512) 8015655 | M1: DATE
A2: Daily Report | D2: Date: | F2: ='2'!F2+1 -> 2 | H2: OTHER REPORTS | M2: =F2 -> 2 | O2: Lottery Sale
D3: Day: | M3: =F3 -> 0 | O3: Game # | P3: Open | Q3: Close | R3: Tic.Sold | S3: $ Value | T3: T. Sale
A4: Reciepts | C4: Amount | D4: Disbursments | F4: Amount | H4: MONEY TRANSFER | N4: 1 | P4: ='2'!Q4 -> 0 | R4: =Q4-P4 -> 0 | S4: 50 | T4: =R4*S4 -> 0
A5: ='1'!A5:B5 -> Taxable Sale | D5: ='1'!D5:E5 -> Cash Purchases | F5: =C40 -> 0 | H5: Company | I5: Amount | J5: Fees | K5: Commission | L5: Individual Total Amount | N5: 2 | P5: ='2'!Q5 -> 0 | R5: =Q5-P5 -> 0 | S5: 20 | T5: =R5*S5 -> 0
A6: ='1'!A6:B6 -> Comm & Fee | C6: 25 | D6: ='1'!D6:E6 -> Cash Expense | F6: =F40 -> 0 | H6: ='1'!H6 -> DINEX | L6: =SUM(I6:K6) -> 0 | N6: 3 | P6: ='2'!Q6 -> 0 | R6: =Q6-P6 -> 0 | S6: 20 | T6: =R6*S6 -> 0
A7: ='1'!A7:B7 -> Sales Tax | D7: ='1'!D7:E7 -> Check Purchases | F7: =C53 -> 0 | H7: ='1'!H7 -> INTERMEX | I7: 9112.39 | J7: 192.5 | L7: =SUM(I7:K7) -> 9304.89 | N7: 4 | P7: ='2'!Q7 -> 0 | R7: =Q7-P7 -> 0 | S7: 10 | T7: =R7*S7 -> 0
A8: ='1'!A8:B8 -> Money Transfers | C8: =L14 -> 14755.09 | D8: ='1'!D8:E8 -> Check Expense | F8: =F47 -> 0 | H8: ='1'!H8 -> SIGUE | L8: =SUM(I8:K8) -> 0 | N8: 5 | P8: ='2'!Q8 -> 0 | R8: =Q8-P8 -> 0 | S8: 10 | T8: =R8*S8 -> 0
A9: ='1'!A9:B9 -> Lottery Sales | C9: =S52 -> 0 | D9: ='1'!D9:E9 -> Lotto Paid Out | H9: ='1'!H9 -> AFEX | L9: =SUM(I9:K9) -> 0 | N9: 6 | P9: ='2'!Q9 -> 0 | R9: =Q9-P9 -> 0 | S9: 20 | T9: =R9*S9 -> 0
A10: ='1'!A10:B10 -> Lotto Net Sales | D10: ='1'!D10:E10 -> Lottery Paid Out | H10: ='1'!H10 -> MONEYGRAM | L10: =SUM(I10:K10) -> 0 | N10: 7 | P10: ='2'!Q10 -> 0 | R10: =Q10-P10 -> 0 | S10: 20 | T10: =R10*S10 -> 0
A11: ='1'!A11:B11 -> PhoneCard | D11: ='1'!D11:E11 -> ATM Drop | H11: ='1'!H11 -> BARRI | I11: 1310 | J11: 20 | L11: =SUM(I11:K11) -> 1330 | N11: 8 | P11: ='2'!Q11 -> 0 | R11: =Q11-P11 -> 0 | S11: 20 | T11: =R11*S11 -> 0
A12: ='1'!A12:B12 -> Boss Revolution | D12: ='1'!D12:E12 -> Credit Card | H12: ='1'!H12 -> MAXI | I12: 4006.2 | J12: 114 | L12: =SUM(I12:K12) -> 4120.2 | N12: 9 | P12: ='2'!Q12 -> 0 | R12: =Q12-P12 -> 0 | S12: 10 | T12: =R12*S12 -> 0
A13: ='1'!A13:B13 -> Bill Payment | D13: ='1'!D13:E13 -> Outside Cash & Drops | F13: =L40 -> 14755 | H13: ='1'!H13 -> AMIGO SIN PIN | L13: =SUM(I13:K13) -> 0 | N13: 10 | P13: ='2'!Q13 -> 0 | R13: =Q13-P13 -> 0 | S13: 10 | T13: =R13*S13 -> 0
A14: ='1'!A14:B14 -> VidaPay | D14: ='1'!D14:E14 -> Cash Deposit | H14: TOTAL | I14: =SUM(I6:I13) -> 14428.59 | J14: =SUM(J6:J13) -> 326.5 | K14: =SUM(K6:K13) -> 0 | L14: =SUM(L6:M13) -> 14755.09 | N14: 11 | P14: ='2'!Q14 -> 0 | R14: =Q14-P14 -> 0 | S14: 5 | T14: =R14*S14 -> 0
A15: ='1'!A15:B15 -> Boost Epay | D15: ='1'!D15:E15 -> Money Gram Payment | N15: 12 | P15: ='2'!Q15 -> 0 | R15: =Q15-P15 -> 0 | S15: 5 | T15: =R15*S15 -> 0
A16: ='1'!A16:B16 -> Epay | D16: ='1'!D16:E16 -> Vigo Payment | N16: 13 | P16: ='2'!Q16 -> 0 | R16: =Q16-P16 -> 0 | S16: 5 | T16: =R16*S16 -> 0
A17: ='1'!A17:B17 -> Check Cashing Fees | C17: 336.23 | D17: ='1'!D17:E17 -> Ria Payment | N17: 14 | P17: ='2'!Q17 -> 0 | R17: =Q17-P17 -> 0 | S17: 5 | T17: =R17*S17 -> 0
A18: ='1'!A18:B18 -> Money Order | C18: 6003.17 | D18: ='1'!D18:E18 -> Checks Deposit | F18: =J25 -> 47013.95 | H18: CHECK DEPOSITS | K18: DROPS | L18: AMOUNT | M18: TIME | N18: 15 | P18: ='2'!Q18 -> 0 | R18: =Q18-P18 -> 0 | S18: 5 | T18: =R18*S18 -> 0
A19: ='1'!A19:B19 -> Return Check Paid | C19: =F33 -> 0 | D19: ='1'!D19:E19 -> Safe Balance | F19: 48991 | H19: CHECK DEPOSITS TO BANK | J19: AMOUNT | K19: 1 | L19: 3850 | M19: 0.55347222 | N19: 16 | P19: ='2'!Q19 -> 0 | R19: =Q19-P19 -> 0 | S19: 5 | T19: =R19*S19 -> 0
A20: ='1'!A20:B20 -> Forward Balance | C20: ='2'!F19+'2'!F13 -> 73871 | D20: ='1'!D20:E20 -> Payroll Expense | F20: =J40 -> 0 | H20: NIZARI | J20: 47013.95 | K20: 2 | L20: 5630 | M20: 0.625 | N20: 17 | P20: ='2'!Q20 -> 0 | R20: =Q20-P20 -> 0 | S20: 5 | T20: =R20*S20 -> 0
A21: ='1'!A21:B21 -> Cash From Bank | C21: 36000 | D21: ='1'!D21:E21 -> Other Cash Out | F21: =M53 -> 20231 | K21: 3 | L21: 2040 | M21: 0.83055556 | N21: 18 | P21: ='2'!Q21 -> 0 | R21: =Q21-P21 -> 0 | S21: 5 | T21: =R21*S21 -> 0
A22: ='1'!A22:B22 -> Other Cash In | C22: =J53 -> 0 | D22: TOTAL PAYOUTS | F22: =SUM(F5:F21)-F7-F8 -> 130990.95 | K22: 4 | L22: 2040 | M22: 0.83263889 | N22: 19 | P22: ='2'!Q22 -> 0 | R22: =Q22-P22 -> 0 | S22: 5 | T22: =R22*S22 -> 0
A23: ='1'!A23:B23 -> Rebates & Commissions | C23: =F53 -> 0 | D23: Inside Over - (Short) | F23: =(F11+F14+F15+F16+F17+F18+F19+F20+F21+F5+F6)-(C17+C19+C20+C21+C22+C23) -> 6028.72 | K23: 5 | L23: 1195 | M23: 0.875 | N23: 20 | P23: ='2'!Q23 -> 0 | R23: =Q23-P23 -> 0 | S23: 5 | T23: =R23*S23 -> 0
A24: TOTAL RECEIPTS | C24: =SUM(C5:C23) -> 130990.49 | D24: Over All Over - (Short) | F24: =SUM(F22-C24) -> 0.46 | K24: 6 | N24: 21 | P24: ='2'!Q24 -> 0 | R24: =Q24-P24 -> 0 | S24: 5 | T24: =R24*S24 -> 0
A25: Out Side Over - (Short) | C25: =(F9+F10+F12+F13)-(C5+C6+C7+C8+C9+C10+C11+C12+C13+C14+C15+C16+C18) -> -6028.26 | H25: TOTAL | J25: =SUM(J20:J24) -> 47013.95 | K25: 7 | N25: 22 | P25: ='2'!Q25 -> 0 | R25: =Q25-P25 -> 0 | S25: 5 | T25: =R25*S25 -> 0
A26: Cash Purchases | D26: Return Check Paid | K26: 8 | N26: 23 | P26: ='2'!Q26 -> 0 | R26: =Q26-P26 -> 0 | S26: 3 | T26: =R26*S26 -> 0
A27: Description | C27: Amount | D27: Description | F27: Amount | K27: 9 | N27: 24 | P27: ='2'!Q27 -> 0 | R27: =Q27-P27 -> 0 | S27: 3 | T27: =R27*S27 -> 0
H28: CASH PAYROLL EXPENSE | K28: 10 | N28: 25 | P28: ='2'!Q28 -> 0 | R28: =Q28-P28 -> 0 | S28: 2 | T28: =R28*S28 -> 0
H29: CASH PAYROLL PAID TO | J29: AMOUNT | K29: 11 | N29: 26 | P29: ='2'!Q29 -> 0 | R29: =Q29-P29 -> 0 | S29: 5 | T29: =R29*S29 -> 0
K30: 12 | N30: 27 | P30: ='2'!Q30 -> 0 | R30: =Q30-P30 -> 0 | S30: 3 | T30: =R30*S30 -> 0
K31: 13 | N31: 28 | P31: ='2'!Q31 -> 0 | R31: =Q31-P31 -> 0 | S31: 3 | T31: =R31*S31 -> 0
K32: 14 | N32: 29 | P32: ='2'!Q32 -> 0 | R32: =Q32-P32 -> 0 | S32: 2 | T32: =R32*S32 -> 0
D33: Total | F33: =SUM(F28:F32) -> 0 | K33: 15 | N33: 30 | P33: ='2'!Q33 -> 0 | R33: =Q33-P33 -> 0 | S33: 2 | T33: =R33*S33 -> 0
D34: Cash Expense | K34: 16 | N34: 31 | P34: ='2'!Q34 -> 0 | R34: =Q34-P34 -> 0 | S34: 2 | T34: =R34*S34 -> 0
D35: Description | F35: Amount | K35: 17 | N35: 32 | P35: ='2'!Q35 -> 0 | R35: =Q35-P35 -> 0 | S35: 2 | T35: =R35*S35 -> 0
K36: 18 | N36: 33 | P36: ='2'!Q36 -> 0 | R36: =Q36-P36 -> 0 | S36: 2 | T36: =R36*S36 -> 0
K37: 19 | N37: 34 | P37: ='2'!Q37 -> 0 | R37: =Q37-P37 -> 0 | S37: 1 | T37: =R37*S37 -> 0
K38: 20 | N38: 35 | P38: ='2'!Q38 -> 0 | R38: =Q38-P38 -> 0 | S38: 1 | T38: =R38*S38 -> 0
K39: 21 | N39: 36 | P39: ='2'!Q39 -> 0 | R39: =Q39-P39 -> 0 | S39: 2 | T39: =R39*S39 -> 0
A40: Total | C40: =SUM(C28:C39) -> 0 | D40: Total | F40: =SUM(F36:F39) -> 0 | H40: TOTAL | J40: =SUM(J30:J39) -> 0 | K40: TOTAL | L40: =SUM(L19:L39) -> 14755 | N40: 37 | P40: ='2'!Q40 -> 0 | R40: =Q40-P40 -> 0 | S40: 2 | T40: =R40*S40 -> 0
N41: 38 | P41: ='2'!Q41 -> 0 | R41: =Q41-P41 -> 0 | S41: 2 | T41: =R41*S41 -> 0
A42: Check Purchases | D42: Check Expenses | N42: 39 | P42: ='2'!Q42 -> 0 | R42: =Q42-P42 -> 0 | S42: 1 | T42: =R42*S42 -> 0
A43: Description | B43: Check | C43: Amount | D43: Description | E43: Check | F43: Amount | H43: CASH IN | K43: CASH OUT TO OTHER | N43: 40 | P43: ='2'!Q43 -> 0 | R43: =Q43-P43 -> 0 | S43: 1 | T43: =R43*S43 -> 0
H44: CASH IN FROM | J44: AMOUNT | K44: OTHER CASH OUT | M44: AMOUNT | N44: 41 | P44: ='2'!Q44 -> 0 | R44: =Q44-P44 -> 0 | S44: 10 | T44: =R44*S44 -> 0
K45: LED Logistics LLC (20 Checks) | M45: 20231 | N45: 42 | P45: ='2'!Q45 -> 0 | R45: =Q45-P45 -> 0 | S45: 1 | T45: =R45*S45 -> 0
N46: 43 | P46: ='2'!Q46 -> 0 | R46: =Q46-P46 -> 0 | S46: 1 | T46: =R46*S46 -> 0
D47: Total | F47: =SUM(F44:F46) -> 0 | N47: 44 | P47: ='2'!Q47 -> 0 | R47: =Q47-P47 -> 0 | S47: 1 | T47: =R47*S47 -> 0
D48: Rebates and Commissions | N48: 45 | P48: ='2'!Q48 -> 0 | R48: =Q48-P48 -> 0 | S48: 1 | T48: =R48*S48 -> 0
D49: Description | F49: Amount | N49: 46 | P49: ='2'!Q49 -> 0 | R49: =Q49-P49 -> 0 | S49: 1 | T49: =R49*S49 -> 0
N50: 47 | P50: ='2'!Q50 -> 0 | R50: =Q50-P50 -> 0 | S50: 1 | T50: =R50*S50 -> 0
N51: 48 | P51: ='2'!Q51 -> 0 | R51: =Q51-P51 -> 0 | S51: 1 | T51: =R51*S51 -> 0
O52: Total Lottery Sale | S52: =SUM(T4:T51) -> 0
A53: Total | C53: =SUM(C44:C52) -> 0 | D53: Total | F53: =SUM(F50:F52) -> 0 | H53: TOTAL | J53: =SUM(J45:J52) -> 0 | K53: TOTAL | M53: =SUM(M45:M52) -> 20231

Sheet 4
A1: ='1'!A1:F1 -> DINERO EXPRESS #8 (512) 8015655 | H1: =A1 -> DINERO EXPRESS #8 (512) 8015655 | M1: DATE
A2: Daily Report | D2: Date: | F2: ='3'!F2+1 -> 3 | H2: OTHER REPORTS | M2: =F2 -> 3 | O2: Lottery Sale
D3: Day: | M3: =F3 -> 0 | O3: Game # | P3: Open | Q3: Close | R3: Tic.Sold | S3: $ Value | T3: T. Sale
A4: Reciepts | C4: Amount | D4: Disbursments | F4: Amount | H4: MONEY TRANSFER | N4: 1 | P4: ='3'!Q4 -> 0 | R4: =Q4-P4 -> 0 | S4: 50 | T4: =R4*S4 -> 0
A5: ='1'!A5:B5 -> Taxable Sale | C5: 10 | D5: ='1'!D5:E5 -> Cash Purchases | F5: =C40 -> 0 | H5: Company | I5: Amount | J5: Fees | K5: Commission | L5: Individual Total Amount | N5: 2 | P5: ='3'!Q5 -> 0 | R5: =Q5-P5 -> 0 | S5: 20 | T5: =R5*S5 -> 0
A6: ='1'!A6:B6 -> Comm & Fee | C6: 18 | D6: ='1'!D6:E6 -> Cash Expense | F6: =F40 -> 0 | H6: ='1'!H6 -> DINEX | L6: =SUM(I6:K6) -> 0 | N6: 3 | P6: ='3'!Q6 -> 0 | R6: =Q6-P6 -> 0 | S6: 20 | T6: =R6*S6 -> 0
A7: ='1'!A7:B7 -> Sales Tax | D7: ='1'!D7:E7 -> Check Purchases | F7: =C53 -> 0 | H7: ='1'!H7 -> INTERMEX | I7: 4559.68 | J7: 127 | L7: =SUM(I7:K7) -> 4686.68 | N7: 4 | P7: ='3'!Q7 -> 0 | R7: =Q7-P7 -> 0 | S7: 10 | T7: =R7*S7 -> 0
A8: ='1'!A8:B8 -> Money Transfers | C8: =L14 -> 9691.78 | D8: ='1'!D8:E8 -> Check Expense | F8: =F47 -> 0 | H8: ='1'!H8 -> SIGUE | L8: =SUM(I8:K8) -> 0 | N8: 5 | P8: ='3'!Q8 -> 0 | R8: =Q8-P8 -> 0 | S8: 10 | T8: =R8*S8 -> 0
A9: ='1'!A9:B9 -> Lottery Sales | C9: =S52 -> 0 | D9: ='1'!D9:E9 -> Lotto Paid Out | H9: ='1'!H9 -> AFEX | L9: =SUM(I9:K9) -> 0 | N9: 6 | P9: ='3'!Q9 -> 0 | R9: =Q9-P9 -> 0 | S9: 20 | T9: =R9*S9 -> 0
A10: ='1'!A10:B10 -> Lotto Net Sales | D10: ='1'!D10:E10 -> Lottery Paid Out | H10: ='1'!H10 -> MONEYGRAM | L10: =SUM(I10:K10) -> 0 | N10: 7 | P10: ='3'!Q10 -> 0 | R10: =Q10-P10 -> 0 | S10: 20 | T10: =R10*S10 -> 0
A11: ='1'!A11:B11 -> PhoneCard | D11: ='1'!D11:E11 -> ATM Drop | H11: ='1'!H11 -> BARRI | I11: 1093 | J11: 30 | L11: =SUM(I11:K11) -> 1123 | N11: 8 | P11: ='3'!Q11 -> 0 | R11: =Q11-P11 -> 0 | S11: 20 | T11: =R11*S11 -> 0
A12: ='1'!A12:B12 -> Boss Revolution | D12: ='1'!D12:E12 -> Credit Card | H12: ='1'!H12 -> MAXI | I12: 3769.1 | J12: 113 | L12: =SUM(I12:K12) -> 3882.1 | N12: 9 | P12: ='3'!Q12 -> 0 | R12: =Q12-P12 -> 0 | S12: 10 | T12: =R12*S12 -> 0
A13: ='1'!A13:B13 -> Bill Payment | D13: ='1'!D13:E13 -> Outside Cash & Drops | F13: =L40 -> 9596 | H13: ='1'!H13 -> AMIGO SIN PIN | L13: =SUM(I13:K13) -> 0 | N13: 10 | P13: ='3'!Q13 -> 0 | R13: =Q13-P13 -> 0 | S13: 10 | T13: =R13*S13 -> 0
A14: ='1'!A14:B14 -> VidaPay | D14: ='1'!D14:E14 -> Cash Deposit | H14: TOTAL | I14: =SUM(I6:I13) -> 9421.78 | J14: =SUM(J6:J13) -> 270 | K14: =SUM(K6:K13) -> 0 | L14: =SUM(L6:M13) -> 9691.78 | N14: 11 | P14: ='3'!Q14 -> 0 | R14: =Q14-P14 -> 0 | S14: 5 | T14: =R14*S14 -> 0
A15: ='1'!A15:B15 -> Boost Epay | D15: ='1'!D15:E15 -> Money Gram Payment | N15: 12 | P15: ='3'!Q15 -> 0 | R15: =Q15-P15 -> 0 | S15: 5 | T15: =R15*S15 -> 0
A16: ='1'!A16:B16 -> Epay | D16: ='1'!D16:E16 -> Vigo Payment | N16: 13 | P16: ='3'!Q16 -> 0 | R16: =Q16-P16 -> 0 | S16: 5 | T16: =R16*S16 -> 0
A17: ='1'!A17:B17 -> Check Cashing Fees | C17: 290.09 | D17: ='1'!D17:E17 -> Ria Payment | N17: 14 | P17: ='3'!Q17 -> 0 | R17: =Q17-P17 -> 0 | S17: 5 | T17: =R17*S17 -> 0
A18: ='1'!A18:B18 -> Money Order | C18: 4425 | D18: ='1'!D18:E18 -> Checks Deposit | F18: =J25 -> 49918.03 | H18: CHECK DEPOSITS | K18: DROPS | L18: AMOUNT | M18: TIME | N18: 15 | P18: ='3'!Q18 -> 0 | R18: =Q18-P18 -> 0 | S18: 5 | T18: =R18*S18 -> 0
A19: ='1'!A19:B19 -> Return Check Paid | C19: =F33 -> 0 | D19: ='1'!D19:E19 -> Safe Balance | F19: 54870 | H19: CHECK DEPOSITS TO BANK | J19: AMOUNT | K19: 1 | L19: 2850 | M19: 12:39PM | N19: 16 | P19: ='3'!Q19 -> 0 | R19: =Q19-P19 -> 0 | S19: 5 | T19: =R19*S19 -> 0
A20: ='1'!A20:B20 -> Forward Balance | C20: ='3'!F19+'3'!F13 -> 63746 | D20: ='1'!D20:E20 -> Payroll Expense | F20: =J40 -> 0 | H20: NIZARI (40 Checks) | J20: 49918.03 | K20: 2 | L20: 100 | M20: 1:37PM | N20: 17 | P20: ='3'!Q20 -> 0 | R20: =Q20-P20 -> 0 | S20: 5 | T20: =R20*S20 -> 0
A21: ='1'!A21:B21 -> Cash From Bank | C21: 43500 | D21: ='1'!D21:E21 -> Other Cash Out | F21: =M53 -> 8130 | K21: 3 | L21: 100 | M21: 1:37PM | N21: 18 | P21: ='3'!Q21 -> 0 | R21: =Q21-P21 -> 0 | S21: 5 | T21: =R21*S21 -> 0
A22: ='1'!A22:B22 -> Other Cash In | C22: =J53 -> 833 | D22: TOTAL PAYOUTS | F22: =SUM(F5:F21)-F7-F8 -> 122514.03 | K22: 4 | L22: 100 | M22: 1:37PM | N22: 19 | P22: ='3'!Q22 -> 0 | R22: =Q22-P22 -> 0 | S22: 5 | T22: =R22*S22 -> 0
A23: ='1'!A23:B23 -> Rebates & Commissions | C23: =F53 -> 0 | D23: Inside Over - (Short) | F23: =(F11+F14+F15+F16+F17+F18+F19+F20+F21+F5+F6)-(C17+C19+C20+C21+C22+C23) -> 4548.94 | K23: 5 | L23: 2490 | M23: 3:13PM | N23: 20 | P23: ='3'!Q23 -> 0 | R23: =Q23-P23 -> 0 | S23: 5 | T23: =R23*S23 -> 0
A24: TOTAL RECEIPTS | C24: =SUM(C5:C23) -> 122513.87 | D24: Over All Over - (Short) | F24: =SUM(F22-C24) -> 0.16 | K24: 6 | L24: 1690 | M24: 3:35PM | N24: 21 | P24: ='3'!Q24 -> 0 | R24: =Q24-P24 -> 0 | S24: 5 | T24: =R24*S24 -> 0
A25: Out Side Over - (Short) | C25: =(F9+F10+F12+F13)-(C5+C6+C7+C8+C9+C10+C11+C12+C13+C14+C15+C16+C18) -> -4548.78 | H25: TOTAL | J25: =SUM(J20:J24) -> 49918.03 | K25: 7 | L25: 2266 | M25: 8:34PM | N25: 22 | P25: ='3'!Q25 -> 0 | R25: =Q25-P25 -> 0 | S25: 5 | T25: =R25*S25 -> 0
A26: Cash Purchases | D26: Return Check Paid | K26: 8 | N26: 23 | P26: ='3'!Q26 -> 0 | R26: =Q26-P26 -> 0 | S26: 3 | T26: =R26*S26 -> 0
A27: Description | C27: Amount | D27: Description | F27: Amount | K27: 9 | N27: 24 | P27: ='3'!Q27 -> 0 | R27: =Q27-P27 -> 0 | S27: 3 | T27: =R27*S27 -> 0
H28: CASH PAYROLL EXPENSE | K28: 10 | N28: 25 | P28: ='3'!Q28 -> 0 | R28: =Q28-P28 -> 0 | S28: 2 | T28: =R28*S28 -> 0
H29: CASH PAYROLL PAID TO | J29: AMOUNT | K29: 11 | N29: 26 | P29: ='3'!Q29 -> 0 | R29: =Q29-P29 -> 0 | S29: 5 | T29: =R29*S29 -> 0
K30: 12 | N30: 27 | P30: ='3'!Q30 -> 0 | R30: =Q30-P30 -> 0 | S30: 3 | T30: =R30*S30 -> 0
K31: 13 | N31: 28 | P31: ='3'!Q31 -> 0 | R31: =Q31-P31 -> 0 | S31: 3 | T31: =R31*S31 -> 0
K32: 14 | N32: 29 | P32: ='3'!Q32 -> 0 | R32: =Q32-P32 -> 0 | S32: 2 | T32: =R32*S32 -> 0
D33: Total | F33: =SUM(F28:F32) -> 0 | K33: 15 | N33: 30 | P33: ='3'!Q33 -> 0 | R33: =Q33-P33 -> 0 | S33: 2 | T33: =R33*S33 -> 0
D34: Cash Expense | K34: 16 | N34: 31 | P34: ='3'!Q34 -> 0 | R34: =Q34-P34 -> 0 | S34: 2 | T34: =R34*S34 -> 0
D35: Description | F35: Amount | K35: 17 | N35: 32 | P35: ='3'!Q35 -> 0 | R35: =Q35-P35 -> 0 | S35: 2 | T35: =R35*S35 -> 0
K36: 18 | N36: 33 | P36: ='3'!Q36 -> 0 | R36: =Q36-P36 -> 0 | S36: 2 | T36: =R36*S36 -> 0
K37: 19 | N37: 34 | P37: ='3'!Q37 -> 0 | R37: =Q37-P37 -> 0 | S37: 1 | T37: =R37*S37 -> 0
K38: 20 | N38: 35 | P38: ='3'!Q38 -> 0 | R38: =Q38-P38 -> 0 | S38: 1 | T38: =R38*S38 -> 0
K39: 21 | N39: 36 | P39: ='3'!Q39 -> 0 | R39: =Q39-P39 -> 0 | S39: 2 | T39: =R39*S39 -> 0
A40: Total | C40: =SUM(C28:C39) -> 0 | D40: Total | F40: =SUM(F36:F39) -> 0 | H40: TOTAL | J40: =SUM(J30:J39) -> 0 | K40: TOTAL | L40: =SUM(L19:L39) -> 9596 | N40: 37 | P40: ='3'!Q40 -> 0 | R40: =Q40-P40 -> 0 | S40: 2 | T40: =R40*S40 -> 0
N41: 38 | P41: ='3'!Q41 -> 0 | R41: =Q41-P41 -> 0 | S41: 2 | T41: =R41*S41 -> 0
A42: Check Purchases | D42: Check Expenses | N42: 39 | P42: ='3'!Q42 -> 0 | R42: =Q42-P42 -> 0 | S42: 1 | T42: =R42*S42 -> 0
A43: Description | B43: Check | C43: Amount | D43: Description | E43: Check | F43: Amount | H43: CASH IN | K43: CASH OUT TO OTHER | N43: 40 | P43: ='3'!Q43 -> 0 | R43: =Q43-P43 -> 0 | S43: 1 | T43: =R43*S43 -> 0
H44: CASH IN FROM | J44: AMOUNT | K44: OTHER CASH OUT | M44: AMOUNT | N44: 41 | P44: ='3'!Q44 -> 0 | R44: =Q44-P44 -> 0 | S44: 10 | T44: =R44*S44 -> 0
H45: Side Expense from 1st till today | J45: 833 | K45: LED Logistics LLC (4 Checks) | M45: 8100 | N45: 42 | P45: ='3'!Q45 -> 0 | R45: =Q45-P45 -> 0 | S45: 1 | T45: =R45*S45 -> 0
K46: 4/1/2026 Coin to Cash | M46: 30 | N46: 43 | P46: ='3'!Q46 -> 0 | R46: =Q46-P46 -> 0 | S46: 1 | T46: =R46*S46 -> 0
D47: Total | F47: =SUM(F44:F46) -> 0 | N47: 44 | P47: ='3'!Q47 -> 0 | R47: =Q47-P47 -> 0 | S47: 1 | T47: =R47*S47 -> 0
D48: Rebates and Commissions | N48: 45 | P48: ='3'!Q48 -> 0 | R48: =Q48-P48 -> 0 | S48: 1 | T48: =R48*S48 -> 0
D49: Description | F49: Amount | N49: 46 | P49: ='3'!Q49 -> 0 | R49: =Q49-P49 -> 0 | S49: 1 | T49: =R49*S49 -> 0
N50: 47 | P50: ='3'!Q50 -> 0 | R50: =Q50-P50 -> 0 | S50: 1 | T50: =R50*S50 -> 0
N51: 48 | P51: ='3'!Q51 -> 0 | R51: =Q51-P51 -> 0 | S51: 1 | T51: =R51*S51 -> 0
O52: Total Lottery Sale | S52: =SUM(T4:T51) -> 0
A53: Total | C53: =SUM(C44:C52) -> 0 | D53: Total | F53: =SUM(F50:F52) -> 0 | H53: TOTAL | J53: =SUM(J45:J52) -> 833 | K53: TOTAL | M53: =SUM(M45:M52) -> 8130

Sheet 5
A1: ='1'!A1:F1 -> DINERO EXPRESS #8 (512) 8015655 | H1: =A1 -> DINERO EXPRESS #8 (512) 8015655 | M1: DATE
A2: Daily Report | D2: Date: | F2: ='4'!F2+1 -> 4 | H2: OTHER REPORTS | M2: =F2 -> 4 | O2: Lottery Sale
D3: Day: | M3: =F3 -> 0 | O3: Game # | P3: Open | Q3: Close | R3: Tic.Sold | S3: $ Value | T3: T. Sale
A4: Reciepts | C4: Amount | D4: Disbursments | F4: Amount | H4: MONEY TRANSFER | N4: 1 | P4: ='4'!Q4 -> 0 | R4: =Q4-P4 -> 0 | S4: 50 | T4: =R4*S4 -> 0
A5: ='1'!A5:B5 -> Taxable Sale | C5: 36 | D5: ='1'!D5:E5 -> Cash Purchases | F5: =C40 -> 0 | H5: Company | I5: Amount | J5: Fees | K5: Commission | L5: Individual Total Amount | N5: 2 | P5: ='4'!Q5 -> 0 | R5: =Q5-P5 -> 0 | S5: 20 | T5: =R5*S5 -> 0
A6: ='1'!A6:B6 -> Comm & Fee | C6: 17 | D6: ='1'!D6:E6 -> Cash Expense | F6: =F40 -> 0 | H6: ='1'!H6 -> DINEX | L6: =SUM(I6:K6) -> 0 | N6: 3 | P6: ='4'!Q6 -> 0 | R6: =Q6-P6 -> 0 | S6: 20 | T6: =R6*S6 -> 0
A7: ='1'!A7:B7 -> Sales Tax | D7: ='1'!D7:E7 -> Check Purchases | F7: =C53 -> 0 | H7: ='1'!H7 -> INTERMEX | I7: 18292.7 | J7: 309.03 | L7: =SUM(I7:K7) -> 18601.73 | N7: 4 | P7: ='4'!Q7 -> 0 | R7: =Q7-P7 -> 0 | S7: 10 | T7: =R7*S7 -> 0
A8: ='1'!A8:B8 -> Money Transfers | C8: =L14 -> 23323.32 | D8: ='1'!D8:E8 -> Check Expense | F8: =F47 -> 0 | H8: ='1'!H8 -> SIGUE | L8: =SUM(I8:K8) -> 0 | N8: 5 | P8: ='4'!Q8 -> 0 | R8: =Q8-P8 -> 0 | S8: 10 | T8: =R8*S8 -> 0
A9: ='1'!A9:B9 -> Lottery Sales | C9: =S52 -> 0 | D9: ='1'!D9:E9 -> Lotto Paid Out | H9: ='1'!H9 -> AFEX | L9: =SUM(I9:K9) -> 0 | N9: 6 | P9: ='4'!Q9 -> 0 | R9: =Q9-P9 -> 0 | S9: 20 | T9: =R9*S9 -> 0
A10: ='1'!A10:B10 -> Lotto Net Sales | D10: ='1'!D10:E10 -> Lottery Paid Out | H10: ='1'!H10 -> MONEYGRAM | L10: =SUM(I10:K10) -> 0 | N10: 7 | P10: ='4'!Q10 -> 0 | R10: =Q10-P10 -> 0 | S10: 20 | T10: =R10*S10 -> 0
A11: ='1'!A11:B11 -> PhoneCard | D11: ='1'!D11:E11 -> ATM Drop | H11: ='1'!H11 -> BARRI | I11: 2095.75 | J11: 26 | L11: =SUM(I11:K11) -> 2121.75 | N11: 8 | P11: ='4'!Q11 -> 0 | R11: =Q11-P11 -> 0 | S11: 20 | T11: =R11*S11 -> 0
A12: ='1'!A12:B12 -> Boss Revolution | D12: ='1'!D12:E12 -> Credit Card | H12: ='1'!H12 -> MAXI | I12: 2535.84 | J12: 64 | L12: =SUM(I12:K12) -> 2599.84 | N12: 9 | P12: ='4'!Q12 -> 0 | R12: =Q12-P12 -> 0 | S12: 10 | T12: =R12*S12 -> 0
A13: ='1'!A13:B13 -> Bill Payment | D13: ='1'!D13:E13 -> Outside Cash & Drops | F13: =L40 -> 23327 | H13: ='1'!H13 -> AMIGO SIN PIN | L13: =SUM(I13:K13) -> 0 | N13: 10 | P13: ='4'!Q13 -> 0 | R13: =Q13-P13 -> 0 | S13: 10 | T13: =R13*S13 -> 0
A14: ='1'!A14:B14 -> VidaPay | D14: ='1'!D14:E14 -> Cash Deposit | H14: TOTAL | I14: =SUM(I6:I13) -> 22924.29 | J14: =SUM(J6:J13) -> 399.03 | K14: =SUM(K6:K13) -> 0 | L14: =SUM(L6:M13) -> 23323.32 | N14: 11 | P14: ='4'!Q14 -> 0 | R14: =Q14-P14 -> 0 | S14: 5 | T14: =R14*S14 -> 0
A15: ='1'!A15:B15 -> Boost Epay | D15: ='1'!D15:E15 -> Money Gram Payment | N15: 12 | P15: ='4'!Q15 -> 0 | R15: =Q15-P15 -> 0 | S15: 5 | T15: =R15*S15 -> 0
A16: ='1'!A16:B16 -> Epay | D16: ='1'!D16:E16 -> Vigo Payment | N16: 13 | P16: ='4'!Q16 -> 0 | R16: =Q16-P16 -> 0 | S16: 5 | T16: =R16*S16 -> 0
A17: ='1'!A17:B17 -> Check Cashing Fees | C17: 99.95 | D17: ='1'!D17:E17 -> Ria Payment | N17: 14 | P17: ='4'!Q17 -> 0 | R17: =Q17-P17 -> 0 | S17: 5 | T17: =R17*S17 -> 0
A18: ='1'!A18:B18 -> Money Order | C18: 3395 | D18: ='1'!D18:E18 -> Checks Deposit | F18: =J25 -> 23499.42 | H18: CHECK DEPOSITS | K18: DROPS | L18: AMOUNT | M18: TIME | N18: 15 | P18: ='4'!Q18 -> 0 | R18: =Q18-P18 -> 0 | S18: 5 | T18: =R18*S18 -> 0
A19: ='1'!A19:B19 -> Return Check Paid | C19: =F33 -> 0 | D19: ='1'!D19:E19 -> Safe Balance | F19: 47608 | H19: CHECK DEPOSITS TO BANK | J19: AMOUNT | K19: 1 | L19: 3000 | M19: 10:59AM | N19: 16 | P19: ='4'!Q19 -> 0 | R19: =Q19-P19 -> 0 | S19: 5 | T19: =R19*S19 -> 0
A20: ='1'!A20:B20 -> Forward Balance | C20: ='4'!F19+'4'!F13 -> 64466 | D20: ='1'!D20:E20 -> Payroll Expense | F20: =J40 -> 0 | H20: NIZARI (25 Checks) | J20: 23499.42 | K20: 2 | L20: 9850 | M20: 4:38PM | N20: 17 | P20: ='4'!Q20 -> 0 | R20: =Q20-P20 -> 0 | S20: 5 | T20: =R20*S20 -> 0
A21: ='1'!A21:B21 -> Cash From Bank | D21: ='1'!D21:E21 -> Other Cash Out | F21: =M53 -> 538 | K21: 3 | L21: 9941 | M21: 8:50PM | N21: 18 | P21: ='4'!Q21 -> 0 | R21: =Q21-P21 -> 0 | S21: 5 | T21: =R21*S21 -> 0
A22: ='1'!A22:B22 -> Other Cash In | C22: =J53 -> 3635 | D22: TOTAL PAYOUTS | F22: =SUM(F5:F21)-F7-F8 -> 94972.42 | K22: 4 | L22: 536 | M22: 9:02PM | N22: 19 | P22: ='4'!Q22 -> 0 | R22: =Q22-P22 -> 0 | S22: 5 | T22: =R22*S22 -> 0
A23: ='1'!A23:B23 -> Rebates & Commissions | C23: =F53 -> 0 | D23: Inside Over - (Short) | F23: =(F11+F14+F15+F16+F17+F18+F19+F20+F21+F5+F6)-(C17+C19+C20+C21+C22+C23) -> 3444.47 | K23: 5 | N23: 20 | P23: ='4'!Q23 -> 0 | R23: =Q23-P23 -> 0 | S23: 5 | T23: =R23*S23 -> 0
A24: TOTAL RECEIPTS | C24: =SUM(C5:C23) -> 94972.27 | D24: Over All Over - (Short) | F24: =SUM(F22-C24) -> 0.15 | K24: 6 | N24: 21 | P24: ='4'!Q24 -> 0 | R24: =Q24-P24 -> 0 | S24: 5 | T24: =R24*S24 -> 0
A25: Out Side Over - (Short) | C25: =(F9+F10+F12+F13)-(C5+C6+C7+C8+C9+C10+C11+C12+C13+C14+C15+C16+C18) -> -3444.32 | H25: TOTAL | J25: =SUM(J20:J24) -> 23499.42 | K25: 7 | N25: 22 | P25: ='4'!Q25 -> 0 | R25: =Q25-P25 -> 0 | S25: 5 | T25: =R25*S25 -> 0
A26: Cash Purchases | D26: Return Check Paid | K26: 8 | N26: 23 | P26: ='4'!Q26 -> 0 | R26: =Q26-P26 -> 0 | S26: 3 | T26: =R26*S26 -> 0
A27: Description | C27: Amount | D27: Description | F27: Amount | K27: 9 | N27: 24 | P27: ='4'!Q27 -> 0 | R27: =Q27-P27 -> 0 | S27: 3 | T27: =R27*S27 -> 0
H28: CASH PAYROLL EXPENSE | K28: 10 | N28: 25 | P28: ='4'!Q28 -> 0 | R28: =Q28-P28 -> 0 | S28: 2 | T28: =R28*S28 -> 0
H29: CASH PAYROLL PAID TO | J29: AMOUNT | K29: 11 | N29: 26 | P29: ='4'!Q29 -> 0 | R29: =Q29-P29 -> 0 | S29: 5 | T29: =R29*S29 -> 0
K30: 12 | N30: 27 | P30: ='4'!Q30 -> 0 | R30: =Q30-P30 -> 0 | S30: 3 | T30: =R30*S30 -> 0
K31: 13 | N31: 28 | P31: ='4'!Q31 -> 0 | R31: =Q31-P31 -> 0 | S31: 3 | T31: =R31*S31 -> 0
K32: 14 | N32: 29 | P32: ='4'!Q32 -> 0 | R32: =Q32-P32 -> 0 | S32: 2 | T32: =R32*S32 -> 0
D33: Total | F33: =SUM(F28:F32) -> 0 | K33: 15 | N33: 30 | P33: ='4'!Q33 -> 0 | R33: =Q33-P33 -> 0 | S33: 2 | T33: =R33*S33 -> 0
D34: Cash Expense | K34: 16 | N34: 31 | P34: ='4'!Q34 -> 0 | R34: =Q34-P34 -> 0 | S34: 2 | T34: =R34*S34 -> 0
D35: Description | F35: Amount | K35: 17 | N35: 32 | P35: ='4'!Q35 -> 0 | R35: =Q35-P35 -> 0 | S35: 2 | T35: =R35*S35 -> 0
K36: 18 | N36: 33 | P36: ='4'!Q36 -> 0 | R36: =Q36-P36 -> 0 | S36: 2 | T36: =R36*S36 -> 0
K37: 19 | N37: 34 | P37: ='4'!Q37 -> 0 | R37: =Q37-P37 -> 0 | S37: 1 | T37: =R37*S37 -> 0
K38: 20 | N38: 35 | P38: ='4'!Q38 -> 0 | R38: =Q38-P38 -> 0 | S38: 1 | T38: =R38*S38 -> 0
K39: 21 | N39: 36 | P39: ='4'!Q39 -> 0 | R39: =Q39-P39 -> 0 | S39: 2 | T39: =R39*S39 -> 0
A40: Total | C40: =SUM(C28:C39) -> 0 | D40: Total | F40: =SUM(F36:F39) -> 0 | H40: TOTAL | J40: =SUM(J30:J39) -> 0 | K40: TOTAL | L40: =SUM(L19:L39) -> 23327 | N40: 37 | P40: ='4'!Q40 -> 0 | R40: =Q40-P40 -> 0 | S40: 2 | T40: =R40*S40 -> 0
N41: 38 | P41: ='4'!Q41 -> 0 | R41: =Q41-P41 -> 0 | S41: 2 | T41: =R41*S41 -> 0
A42: Check Purchases | D42: Check Expenses | N42: 39 | P42: ='4'!Q42 -> 0 | R42: =Q42-P42 -> 0 | S42: 1 | T42: =R42*S42 -> 0
A43: Description | B43: Check | C43: Amount | D43: Description | E43: Check | F43: Amount | H43: CASH IN | K43: CASH OUT TO OTHER | N43: 40 | P43: ='4'!Q43 -> 0 | R43: =Q43-P43 -> 0 | S43: 1 | T43: =R43*S43 -> 0
H44: CASH IN FROM | J44: AMOUNT | K44: OTHER CASH OUT | M44: AMOUNT | N44: 41 | P44: ='4'!Q44 -> 0 | R44: =Q44-P44 -> 0 | S44: 10 | T44: =R44*S44 -> 0
K45: Skill Game Out | M45: 338 | N45: 42 | P45: ='4'!Q45 -> 0 | R45: =Q45-P45 -> 0 | S45: 1 | T45: =R45*S45 -> 0
K46: Skill Game Out | M46: 200 | N46: 43 | P46: ='4'!Q46 -> 0 | R46: =Q46-P46 -> 0 | S46: 1 | T46: =R46*S46 -> 0
D47: Total | F47: =SUM(F44:F46) -> 0 | H47: Led Check | J47: 3510 | N47: 44 | P47: ='4'!Q47 -> 0 | R47: =Q47-P47 -> 0 | S47: 1 | T47: =R47*S47 -> 0
D48: Rebates and Commissions | H48: Side Expense In | J48: 125 | N48: 45 | P48: ='4'!Q48 -> 0 | R48: =Q48-P48 -> 0 | S48: 1 | T48: =R48*S48 -> 0
D49: Description | F49: Amount | N49: 46 | P49: ='4'!Q49 -> 0 | R49: =Q49-P49 -> 0 | S49: 1 | T49: =R49*S49 -> 0
N50: 47 | P50: ='4'!Q50 -> 0 | R50: =Q50-P50 -> 0 | S50: 1 | T50: =R50*S50 -> 0
N51: 48 | P51: ='4'!Q51 -> 0 | R51: =Q51-P51 -> 0 | S51: 1 | T51: =R51*S51 -> 0
O52: Total Lottery Sale | S52: =SUM(T4:T51) -> 0
A53: Total | C53: =SUM(C44:C52) -> 0 | D53: Total | F53: =SUM(F50:F52) -> 0 | H53: TOTAL | J53: =SUM(J45:J52) -> 3635 | K53: TOTAL | M53: =SUM(M45:M52) -> 538

Sheet 6
A1: ='1'!A1:F1 -> DINERO EXPRESS #8 (512) 8015655 | H1: =A1 -> DINERO EXPRESS #8 (512) 8015655 | M1: DATE
A2: Daily Report | D2: Date: | F2: ='5'!F2+1 -> 5 | H2: OTHER REPORTS | M2: =F2 -> 5 | O2: Lottery Sale
D3: Day: | M3: =F3 -> 0 | O3: Game # | P3: Open | Q3: Close | R3: Tic.Sold | S3: $ Value | T3: T. Sale
A4: Reciepts | C4: Amount | D4: Disbursments | F4: Amount | H4: MONEY TRANSFER | N4: 1 | P4: ='5'!Q4 -> 0 | R4: =Q4-P4 -> 0 | S4: 50 | T4: =R4*S4 -> 0
A5: ='1'!A5:B5 -> Taxable Sale | C5: 32 | D5: ='1'!D5:E5 -> Cash Purchases | F5: =C40 -> 0 | H5: Company | I5: Amount | J5: Fees | K5: Commission | L5: Individual Total Amount | N5: 2 | P5: ='5'!Q5 -> 0 | R5: =Q5-P5 -> 0 | S5: 20 | T5: =R5*S5 -> 0
A6: ='1'!A6:B6 -> Comm & Fee | C6: 13 | D6: ='1'!D6:E6 -> Cash Expense | F6: =F40 -> 0 | H6: ='1'!H6 -> DINEX | L6: =SUM(I6:K6) -> 0 | N6: 3 | P6: ='5'!Q6 -> 0 | R6: =Q6-P6 -> 0 | S6: 20 | T6: =R6*S6 -> 0
A7: ='1'!A7:B7 -> Sales Tax | D7: ='1'!D7:E7 -> Check Purchases | F7: =C53 -> 0 | H7: ='1'!H7 -> INTERMEX | I7: 6209.8 | J7: 128 | L7: =SUM(I7:K7) -> 6337.8 | N7: 4 | P7: ='5'!Q7 -> 0 | R7: =Q7-P7 -> 0 | S7: 10 | T7: =R7*S7 -> 0
A8: ='1'!A8:B8 -> Money Transfers | C8: =L14 -> 9907.4 | D8: ='1'!D8:E8 -> Check Expense | F8: =F47 -> 0 | H8: ='1'!H8 -> SIGUE | L8: =SUM(I8:K8) -> 0 | N8: 5 | P8: ='5'!Q8 -> 0 | R8: =Q8-P8 -> 0 | S8: 10 | T8: =R8*S8 -> 0
A9: ='1'!A9:B9 -> Lottery Sales | C9: =S52 -> 0 | D9: ='1'!D9:E9 -> Lotto Paid Out | H9: ='1'!H9 -> AFEX | L9: =SUM(I9:K9) -> 0 | N9: 6 | P9: ='5'!Q9 -> 0 | R9: =Q9-P9 -> 0 | S9: 20 | T9: =R9*S9 -> 0
A10: ='1'!A10:B10 -> Lotto Net Sales | D10: ='1'!D10:E10 -> Lottery Paid Out | H10: ='1'!H10 -> MONEYGRAM | L10: =SUM(I10:K10) -> 0 | N10: 7 | P10: ='5'!Q10 -> 0 | R10: =Q10-P10 -> 0 | S10: 20 | T10: =R10*S10 -> 0
A11: ='1'!A11:B11 -> PhoneCard | D11: ='1'!D11:E11 -> ATM Drop | H11: ='1'!H11 -> BARRI | L11: =SUM(I11:K11) -> 0 | N11: 8 | P11: ='5'!Q11 -> 0 | R11: =Q11-P11 -> 0 | S11: 20 | T11: =R11*S11 -> 0
A12: ='1'!A12:B12 -> Boss Revolution | D12: ='1'!D12:E12 -> Credit Card | H12: ='1'!H12 -> MAXI | I12: 3417.6 | J12: 152 | L12: =SUM(I12:K12) -> 3569.6 | N12: 9 | P12: ='5'!Q12 -> 0 | R12: =Q12-P12 -> 0 | S12: 10 | T12: =R12*S12 -> 0
A13: ='1'!A13:B13 -> Bill Payment | D13: ='1'!D13:E13 -> Outside Cash & Drops | F13: =L40 -> 9908 | H13: ='1'!H13 -> AMIGO SIN PIN | L13: =SUM(I13:K13) -> 0 | N13: 10 | P13: ='5'!Q13 -> 0 | R13: =Q13-P13 -> 0 | S13: 10 | T13: =R13*S13 -> 0
A14: ='1'!A14:B14 -> VidaPay | D14: ='1'!D14:E14 -> Cash Deposit | H14: TOTAL | I14: =SUM(I6:I13) -> 9627.4 | J14: =SUM(J6:J13) -> 280 | K14: =SUM(K6:K13) -> 0 | L14: =SUM(L6:M13) -> 9907.4 | N14: 11 | P14: ='5'!Q14 -> 0 | R14: =Q14-P14 -> 0 | S14: 5 | T14: =R14*S14 -> 0
A15: ='1'!A15:B15 -> Boost Epay | D15: ='1'!D15:E15 -> Money Gram Payment | N15: 12 | P15: ='5'!Q15 -> 0 | R15: =Q15-P15 -> 0 | S15: 5 | T15: =R15*S15 -> 0
A16: ='1'!A16:B16 -> Epay | D16: ='1'!D16:E16 -> Vigo Payment | N16: 13 | P16: ='5'!Q16 -> 0 | R16: =Q16-P16 -> 0 | S16: 5 | T16: =R16*S16 -> 0
A17: ='1'!A17:B17 -> Check Cashing Fees | C17: 78.99 | D17: ='1'!D17:E17 -> Ria Payment | N17: 14 | P17: ='5'!Q17 -> 0 | R17: =Q17-P17 -> 0 | S17: 5 | T17: =R17*S17 -> 0
A18: ='1'!A18:B18 -> Money Order | C18: 4391 | D18: ='1'!D18:E18 -> Checks Deposit | F18: =J25 -> 13497.7 | H18: CHECK DEPOSITS | K18: DROPS | L18: AMOUNT | M18: TIME | N18: 15 | P18: ='5'!Q18 -> 0 | R18: =Q18-P18 -> 0 | S18: 5 | T18: =R18*S18 -> 0
A19: ='1'!A19:B19 -> Return Check Paid | C19: =F33 -> 550 | D19: ='1'!D19:E19 -> Safe Balance | F19: 62822 | H19: CHECK DEPOSITS TO BANK | J19: AMOUNT | K19: 1 | L19: 2160 | M19: 12:53PM | N19: 16 | P19: ='5'!Q19 -> 0 | R19: =Q19-P19 -> 0 | S19: 5 | T19: =R19*S19 -> 0
A20: ='1'!A20:B20 -> Forward Balance | C20: ='5'!F19+'5'!F13 -> 70935 | D20: ='1'!D20:E20 -> Payroll Expense | F20: =J40 -> 0 | H20: NIZARI (15 Checks) | J20: 13497.7 | K20: 2 | L20: 4790 | M20: 5:05PM | N20: 17 | P20: ='5'!Q20 -> 0 | R20: =Q20-P20 -> 0 | S20: 5 | T20: =R20*S20 -> 0
A21: ='1'!A21:B21 -> Cash From Bank | D21: ='1'!D21:E21 -> Other Cash Out | F21: =M53 -> 2300 | K21: 3 | L21: 2958 | M21: 8:52PM | N21: 18 | P21: ='5'!Q21 -> 0 | R21: =Q21-P21 -> 0 | S21: 5 | T21: =R21*S21 -> 0
A22: ='1'!A22:B22 -> Other Cash In | C22: =J53 -> 2620 | D22: TOTAL PAYOUTS | F22: =SUM(F5:F21)-F7-F8 -> 88527.7 | K22: 4 | N22: 19 | P22: ='5'!Q22 -> 0 | R22: =Q22-P22 -> 0 | S22: 5 | T22: =R22*S22 -> 0
A23: ='1'!A23:B23 -> Rebates & Commissions | C23: =F53 -> 0 | D23: Inside Over - (Short) | F23: =(F11+F14+F15+F16+F17+F18+F19+F20+F21+F5+F6)-(C17+C19+C20+C21+C22+C23) -> 4435.71 | K23: 5 | N23: 20 | P23: ='5'!Q23 -> 0 | R23: =Q23-P23 -> 0 | S23: 5 | T23: =R23*S23 -> 0
A24: TOTAL RECEIPTS | C24: =SUM(C5:C23) -> 88527.39 | D24: Over All Over - (Short) | F24: =SUM(F22-C24) -> 0.31 | K24: 6 | N24: 21 | P24: ='5'!Q24 -> 0 | R24: =Q24-P24 -> 0 | S24: 5 | T24: =R24*S24 -> 0
A25: Out Side Over - (Short) | C25: =(F9+F10+F12+F13)-(C5+C6+C7+C8+C9+C10+C11+C12+C13+C14+C15+C16+C18) -> -4435.4 | H25: TOTAL | J25: =SUM(J20:J24) -> 13497.7 | K25: 7 | N25: 22 | P25: ='5'!Q25 -> 0 | R25: =Q25-P25 -> 0 | S25: 5 | T25: =R25*S25 -> 0
A26: Cash Purchases | D26: Return Check Paid | K26: 8 | N26: 23 | P26: ='5'!Q26 -> 0 | R26: =Q26-P26 -> 0 | S26: 3 | T26: =R26*S26 -> 0
A27: Description | C27: Amount | D27: Description | F27: Amount | K27: 9 | N27: 24 | P27: ='5'!Q27 -> 0 | R27: =Q27-P27 -> 0 | S27: 3 | T27: =R27*S27 -> 0
D28: Innova Service | F28: 150 | H28: CASH PAYROLL EXPENSE | K28: 10 | N28: 25 | P28: ='5'!Q28 -> 0 | R28: =Q28-P28 -> 0 | S28: 2 | T28: =R28*S28 -> 0
D29: Santex (Partial Pay $400) | F29: 400 | H29: CASH PAYROLL PAID TO | J29: AMOUNT | K29: 11 | N29: 26 | P29: ='5'!Q29 -> 0 | R29: =Q29-P29 -> 0 | S29: 5 | T29: =R29*S29 -> 0
K30: 12 | N30: 27 | P30: ='5'!Q30 -> 0 | R30: =Q30-P30 -> 0 | S30: 3 | T30: =R30*S30 -> 0
K31: 13 | N31: 28 | P31: ='5'!Q31 -> 0 | R31: =Q31-P31 -> 0 | S31: 3 | T31: =R31*S31 -> 0
K32: 14 | N32: 29 | P32: ='5'!Q32 -> 0 | R32: =Q32-P32 -> 0 | S32: 2 | T32: =R32*S32 -> 0
D33: Total | F33: =SUM(F28:F32) -> 550 | K33: 15 | N33: 30 | P33: ='5'!Q33 -> 0 | R33: =Q33-P33 -> 0 | S33: 2 | T33: =R33*S33 -> 0
D34: Cash Expense | K34: 16 | N34: 31 | P34: ='5'!Q34 -> 0 | R34: =Q34-P34 -> 0 | S34: 2 | T34: =R34*S34 -> 0
D35: Description | F35: Amount | K35: 17 | N35: 32 | P35: ='5'!Q35 -> 0 | R35: =Q35-P35 -> 0 | S35: 2 | T35: =R35*S35 -> 0
K36: 18 | N36: 33 | P36: ='5'!Q36 -> 0 | R36: =Q36-P36 -> 0 | S36: 2 | T36: =R36*S36 -> 0
K37: 19 | N37: 34 | P37: ='5'!Q37 -> 0 | R37: =Q37-P37 -> 0 | S37: 1 | T37: =R37*S37 -> 0
K38: 20 | N38: 35 | P38: ='5'!Q38 -> 0 | R38: =Q38-P38 -> 0 | S38: 1 | T38: =R38*S38 -> 0
K39: 21 | N39: 36 | P39: ='5'!Q39 -> 0 | R39: =Q39-P39 -> 0 | S39: 2 | T39: =R39*S39 -> 0
A40: Total | C40: =SUM(C28:C39) -> 0 | D40: Total | F40: =SUM(F36:F39) -> 0 | H40: TOTAL | J40: =SUM(J30:J39) -> 0 | K40: TOTAL | L40: =SUM(L19:L39) -> 9908 | N40: 37 | P40: ='5'!Q40 -> 0 | R40: =Q40-P40 -> 0 | S40: 2 | T40: =R40*S40 -> 0
N41: 38 | P41: ='5'!Q41 -> 0 | R41: =Q41-P41 -> 0 | S41: 2 | T41: =R41*S41 -> 0
A42: Check Purchases | D42: Check Expenses | N42: 39 | P42: ='5'!Q42 -> 0 | R42: =Q42-P42 -> 0 | S42: 1 | T42: =R42*S42 -> 0
A43: Description | B43: Check | C43: Amount | D43: Description | E43: Check | F43: Amount | H43: CASH IN | K43: CASH OUT TO OTHER | N43: 40 | P43: ='5'!Q43 -> 0 | R43: =Q43-P43 -> 0 | S43: 1 | T43: =R43*S43 -> 0
H44: CASH IN FROM | J44: AMOUNT | K44: OTHER CASH OUT | M44: AMOUNT | N44: 41 | P44: ='5'!Q44 -> 0 | R44: =Q44-P44 -> 0 | S44: 10 | T44: =R44*S44 -> 0
H45: Take ATM In $2K | J45: 2000 | K45: LED Logistics LLC (2 Checks) | M45: 2300 | N45: 42 | P45: ='5'!Q45 -> 0 | R45: =Q45-P45 -> 0 | S45: 1 | T45: =R45*S45 -> 0
H46: Skill Game In | J46: 538 | N46: 43 | P46: ='5'!Q46 -> 0 | R46: =Q46-P46 -> 0 | S46: 1 | T46: =R46*S46 -> 0
D47: Total | F47: =SUM(F44:F46) -> 0 | H47: Side Expense In | J47: 82 | N47: 44 | P47: ='5'!Q47 -> 0 | R47: =Q47-P47 -> 0 | S47: 1 | T47: =R47*S47 -> 0
D48: Rebates and Commissions | N48: 45 | P48: ='5'!Q48 -> 0 | R48: =Q48-P48 -> 0 | S48: 1 | T48: =R48*S48 -> 0
D49: Description | F49: Amount | N49: 46 | P49: ='5'!Q49 -> 0 | R49: =Q49-P49 -> 0 | S49: 1 | T49: =R49*S49 -> 0
N50: 47 | P50: ='5'!Q50 -> 0 | R50: =Q50-P50 -> 0 | S50: 1 | T50: =R50*S50 -> 0
N51: 48 | P51: ='5'!Q51 -> 0 | R51: =Q51-P51 -> 0 | S51: 1 | T51: =R51*S51 -> 0
O52: Total Lottery Sale | S52: =SUM(T4:T51) -> 0
A53: Total | C53: =SUM(C44:C52) -> 0 | D53: Total | F53: =SUM(F50:F52) -> 0 | H53: TOTAL | J53: =SUM(J45:J52) -> 2620 | K53: TOTAL | M53: =SUM(M45:M52) -> 2300

Sheet 7
A1: ='1'!A1:F1 -> DINERO EXPRESS #8 (512) 8015655 | H1: =A1 -> DINERO EXPRESS #8 (512) 8015655 | M1: DATE
A2: Daily Report | D2: Date: | F2: ='6'!F2+1 -> 6 | H2: OTHER REPORTS | M2: =F2 -> 6 | O2: Lottery Sale
D3: Day: | M3: =F3 -> 0 | O3: Game # | P3: Open | Q3: Close | R3: Tic.Sold | S3: $ Value | T3: T. Sale
A4: Reciepts | C4: Amount | D4: Disbursments | F4: Amount | H4: MONEY TRANSFER | N4: 1 | P4: ='6'!Q4 -> 0 | R4: =Q4-P4 -> 0 | S4: 50 | T4: =R4*S4 -> 0
A5: ='1'!A5:B5 -> Taxable Sale | C5: 19 | D5: ='1'!D5:E5 -> Cash Purchases | F5: =C40 -> 0 | H5: Company | I5: Amount | J5: Fees | K5: Commission | L5: Individual Total Amount | N5: 2 | P5: ='6'!Q5 -> 0 | R5: =Q5-P5 -> 0 | S5: 20 | T5: =R5*S5 -> 0
A6: ='1'!A6:B6 -> Comm & Fee | C6: 6 | D6: ='1'!D6:E6 -> Cash Expense | F6: =F40 -> 0 | H6: ='1'!H6 -> DINEX | L6: =SUM(I6:K6) -> 0 | N6: 3 | P6: ='6'!Q6 -> 0 | R6: =Q6-P6 -> 0 | S6: 20 | T6: =R6*S6 -> 0
A7: ='1'!A7:B7 -> Sales Tax | D7: ='1'!D7:E7 -> Check Purchases | F7: =C53 -> 0 | H7: ='1'!H7 -> INTERMEX | I7: 4852.6 | J7: 91 | L7: =SUM(I7:K7) -> 4943.6 | N7: 4 | P7: ='6'!Q7 -> 0 | R7: =Q7-P7 -> 0 | S7: 10 | T7: =R7*S7 -> 0
A8: ='1'!A8:B8 -> Money Transfers | C8: =L14 -> 6814.53 | D8: ='1'!D8:E8 -> Check Expense | F8: =F47 -> 0 | H8: ='1'!H8 -> SIGUE | L8: =SUM(I8:K8) -> 0 | N8: 5 | P8: ='6'!Q8 -> 0 | R8: =Q8-P8 -> 0 | S8: 10 | T8: =R8*S8 -> 0
A9: ='1'!A9:B9 -> Lottery Sales | C9: =S52 -> 0 | D9: ='1'!D9:E9 -> Lotto Paid Out | H9: ='1'!H9 -> AFEX | L9: =SUM(I9:K9) -> 0 | N9: 6 | P9: ='6'!Q9 -> 0 | R9: =Q9-P9 -> 0 | S9: 20 | T9: =R9*S9 -> 0
A10: ='1'!A10:B10 -> Lotto Net Sales | D10: ='1'!D10:E10 -> Lottery Paid Out | H10: ='1'!H10 -> MONEYGRAM | L10: =SUM(I10:K10) -> 0 | N10: 7 | P10: ='6'!Q10 -> 0 | R10: =Q10-P10 -> 0 | S10: 20 | T10: =R10*S10 -> 0
A11: ='1'!A11:B11 -> PhoneCard | D11: ='1'!D11:E11 -> ATM Drop | H11: ='1'!H11 -> BARRI | L11: =SUM(I11:K11) -> 0 | N11: 8 | P11: ='6'!Q11 -> 0 | R11: =Q11-P11 -> 0 | S11: 20 | T11: =R11*S11 -> 0
A12: ='1'!A12:B12 -> Boss Revolution | D12: ='1'!D12:E12 -> Credit Card | H12: ='1'!H12 -> MAXI | I12: 1810.93 | J12: 60 | L12: =SUM(I12:K12) -> 1870.93 | N12: 9 | P12: ='6'!Q12 -> 0 | R12: =Q12-P12 -> 0 | S12: 10 | T12: =R12*S12 -> 0
A13: ='1'!A13:B13 -> Bill Payment | D13: ='1'!D13:E13 -> Outside Cash & Drops | F13: =L40 -> 6926 | H13: ='1'!H13 -> AMIGO SIN PIN | L13: =SUM(I13:K13) -> 0 | N13: 10 | P13: ='6'!Q13 -> 0 | R13: =Q13-P13 -> 0 | S13: 10 | T13: =R13*S13 -> 0
A14: ='1'!A14:B14 -> VidaPay | D14: ='1'!D14:E14 -> Cash Deposit | H14: TOTAL | I14: =SUM(I6:I13) -> 6663.53 | J14: =SUM(J6:J13) -> 151 | K14: =SUM(K6:K13) -> 0 | L14: =SUM(L6:M13) -> 6814.53 | N14: 11 | P14: ='6'!Q14 -> 0 | R14: =Q14-P14 -> 0 | S14: 5 | T14: =R14*S14 -> 0
A15: ='1'!A15:B15 -> Boost Epay | D15: ='1'!D15:E15 -> Money Gram Payment | N15: 12 | P15: ='6'!Q15 -> 0 | R15: =Q15-P15 -> 0 | S15: 5 | T15: =R15*S15 -> 0
A16: ='1'!A16:B16 -> Epay | D16: ='1'!D16:E16 -> Vigo Payment | N16: 13 | P16: ='6'!Q16 -> 0 | R16: =Q16-P16 -> 0 | S16: 5 | T16: =R16*S16 -> 0
A17: ='1'!A17:B17 -> Check Cashing Fees | C17: 162.79 | D17: ='1'!D17:E17 -> Ria Payment | N17: 14 | P17: ='6'!Q17 -> 0 | R17: =Q17-P17 -> 0 | S17: 5 | T17: =R17*S17 -> 0
A18: ='1'!A18:B18 -> Money Order | C18: 750 | D18: ='1'!D18:E18 -> Checks Deposit | F18: =J25 -> 32558.48 | H18: CHECK DEPOSITS | K18: DROPS | L18: AMOUNT | M18: TIME | N18: 15 | P18: ='6'!Q18 -> 0 | R18: =Q18-P18 -> 0 | S18: 5 | T18: =R18*S18 -> 0
A19: ='1'!A19:B19 -> Return Check Paid | C19: =F33 -> 0 | D19: ='1'!D19:E19 -> Safe Balance | F19: 66804 | H19: CHECK DEPOSITS TO BANK | J19: AMOUNT | K19: 1 | L19: 3040 | M19: 4:03PM | N19: 16 | P19: ='6'!Q19 -> 0 | R19: =Q19-P19 -> 0 | S19: 5 | T19: =R19*S19 -> 0
A20: ='1'!A20:B20 -> Forward Balance | C20: ='6'!F19+'6'!F13 -> 72730 | D20: ='1'!D20:E20 -> Payroll Expense | F20: =J40 -> 0 | H20: NIZARI (22 Checks) | J20: 32558.48 | K20: 2 | L20: 3395 | M20: 8:10PM | N20: 17 | P20: ='6'!Q20 -> 0 | R20: =Q20-P20 -> 0 | S20: 5 | T20: =R20*S20 -> 0
A21: ='1'!A21:B21 -> Cash From Bank | C21: 25500 | D21: ='1'!D21:E21 -> Other Cash Out | F21: =M53 -> 20 | K21: 3 | L21: 471 | M21: 8:49PM | N21: 18 | P21: ='6'!Q21 -> 0 | R21: =Q21-P21 -> 0 | S21: 5 | T21: =R21*S21 -> 0
A22: ='1'!A22:B22 -> Other Cash In | C22: =J53 -> 326 | D22: TOTAL PAYOUTS | F22: =SUM(F5:F21)-F7-F8 -> 106308.48 | K22: 4 | L22: 20 | N22: 19 | P22: ='6'!Q22 -> 0 | R22: =Q22-P22 -> 0 | S22: 5 | T22: =R22*S22 -> 0
A23: ='1'!A23:B23 -> Rebates & Commissions | C23: =F53 -> 0 | D23: Inside Over - (Short) | F23: =(F11+F14+F15+F16+F17+F18+F19+F20+F21+F5+F6)-(C17+C19+C20+C21+C22+C23) -> 663.69 | K23: 5 | N23: 20 | P23: ='6'!Q23 -> 0 | R23: =Q23-P23 -> 0 | S23: 5 | T23: =R23*S23 -> 0
A24: TOTAL RECEIPTS | C24: =SUM(C5:C23) -> 106308.32 | D24: Over All Over - (Short) | F24: =SUM(F22-C24) -> 0.16 | K24: 6 | N24: 21 | P24: ='6'!Q24 -> 0 | R24: =Q24-P24 -> 0 | S24: 5 | T24: =R24*S24 -> 0
A25: Out Side Over - (Short) | C25: =(F9+F10+F12+F13)-(C5+C6+C7+C8+C9+C10+C11+C12+C13+C14+C15+C16+C18) -> -663.53 | H25: TOTAL | J25: =SUM(J20:J24) -> 32558.48 | K25: 7 | N25: 22 | P25: ='6'!Q25 -> 0 | R25: =Q25-P25 -> 0 | S25: 5 | T25: =R25*S25 -> 0
A26: Cash Purchases | D26: Return Check Paid | K26: 8 | N26: 23 | P26: ='6'!Q26 -> 0 | R26: =Q26-P26 -> 0 | S26: 3 | T26: =R26*S26 -> 0
A27: Description | C27: Amount | D27: Description | F27: Amount | K27: 9 | N27: 24 | P27: ='6'!Q27 -> 0 | R27: =Q27-P27 -> 0 | S27: 3 | T27: =R27*S27 -> 0
H28: CASH PAYROLL EXPENSE | K28: 10 | N28: 25 | P28: ='6'!Q28 -> 0 | R28: =Q28-P28 -> 0 | S28: 2 | T28: =R28*S28 -> 0
H29: CASH PAYROLL PAID TO | J29: AMOUNT | K29: 11 | N29: 26 | P29: ='6'!Q29 -> 0 | R29: =Q29-P29 -> 0 | S29: 5 | T29: =R29*S29 -> 0
K30: 12 | N30: 27 | P30: ='6'!Q30 -> 0 | R30: =Q30-P30 -> 0 | S30: 3 | T30: =R30*S30 -> 0
K31: 13 | N31: 28 | P31: ='6'!Q31 -> 0 | R31: =Q31-P31 -> 0 | S31: 3 | T31: =R31*S31 -> 0
K32: 14 | N32: 29 | P32: ='6'!Q32 -> 0 | R32: =Q32-P32 -> 0 | S32: 2 | T32: =R32*S32 -> 0
D33: Total | F33: =SUM(F28:F32) -> 0 | K33: 15 | N33: 30 | P33: ='6'!Q33 -> 0 | R33: =Q33-P33 -> 0 | S33: 2 | T33: =R33*S33 -> 0
D34: Cash Expense | K34: 16 | N34: 31 | P34: ='6'!Q34 -> 0 | R34: =Q34-P34 -> 0 | S34: 2 | T34: =R34*S34 -> 0
D35: Description | F35: Amount | K35: 17 | N35: 32 | P35: ='6'!Q35 -> 0 | R35: =Q35-P35 -> 0 | S35: 2 | T35: =R35*S35 -> 0
K36: 18 | N36: 33 | P36: ='6'!Q36 -> 0 | R36: =Q36-P36 -> 0 | S36: 2 | T36: =R36*S36 -> 0
K37: 19 | N37: 34 | P37: ='6'!Q37 -> 0 | R37: =Q37-P37 -> 0 | S37: 1 | T37: =R37*S37 -> 0
K38: 20 | N38: 35 | P38: ='6'!Q38 -> 0 | R38: =Q38-P38 -> 0 | S38: 1 | T38: =R38*S38 -> 0
K39: 21 | N39: 36 | P39: ='6'!Q39 -> 0 | R39: =Q39-P39 -> 0 | S39: 2 | T39: =R39*S39 -> 0
A40: Total | C40: =SUM(C28:C39) -> 0 | D40: Total | F40: =SUM(F36:F39) -> 0 | H40: TOTAL | J40: =SUM(J30:J39) -> 0 | K40: TOTAL | L40: =SUM(L19:L39) -> 6926 | N40: 37 | P40: ='6'!Q40 -> 0 | R40: =Q40-P40 -> 0 | S40: 2 | T40: =R40*S40 -> 0
N41: 38 | P41: ='6'!Q41 -> 0 | R41: =Q41-P41 -> 0 | S41: 2 | T41: =R41*S41 -> 0
A42: Check Purchases | D42: Check Expenses | N42: 39 | P42: ='6'!Q42 -> 0 | R42: =Q42-P42 -> 0 | S42: 1 | T42: =R42*S42 -> 0
A43: Description | B43: Check | C43: Amount | D43: Description | E43: Check | F43: Amount | H43: CASH IN | K43: CASH OUT TO OTHER | N43: 40 | P43: ='6'!Q43 -> 0 | R43: =Q43-P43 -> 0 | S43: 1 | T43: =R43*S43 -> 0
H44: CASH IN FROM | J44: AMOUNT | K44: OTHER CASH OUT | M44: AMOUNT | N44: 41 | P44: ='6'!Q44 -> 0 | R44: =Q44-P44 -> 0 | S44: 10 | T44: =R44*S44 -> 0
H45: Intermex Cancel (#8652) | J45: 109 | K45: MT Cash to Coin Out | M45: 20 | N45: 42 | P45: ='6'!Q45 -> 0 | R45: =Q45-P45 -> 0 | S45: 1 | T45: =R45*S45 -> 0
H46: Side Expense In | J46: 217 | N46: 43 | P46: ='6'!Q46 -> 0 | R46: =Q46-P46 -> 0 | S46: 1 | T46: =R46*S46 -> 0
D47: Total | F47: =SUM(F44:F46) -> 0 | N47: 44 | P47: ='6'!Q47 -> 0 | R47: =Q47-P47 -> 0 | S47: 1 | T47: =R47*S47 -> 0
D48: Rebates and Commissions | N48: 45 | P48: ='6'!Q48 -> 0 | R48: =Q48-P48 -> 0 | S48: 1 | T48: =R48*S48 -> 0
D49: Description | F49: Amount | N49: 46 | P49: ='6'!Q49 -> 0 | R49: =Q49-P49 -> 0 | S49: 1 | T49: =R49*S49 -> 0
N50: 47 | P50: ='6'!Q50 -> 0 | R50: =Q50-P50 -> 0 | S50: 1 | T50: =R50*S50 -> 0
N51: 48 | P51: ='6'!Q51 -> 0 | R51: =Q51-P51 -> 0 | S51: 1 | T51: =R51*S51 -> 0
O52: Total Lottery Sale | S52: =SUM(T4:T51) -> 0
A53: Total | C53: =SUM(C44:C52) -> 0 | D53: Total | F53: =SUM(F50:F52) -> 0 | H53: TOTAL | J53: =SUM(J45:J52) -> 326 | K53: TOTAL | M53: =SUM(M45:M52) -> 20

Sheet 8
A1: ='1'!A1:F1 -> DINERO EXPRESS #8 (512) 8015655 | H1: =A1 -> DINERO EXPRESS #8 (512) 8015655 | M1: DATE
A2: Daily Report | D2: Date: | F2: ='7'!F2+1 -> 7 | H2: OTHER REPORTS | M2: =F2 -> 7 | O2: Lottery Sale
D3: Day: | M3: =F3 -> 0 | O3: Game # | P3: Open | Q3: Close | R3: Tic.Sold | S3: $ Value | T3: T. Sale
A4: Reciepts | C4: Amount | D4: Disbursments | F4: Amount | H4: MONEY TRANSFER | N4: 1 | P4: ='7'!Q4 -> 0 | R4: =Q4-P4 -> 0 | S4: 50 | T4: =R4*S4 -> 0
A5: ='1'!A5:B5 -> Taxable Sale | C5: 6 | D5: ='1'!D5:E5 -> Cash Purchases | F5: =C40 -> 0 | H5: Company | I5: Amount | J5: Fees | K5: Commission | L5: Individual Total Amount | N5: 2 | P5: ='7'!Q5 -> 0 | R5: =Q5-P5 -> 0 | S5: 20 | T5: =R5*S5 -> 0
A6: ='1'!A6:B6 -> Comm & Fee | C6: 9 | D6: ='1'!D6:E6 -> Cash Expense | F6: =F40 -> 0 | H6: ='1'!H6 -> DINEX | L6: =SUM(I6:K6) -> 0 | N6: 3 | P6: ='7'!Q6 -> 0 | R6: =Q6-P6 -> 0 | S6: 20 | T6: =R6*S6 -> 0
A7: ='1'!A7:B7 -> Sales Tax | D7: ='1'!D7:E7 -> Check Purchases | F7: =C53 -> 0 | H7: ='1'!H7 -> INTERMEX | I7: 1883 | J7: 51 | L7: =SUM(I7:K7) -> 1934 | N7: 4 | P7: ='7'!Q7 -> 0 | R7: =Q7-P7 -> 0 | S7: 10 | T7: =R7*S7 -> 0
A8: ='1'!A8:B8 -> Money Transfers | C8: =L14 -> 6765.8 | D8: ='1'!D8:E8 -> Check Expense | F8: =F47 -> 0 | H8: ='1'!H8 -> SIGUE | L8: =SUM(I8:K8) -> 0 | N8: 5 | P8: ='7'!Q8 -> 0 | R8: =Q8-P8 -> 0 | S8: 10 | T8: =R8*S8 -> 0
A9: ='1'!A9:B9 -> Lottery Sales | C9: =S52 -> 0 | D9: ='1'!D9:E9 -> Lotto Paid Out | H9: ='1'!H9 -> AFEX | L9: =SUM(I9:K9) -> 0 | N9: 6 | P9: ='7'!Q9 -> 0 | R9: =Q9-P9 -> 0 | S9: 20 | T9: =R9*S9 -> 0
A10: ='1'!A10:B10 -> Lotto Net Sales | D10: ='1'!D10:E10 -> Lottery Paid Out | H10: ='1'!H10 -> MONEYGRAM | L10: =SUM(I10:K10) -> 0 | N10: 7 | P10: ='7'!Q10 -> 0 | R10: =Q10-P10 -> 0 | S10: 20 | T10: =R10*S10 -> 0
A11: ='1'!A11:B11 -> PhoneCard | D11: ='1'!D11:E11 -> ATM Drop | H11: ='1'!H11 -> BARRI | I11: 1702 | J11: 30 | L11: =SUM(I11:K11) -> 1732 | N11: 8 | P11: ='7'!Q11 -> 0 | R11: =Q11-P11 -> 0 | S11: 20 | T11: =R11*S11 -> 0
A12: ='1'!A12:B12 -> Boss Revolution | D12: ='1'!D12:E12 -> Credit Card | H12: ='1'!H12 -> MAXI | I12: 3027.8 | J12: 72 | L12: =SUM(I12:K12) -> 3099.8 | N12: 9 | P12: ='7'!Q12 -> 0 | R12: =Q12-P12 -> 0 | S12: 10 | T12: =R12*S12 -> 0
A13: ='1'!A13:B13 -> Bill Payment | D13: ='1'!D13:E13 -> Outside Cash & Drops | F13: =L40 -> 6660 | H13: ='1'!H13 -> AMIGO SIN PIN | L13: =SUM(I13:K13) -> 0 | N13: 10 | P13: ='7'!Q13 -> 0 | R13: =Q13-P13 -> 0 | S13: 10 | T13: =R13*S13 -> 0
A14: ='1'!A14:B14 -> VidaPay | D14: ='1'!D14:E14 -> Cash Deposit | H14: TOTAL | I14: =SUM(I6:I13) -> 6612.8 | J14: =SUM(J6:J13) -> 153 | K14: =SUM(K6:K13) -> 0 | L14: =SUM(L6:M13) -> 6765.8 | N14: 11 | P14: ='7'!Q14 -> 0 | R14: =Q14-P14 -> 0 | S14: 5 | T14: =R14*S14 -> 0
A15: ='1'!A15:B15 -> Boost Epay | D15: ='1'!D15:E15 -> Money Gram Payment | N15: 12 | P15: ='7'!Q15 -> 0 | R15: =Q15-P15 -> 0 | S15: 5 | T15: =R15*S15 -> 0
A16: ='1'!A16:B16 -> Epay | D16: ='1'!D16:E16 -> Vigo Payment | N16: 13 | P16: ='7'!Q16 -> 0 | R16: =Q16-P16 -> 0 | S16: 5 | T16: =R16*S16 -> 0
A17: ='1'!A17:B17 -> Check Cashing Fees | C17: 165.58 | D17: ='1'!D17:E17 -> Ria Payment | N17: 14 | P17: ='7'!Q17 -> 0 | R17: =Q17-P17 -> 0 | S17: 5 | T17: =R17*S17 -> 0
A18: ='1'!A18:B18 -> Money Order | C18: 1335 | D18: ='1'!D18:E18 -> Checks Deposit | F18: =J25 -> 33116.3 | H18: CHECK DEPOSITS | K18: DROPS | L18: AMOUNT | M18: TIME | N18: 15 | P18: ='7'!Q18 -> 0 | R18: =Q18-P18 -> 0 | S18: 5 | T18: =R18*S18 -> 0
A19: ='1'!A19:B19 -> Return Check Paid | C19: =F33 -> 0 | D19: ='1'!D19:E19 -> Safe Balance | F19: 42579 | H19: CHECK DEPOSITS TO BANK | J19: AMOUNT | K19: 1 | L19: 1735 | M19: 3:00PM | N19: 16 | P19: ='7'!Q19 -> 0 | R19: =Q19-P19 -> 0 | S19: 5 | T19: =R19*S19 -> 0
A20: ='1'!A20:B20 -> Forward Balance | C20: ='7'!F19+'7'!F13 -> 73730 | D20: ='1'!D20:E20 -> Payroll Expense | F20: =J40 -> 0 | H20: NIZARI (25 Checks) | J20: 33116.3 | K20: 2 | L20: 4597 | M20: 9:02PM | N20: 17 | P20: ='7'!Q20 -> 0 | R20: =Q20-P20 -> 0 | S20: 5 | T20: =R20*S20 -> 0
A21: ='1'!A21:B21 -> Cash From Bank | D21: ='1'!D21:E21 -> Other Cash Out | F21: =M53 -> 109 | K21: 3 | L21: 328 | M21: Pending | N21: 18 | P21: ='7'!Q21 -> 0 | R21: =Q21-P21 -> 0 | S21: 5 | T21: =R21*S21 -> 0
A22: ='1'!A22:B22 -> Other Cash In | C22: =J53 -> 452 | D22: TOTAL PAYOUTS | F22: =SUM(F5:F21)-F7-F8 -> 82464.3 | K22: 4 | N22: 19 | P22: ='7'!Q22 -> 0 | R22: =Q22-P22 -> 0 | S22: 5 | T22: =R22*S22 -> 0
A23: ='1'!A23:B23 -> Rebates & Commissions | C23: =F53 -> 0 | D23: Inside Over - (Short) | F23: =(F11+F14+F15+F16+F17+F18+F19+F20+F21+F5+F6)-(C17+C19+C20+C21+C22+C23) -> 1456.72 | K23: 5 | N23: 20 | P23: ='7'!Q23 -> 0 | R23: =Q23-P23 -> 0 | S23: 5 | T23: =R23*S23 -> 0
A24: TOTAL RECEIPTS | C24: =SUM(C5:C23) -> 82463.38 | D24: Over All Over - (Short) | F24: =SUM(F22-C24) -> 0.92 | K24: 6 | N24: 21 | P24: ='7'!Q24 -> 0 | R24: =Q24-P24 -> 0 | S24: 5 | T24: =R24*S24 -> 0
A25: Out Side Over - (Short) | C25: =(F9+F10+F12+F13)-(C5+C6+C7+C8+C9+C10+C11+C12+C13+C14+C15+C16+C18) -> -1455.8 | H25: TOTAL | J25: =SUM(J20:J24) -> 33116.3 | K25: 7 | N25: 22 | P25: ='7'!Q25 -> 0 | R25: =Q25-P25 -> 0 | S25: 5 | T25: =R25*S25 -> 0
A26: Cash Purchases | D26: Return Check Paid | K26: 8 | N26: 23 | P26: ='7'!Q26 -> 0 | R26: =Q26-P26 -> 0 | S26: 3 | T26: =R26*S26 -> 0
A27: Description | C27: Amount | D27: Description | F27: Amount | K27: 9 | N27: 24 | P27: ='7'!Q27 -> 0 | R27: =Q27-P27 -> 0 | S27: 3 | T27: =R27*S27 -> 0
H28: CASH PAYROLL EXPENSE | K28: 10 | N28: 25 | P28: ='7'!Q28 -> 0 | R28: =Q28-P28 -> 0 | S28: 2 | T28: =R28*S28 -> 0
H29: CASH PAYROLL PAID TO | J29: AMOUNT | K29: 11 | N29: 26 | P29: ='7'!Q29 -> 0 | R29: =Q29-P29 -> 0 | S29: 5 | T29: =R29*S29 -> 0
K30: 12 | N30: 27 | P30: ='7'!Q30 -> 0 | R30: =Q30-P30 -> 0 | S30: 3 | T30: =R30*S30 -> 0
K31: 13 | N31: 28 | P31: ='7'!Q31 -> 0 | R31: =Q31-P31 -> 0 | S31: 3 | T31: =R31*S31 -> 0
K32: 14 | N32: 29 | P32: ='7'!Q32 -> 0 | R32: =Q32-P32 -> 0 | S32: 2 | T32: =R32*S32 -> 0
D33: Total | F33: =SUM(F28:F32) -> 0 | K33: 15 | N33: 30 | P33: ='7'!Q33 -> 0 | R33: =Q33-P33 -> 0 | S33: 2 | T33: =R33*S33 -> 0
D34: Cash Expense | K34: 16 | N34: 31 | P34: ='7'!Q34 -> 0 | R34: =Q34-P34 -> 0 | S34: 2 | T34: =R34*S34 -> 0
D35: Description | F35: Amount | K35: 17 | N35: 32 | P35: ='7'!Q35 -> 0 | R35: =Q35-P35 -> 0 | S35: 2 | T35: =R35*S35 -> 0
K36: 18 | N36: 33 | P36: ='7'!Q36 -> 0 | R36: =Q36-P36 -> 0 | S36: 2 | T36: =R36*S36 -> 0
K37: 19 | N37: 34 | P37: ='7'!Q37 -> 0 | R37: =Q37-P37 -> 0 | S37: 1 | T37: =R37*S37 -> 0
K38: 20 | N38: 35 | P38: ='7'!Q38 -> 0 | R38: =Q38-P38 -> 0 | S38: 1 | T38: =R38*S38 -> 0
K39: 21 | N39: 36 | P39: ='7'!Q39 -> 0 | R39: =Q39-P39 -> 0 | S39: 2 | T39: =R39*S39 -> 0
A40: Total | C40: =SUM(C28:C39) -> 0 | D40: Total | F40: =SUM(F36:F39) -> 0 | H40: TOTAL | J40: =SUM(J30:J39) -> 0 | K40: TOTAL | L40: =SUM(L19:L39) -> 6660 | N40: 37 | P40: ='7'!Q40 -> 0 | R40: =Q40-P40 -> 0 | S40: 2 | T40: =R40*S40 -> 0
N41: 38 | P41: ='7'!Q41 -> 0 | R41: =Q41-P41 -> 0 | S41: 2 | T41: =R41*S41 -> 0
A42: Check Purchases | D42: Check Expenses | N42: 39 | P42: ='7'!Q42 -> 0 | R42: =Q42-P42 -> 0 | S42: 1 | T42: =R42*S42 -> 0
A43: Description | B43: Check | C43: Amount | D43: Description | E43: Check | F43: Amount | H43: CASH IN | K43: CASH OUT TO OTHER | N43: 40 | P43: ='7'!Q43 -> 0 | R43: =Q43-P43 -> 0 | S43: 1 | T43: =R43*S43 -> 0
H44: CASH IN FROM | J44: AMOUNT | K44: OTHER CASH OUT | M44: AMOUNT | N44: 41 | P44: ='7'!Q44 -> 0 | R44: =Q44-P44 -> 0 | S44: 10 | T44: =R44*S44 -> 0
H45: Take Paco $300 | J45: 300 | K45: Intermex Re-Envio (#8652) | M45: 109 | N45: 42 | P45: ='7'!Q45 -> 0 | R45: =Q45-P45 -> 0 | S45: 1 | T45: =R45*S45 -> 0
H46: Side Expense In | J46: 152 | N46: 43 | P46: ='7'!Q46 -> 0 | R46: =Q46-P46 -> 0 | S46: 1 | T46: =R46*S46 -> 0
D47: Total | F47: =SUM(F44:F46) -> 0 | N47: 44 | P47: ='7'!Q47 -> 0 | R47: =Q47-P47 -> 0 | S47: 1 | T47: =R47*S47 -> 0
D48: Rebates and Commissions | N48: 45 | P48: ='7'!Q48 -> 0 | R48: =Q48-P48 -> 0 | S48: 1 | T48: =R48*S48 -> 0
D49: Description | F49: Amount | N49: 46 | P49: ='7'!Q49 -> 0 | R49: =Q49-P49 -> 0 | S49: 1 | T49: =R49*S49 -> 0
N50: 47 | P50: ='7'!Q50 -> 0 | R50: =Q50-P50 -> 0 | S50: 1 | T50: =R50*S50 -> 0
N51: 48 | P51: ='7'!Q51 -> 0 | R51: =Q51-P51 -> 0 | S51: 1 | T51: =R51*S51 -> 0
O52: Total Lottery Sale | S52: =SUM(T4:T51) -> 0
A53: Total | C53: =SUM(C44:C52) -> 0 | D53: Total | F53: =SUM(F50:F52) -> 0 | H53: TOTAL | J53: =SUM(J45:J52) -> 452 | K53: TOTAL | M53: =SUM(M45:M52) -> 109

Sheet 9
A1: ='1'!A1:F1 -> DINERO EXPRESS #8 (512) 8015655 | H1: =A1 -> DINERO EXPRESS #8 (512) 8015655 | M1: DATE
A2: Daily Report | D2: Date: | F2: ='8'!F2+1 -> 8 | H2: OTHER REPORTS | M2: =F2 -> 8 | O2: Lottery Sale
D3: Day: | M3: =F3 -> 0 | O3: Game # | P3: Open | Q3: Close | R3: Tic.Sold | S3: $ Value | T3: T. Sale
A4: Reciepts | C4: Amount | D4: Disbursments | F4: Amount | H4: MONEY TRANSFER | N4: 1 | P4: ='8'!Q4 -> 0 | R4: =Q4-P4 -> 0 | S4: 50 | T4: =R4*S4 -> 0
A5: ='1'!A5:B5 -> Taxable Sale | C5: 14 | D5: ='1'!D5:E5 -> Cash Purchases | F5: =C40 -> 0 | H5: Company | I5: Amount | J5: Fees | K5: Commission | L5: Individual Total Amount | N5: 2 | P5: ='8'!Q5 -> 0 | R5: =Q5-P5 -> 0 | S5: 20 | T5: =R5*S5 -> 0
A6: ='1'!A6:B6 -> Comm & Fee | C6: 4 | D6: ='1'!D6:E6 -> Cash Expense | F6: =F40 -> 0 | H6: ='1'!H6 -> DINEX | L6: =SUM(I6:K6) -> 0 | N6: 3 | P6: ='8'!Q6 -> 0 | R6: =Q6-P6 -> 0 | S6: 20 | T6: =R6*S6 -> 0
A7: ='1'!A7:B7 -> Sales Tax | D7: ='1'!D7:E7 -> Check Purchases | F7: =C53 -> 0 | H7: ='1'!H7 -> INTERMEX | I7: 2095.01 | J7: 74 | L7: =SUM(I7:K7) -> 2169.01 | N7: 4 | P7: ='8'!Q7 -> 0 | R7: =Q7-P7 -> 0 | S7: 10 | T7: =R7*S7 -> 0
A8: ='1'!A8:B8 -> Money Transfers | C8: =L14 -> 7827.16 | D8: ='1'!D8:E8 -> Check Expense | F8: =F47 -> 0 | H8: ='1'!H8 -> SIGUE | L8: =SUM(I8:K8) -> 0 | N8: 5 | P8: ='8'!Q8 -> 0 | R8: =Q8-P8 -> 0 | S8: 10 | T8: =R8*S8 -> 0
A9: ='1'!A9:B9 -> Lottery Sales | C9: =S52 -> 0 | D9: ='1'!D9:E9 -> Lotto Paid Out | H9: ='1'!H9 -> AFEX | L9: =SUM(I9:K9) -> 0 | N9: 6 | P9: ='8'!Q9 -> 0 | R9: =Q9-P9 -> 0 | S9: 20 | T9: =R9*S9 -> 0
A10: ='1'!A10:B10 -> Lotto Net Sales | D10: ='1'!D10:E10 -> Lottery Paid Out | H10: ='1'!H10 -> MONEYGRAM | L10: =SUM(I10:K10) -> 0 | N10: 7 | P10: ='8'!Q10 -> 0 | R10: =Q10-P10 -> 0 | S10: 20 | T10: =R10*S10 -> 0
A11: ='1'!A11:B11 -> PhoneCard | D11: ='1'!D11:E11 -> ATM Drop | H11: ='1'!H11 -> BARRI | I11: 975.38 | J11: 44 | L11: =SUM(I11:K11) -> 1019.38 | N11: 8 | P11: ='8'!Q11 -> 0 | R11: =Q11-P11 -> 0 | S11: 20 | T11: =R11*S11 -> 0
A12: ='1'!A12:B12 -> Boss Revolution | D12: ='1'!D12:E12 -> Credit Card | H12: ='1'!H12 -> MAXI | I12: 4527.77 | J12: 111 | L12: =SUM(I12:K12) -> 4638.77 | N12: 9 | P12: ='8'!Q12 -> 0 | R12: =Q12-P12 -> 0 | S12: 10 | T12: =R12*S12 -> 0
A13: ='1'!A13:B13 -> Bill Payment | D13: ='1'!D13:E13 -> Outside Cash & Drops | F13: =L40 -> 7827 | H13: ='1'!H13 -> AMIGO SIN PIN | L13: =SUM(I13:K13) -> 0 | N13: 10 | P13: ='8'!Q13 -> 0 | R13: =Q13-P13 -> 0 | S13: 10 | T13: =R13*S13 -> 0
A14: ='1'!A14:B14 -> VidaPay | D14: ='1'!D14:E14 -> Cash Deposit | H14: TOTAL | I14: =SUM(I6:I13) -> 7598.16 | J14: =SUM(J6:J13) -> 229 | K14: =SUM(K6:K13) -> 0 | L14: =SUM(L6:M13) -> 7827.16 | N14: 11 | P14: ='8'!Q14 -> 0 | R14: =Q14-P14 -> 0 | S14: 5 | T14: =R14*S14 -> 0
A15: ='1'!A15:B15 -> Boost Epay | D15: ='1'!D15:E15 -> Money Gram Payment | N15: 12 | P15: ='8'!Q15 -> 0 | R15: =Q15-P15 -> 0 | S15: 5 | T15: =R15*S15 -> 0
A16: ='1'!A16:B16 -> Epay | D16: ='1'!D16:E16 -> Vigo Payment | N16: 13 | P16: ='8'!Q16 -> 0 | R16: =Q16-P16 -> 0 | S16: 5 | T16: =R16*S16 -> 0
A17: ='1'!A17:B17 -> Check Cashing Fees | C17: 116.44 | D17: ='1'!D17:E17 -> Ria Payment | N17: 14 | P17: ='8'!Q17 -> 0 | R17: =Q17-P17 -> 0 | S17: 5 | T17: =R17*S17 -> 0
A18: ='1'!A18:B18 -> Money Order | C18: 338 | D18: ='1'!D18:E18 -> Checks Deposit | F18: =J25 -> 23288.32 | H18: CHECK DEPOSITS | K18: DROPS | L18: AMOUNT | M18: TIME | N18: 15 | P18: ='8'!Q18 -> 0 | R18: =Q18-P18 -> 0 | S18: 5 | T18: =R18*S18 -> 0
A19: ='1'!A19:B19 -> Return Check Paid | C19: =F33 -> 620 | D19: ='1'!D19:E19 -> Safe Balance | F19: 47166 | H19: CHECK DEPOSITS TO BANK | J19: AMOUNT | K19: 1 | L19: 2500 | M19: 12:35PM | N19: 16 | P19: ='8'!Q19 -> 0 | R19: =Q19-P19 -> 0 | S19: 5 | T19: =R19*S19 -> 0
A20: ='1'!A20:B20 -> Forward Balance | C20: ='8'!F19+'8'!F13 -> 49239 | D20: ='1'!D20:E20 -> Payroll Expense | F20: =J40 -> 0 | H20: NIZARI (13 Checks) | J20: 23288.32 | K20: 2 | L20: 1100 | M20: 2:14PM | N20: 17 | P20: ='8'!Q20 -> 0 | R20: =Q20-P20 -> 0 | S20: 5 | T20: =R20*S20 -> 0
A21: ='1'!A21:B21 -> Cash From Bank | C21: 20000 | D21: ='1'!D21:E21 -> Other Cash Out | F21: =M53 -> 0 | K21: 3 | L21: 2440 | M21: 5:55PM | N21: 18 | P21: ='8'!Q21 -> 0 | R21: =Q21-P21 -> 0 | S21: 5 | T21: =R21*S21 -> 0
A22: ='1'!A22:B22 -> Other Cash In | C22: =J53 -> 122 | D22: TOTAL PAYOUTS | F22: =SUM(F5:F21)-F7-F8 -> 78281.32 | K22: 4 | L22: 1787 | M22: 8:55PM | N22: 19 | P22: ='8'!Q22 -> 0 | R22: =Q22-P22 -> 0 | S22: 5 | T22: =R22*S22 -> 0
A23: ='1'!A23:B23 -> Rebates & Commissions | C23: =F53 -> 0 | D23: Inside Over - (Short) | F23: =(F11+F14+F15+F16+F17+F18+F19+F20+F21+F5+F6)-(C17+C19+C20+C21+C22+C23) -> 356.88 | K23: 5 | N23: 20 | P23: ='8'!Q23 -> 0 | R23: =Q23-P23 -> 0 | S23: 5 | T23: =R23*S23 -> 0
A24: TOTAL RECEIPTS | C24: =SUM(C5:C23) -> 78280.6 | D24: Over All Over - (Short) | F24: =SUM(F22-C24) -> 0.72 | K24: 6 | N24: 21 | P24: ='8'!Q24 -> 0 | R24: =Q24-P24 -> 0 | S24: 5 | T24: =R24*S24 -> 0
A25: Out Side Over - (Short) | C25: =(F9+F10+F12+F13)-(C5+C6+C7+C8+C9+C10+C11+C12+C13+C14+C15+C16+C18) -> -356.16 | H25: TOTAL | J25: =SUM(J20:J24) -> 23288.32 | K25: 7 | N25: 22 | P25: ='8'!Q25 -> 0 | R25: =Q25-P25 -> 0 | S25: 5 | T25: =R25*S25 -> 0
A26: Cash Purchases | D26: Return Check Paid | K26: 8 | N26: 23 | P26: ='8'!Q26 -> 0 | R26: =Q26-P26 -> 0 | S26: 3 | T26: =R26*S26 -> 0
A27: Description | C27: Amount | D27: Description | F27: Amount | K27: 9 | N27: 24 | P27: ='8'!Q27 -> 0 | R27: =Q27-P27 -> 0 | S27: 3 | T27: =R27*S27 -> 0
D28: Ranger Print House #1733 | F28: 620 | H28: CASH PAYROLL EXPENSE | K28: 10 | N28: 25 | P28: ='8'!Q28 -> 0 | R28: =Q28-P28 -> 0 | S28: 2 | T28: =R28*S28 -> 0
H29: CASH PAYROLL PAID TO | J29: AMOUNT | K29: 11 | N29: 26 | P29: ='8'!Q29 -> 0 | R29: =Q29-P29 -> 0 | S29: 5 | T29: =R29*S29 -> 0
K30: 12 | N30: 27 | P30: ='8'!Q30 -> 0 | R30: =Q30-P30 -> 0 | S30: 3 | T30: =R30*S30 -> 0
K31: 13 | N31: 28 | P31: ='8'!Q31 -> 0 | R31: =Q31-P31 -> 0 | S31: 3 | T31: =R31*S31 -> 0
K32: 14 | N32: 29 | P32: ='8'!Q32 -> 0 | R32: =Q32-P32 -> 0 | S32: 2 | T32: =R32*S32 -> 0
D33: Total | F33: =SUM(F28:F32) -> 620 | K33: 15 | N33: 30 | P33: ='8'!Q33 -> 0 | R33: =Q33-P33 -> 0 | S33: 2 | T33: =R33*S33 -> 0
D34: Cash Expense | K34: 16 | N34: 31 | P34: ='8'!Q34 -> 0 | R34: =Q34-P34 -> 0 | S34: 2 | T34: =R34*S34 -> 0
D35: Description | F35: Amount | K35: 17 | N35: 32 | P35: ='8'!Q35 -> 0 | R35: =Q35-P35 -> 0 | S35: 2 | T35: =R35*S35 -> 0
K36: 18 | N36: 33 | P36: ='8'!Q36 -> 0 | R36: =Q36-P36 -> 0 | S36: 2 | T36: =R36*S36 -> 0
K37: 19 | N37: 34 | P37: ='8'!Q37 -> 0 | R37: =Q37-P37 -> 0 | S37: 1 | T37: =R37*S37 -> 0
K38: 20 | N38: 35 | P38: ='8'!Q38 -> 0 | R38: =Q38-P38 -> 0 | S38: 1 | T38: =R38*S38 -> 0
K39: 21 | N39: 36 | P39: ='8'!Q39 -> 0 | R39: =Q39-P39 -> 0 | S39: 2 | T39: =R39*S39 -> 0
A40: Total | C40: =SUM(C28:C39) -> 0 | D40: Total | F40: =SUM(F36:F39) -> 0 | H40: TOTAL | J40: =SUM(J30:J39) -> 0 | K40: TOTAL | L40: =SUM(L19:L39) -> 7827 | N40: 37 | P40: ='8'!Q40 -> 0 | R40: =Q40-P40 -> 0 | S40: 2 | T40: =R40*S40 -> 0
N41: 38 | P41: ='8'!Q41 -> 0 | R41: =Q41-P41 -> 0 | S41: 2 | T41: =R41*S41 -> 0
A42: Check Purchases | D42: Check Expenses | N42: 39 | P42: ='8'!Q42 -> 0 | R42: =Q42-P42 -> 0 | S42: 1 | T42: =R42*S42 -> 0
A43: Description | B43: Check | C43: Amount | D43: Description | E43: Check | F43: Amount | H43: CASH IN | K43: CASH OUT TO OTHER | N43: 40 | P43: ='8'!Q43 -> 0 | R43: =Q43-P43 -> 0 | S43: 1 | T43: =R43*S43 -> 0
H44: CASH IN FROM | J44: AMOUNT | K44: OTHER CASH OUT | M44: AMOUNT | N44: 41 | P44: ='8'!Q44 -> 0 | R44: =Q44-P44 -> 0 | S44: 10 | T44: =R44*S44 -> 0
H45: Side Expense In | J45: 122 | N45: 42 | P45: ='8'!Q45 -> 0 | R45: =Q45-P45 -> 0 | S45: 1 | T45: =R45*S45 -> 0
N46: 43 | P46: ='8'!Q46 -> 0 | R46: =Q46-P46 -> 0 | S46: 1 | T46: =R46*S46 -> 0
D47: Total | F47: =SUM(F44:F46) -> 0 | N47: 44 | P47: ='8'!Q47 -> 0 | R47: =Q47-P47 -> 0 | S47: 1 | T47: =R47*S47 -> 0
D48: Rebates and Commissions | N48: 45 | P48: ='8'!Q48 -> 0 | R48: =Q48-P48 -> 0 | S48: 1 | T48: =R48*S48 -> 0
D49: Description | F49: Amount | N49: 46 | P49: ='8'!Q49 -> 0 | R49: =Q49-P49 -> 0 | S49: 1 | T49: =R49*S49 -> 0
N50: 47 | P50: ='8'!Q50 -> 0 | R50: =Q50-P50 -> 0 | S50: 1 | T50: =R50*S50 -> 0
N51: 48 | P51: ='8'!Q51 -> 0 | R51: =Q51-P51 -> 0 | S51: 1 | T51: =R51*S51 -> 0
O52: Total Lottery Sale | S52: =SUM(T4:T51) -> 0
A53: Total | C53: =SUM(C44:C52) -> 0 | D53: Total | F53: =SUM(F50:F52) -> 0 | H53: TOTAL | J53: =SUM(J45:J52) -> 122 | K53: TOTAL | M53: =SUM(M45:M52) -> 0

Sheet 10
A1: ='1'!A1:F1 -> DINERO EXPRESS #8 (512) 8015655 | H1: =A1 -> DINERO EXPRESS #8 (512) 8015655 | M1: DATE
A2: Daily Report | D2: Date: | F2: ='9'!F2+1 -> 9 | H2: OTHER REPORTS | M2: =F2 -> 9 | O2: Lottery Sale
D3: Day: | M3: =F3 -> 0 | O3: Game # | P3: Open | Q3: Close | R3: Tic.Sold | S3: $ Value | T3: T. Sale
A4: Reciepts | C4: Amount | D4: Disbursments | F4: Amount | H4: MONEY TRANSFER | N4: 1 | P4: ='9'!Q4 -> 0 | R4: =Q4-P4 -> 0 | S4: 50 | T4: =R4*S4 -> 0
A5: ='1'!A5:B5 -> Taxable Sale | C5: 225 | D5: ='1'!D5:E5 -> Cash Purchases | F5: =C40 -> 0 | H5: Company | I5: Amount | J5: Fees | K5: Commission | L5: Individual Total Amount | N5: 2 | P5: ='9'!Q5 -> 0 | R5: =Q5-P5 -> 0 | S5: 20 | T5: =R5*S5 -> 0
A6: ='1'!A6:B6 -> Comm & Fee | D6: ='1'!D6:E6 -> Cash Expense | F6: =F40 -> 0 | H6: ='1'!H6 -> DINEX | L6: =SUM(I6:K6) -> 0 | N6: 3 | P6: ='9'!Q6 -> 0 | R6: =Q6-P6 -> 0 | S6: 20 | T6: =R6*S6 -> 0
A7: ='1'!A7:B7 -> Sales Tax | D7: ='1'!D7:E7 -> Check Purchases | F7: =C53 -> 0 | H7: ='1'!H7 -> INTERMEX | I7: 5665.05 | J7: 164.75 | L7: =SUM(I7:K7) -> 5829.8 | N7: 4 | P7: ='9'!Q7 -> 0 | R7: =Q7-P7 -> 0 | S7: 10 | T7: =R7*S7 -> 0
A8: ='1'!A8:B8 -> Money Transfers | C8: =L14 -> 15055.56 | D8: ='1'!D8:E8 -> Check Expense | F8: =F47 -> 0 | H8: ='1'!H8 -> SIGUE | L8: =SUM(I8:K8) -> 0 | N8: 5 | P8: ='9'!Q8 -> 0 | R8: =Q8-P8 -> 0 | S8: 10 | T8: =R8*S8 -> 0
A9: ='1'!A9:B9 -> Lottery Sales | C9: =S52 -> 0 | D9: ='1'!D9:E9 -> Lotto Paid Out | H9: ='1'!H9 -> AFEX | L9: =SUM(I9:K9) -> 0 | N9: 6 | P9: ='9'!Q9 -> 0 | R9: =Q9-P9 -> 0 | S9: 20 | T9: =R9*S9 -> 0
A10: ='1'!A10:B10 -> Lotto Net Sales | D10: ='1'!D10:E10 -> Lottery Paid Out | H10: ='1'!H10 -> MONEYGRAM | L10: =SUM(I10:K10) -> 0 | N10: 7 | P10: ='9'!Q10 -> 0 | R10: =Q10-P10 -> 0 | S10: 20 | T10: =R10*S10 -> 0
A11: ='1'!A11:B11 -> PhoneCard | D11: ='1'!D11:E11 -> ATM Drop | H11: ='1'!H11 -> BARRI | I11: 1762 | J11: 48 | L11: =SUM(I11:K11) -> 1810 | N11: 8 | P11: ='9'!Q11 -> 0 | R11: =Q11-P11 -> 0 | S11: 20 | T11: =R11*S11 -> 0
A12: ='1'!A12:B12 -> Boss Revolution | D12: ='1'!D12:E12 -> Credit Card | H12: ='1'!H12 -> MAXI | I12: 7265.76 | J12: 150 | L12: =SUM(I12:K12) -> 7415.76 | N12: 9 | P12: ='9'!Q12 -> 0 | R12: =Q12-P12 -> 0 | S12: 10 | T12: =R12*S12 -> 0
A13: ='1'!A13:B13 -> Bill Payment | D13: ='1'!D13:E13 -> Outside Cash & Drops | F13: =L40 -> 15056 | H13: ='1'!H13 -> AMIGO SIN PIN | L13: =SUM(I13:K13) -> 0 | N13: 10 | P13: ='9'!Q13 -> 0 | R13: =Q13-P13 -> 0 | S13: 10 | T13: =R13*S13 -> 0
A14: ='1'!A14:B14 -> VidaPay | D14: ='1'!D14:E14 -> Cash Deposit | H14: TOTAL | I14: =SUM(I6:I13) -> 14692.81 | J14: =SUM(J6:J13) -> 362.75 | K14: =SUM(K6:K13) -> 0 | L14: =SUM(L6:M13) -> 15055.56 | N14: 11 | P14: ='9'!Q14 -> 0 | R14: =Q14-P14 -> 0 | S14: 5 | T14: =R14*S14 -> 0
A15: ='1'!A15:B15 -> Boost Epay | D15: ='1'!D15:E15 -> Money Gram Payment | N15: 12 | P15: ='9'!Q15 -> 0 | R15: =Q15-P15 -> 0 | S15: 5 | T15: =R15*S15 -> 0
A16: ='1'!A16:B16 -> Epay | D16: ='1'!D16:E16 -> Vigo Payment | N16: 13 | P16: ='9'!Q16 -> 0 | R16: =Q16-P16 -> 0 | S16: 5 | T16: =R16*S16 -> 0
A17: ='1'!A17:B17 -> Check Cashing Fees | C17: 525.27 | D17: ='1'!D17:E17 -> Ria Payment | N17: 14 | P17: ='9'!Q17 -> 0 | R17: =Q17-P17 -> 0 | S17: 5 | T17: =R17*S17 -> 0
A18: ='1'!A18:B18 -> Money Order | D18: ='1'!D18:E18 -> Checks Deposit | F18: =J25 -> 68666.06 | H18: CHECK DEPOSITS | K18: DROPS | L18: AMOUNT | M18: TIME | N18: 15 | P18: ='9'!Q18 -> 0 | R18: =Q18-P18 -> 0 | S18: 5 | T18: =R18*S18 -> 0
A19: ='1'!A19:B19 -> Return Check Paid | C19: =F33 -> 0 | D19: ='1'!D19:E19 -> Safe Balance | F19: 76931 | H19: CHECK DEPOSITS TO BANK | J19: AMOUNT | K19: 1 | L19: 5340 | M19: 4:48PM | N19: 16 | P19: ='9'!Q19 -> 0 | R19: =Q19-P19 -> 0 | S19: 5 | T19: =R19*S19 -> 0
A20: ='1'!A20:B20 -> Forward Balance | C20: ='9'!F19+'9'!F13 -> 54993 | D20: ='1'!D20:E20 -> Payroll Expense | F20: =J40 -> 0 | H20: NIZARI (2 Checks) | J20: 5281 | K20: 2 | L20: 3450 | M20: 6:22PM | N20: 17 | P20: ='9'!Q20 -> 0 | R20: =Q20-P20 -> 0 | S20: 5 | T20: =R20*S20 -> 0
A21: ='1'!A21:B21 -> Cash From Bank | C21: 129500 | D21: ='1'!D21:E21 -> Other Cash Out | F21: =M53 -> 40197 | H21: NIZARI (44 Checks) | J21: 63385.06 | K21: 3 | L21: 6130 | M21: 8:35PM | N21: 18 | P21: ='9'!Q21 -> 0 | R21: =Q21-P21 -> 0 | S21: 5 | T21: =R21*S21 -> 0
A22: ='1'!A22:B22 -> Other Cash In | C22: =J53 -> 551 | D22: TOTAL PAYOUTS | F22: =SUM(F5:F21)-F7-F8 -> 200850.06 | K22: 4 | L22: 136 | M22: 9:18PM | N22: 19 | P22: ='9'!Q22 -> 0 | R22: =Q22-P22 -> 0 | S22: 5 | T22: =R22*S22 -> 0
A23: ='1'!A23:B23 -> Rebates & Commissions | C23: =F53 -> 0 | D23: Inside Over - (Short) | F23: =(F11+F14+F15+F16+F17+F18+F19+F20+F21+F5+F6)-(C17+C19+C20+C21+C22+C23) -> 224.79 | K23: 5 | N23: 20 | P23: ='9'!Q23 -> 0 | R23: =Q23-P23 -> 0 | S23: 5 | T23: =R23*S23 -> 0
A24: TOTAL RECEIPTS | C24: =SUM(C5:C23) -> 200849.83 | D24: Over All Over - (Short) | F24: =SUM(F22-C24) -> 0.23 | K24: 6 | N24: 21 | P24: ='9'!Q24 -> 0 | R24: =Q24-P24 -> 0 | S24: 5 | T24: =R24*S24 -> 0
A25: Out Side Over - (Short) | C25: =(F9+F10+F12+F13)-(C5+C6+C7+C8+C9+C10+C11+C12+C13+C14+C15+C16+C18) -> -224.56 | H25: TOTAL | J25: =SUM(J20:J24) -> 68666.06 | K25: 7 | N25: 22 | P25: ='9'!Q25 -> 0 | R25: =Q25-P25 -> 0 | S25: 5 | T25: =R25*S25 -> 0
A26: Cash Purchases | D26: Return Check Paid | K26: 8 | N26: 23 | P26: ='9'!Q26 -> 0 | R26: =Q26-P26 -> 0 | S26: 3 | T26: =R26*S26 -> 0
A27: Description | C27: Amount | D27: Description | F27: Amount | K27: 9 | N27: 24 | P27: ='9'!Q27 -> 0 | R27: =Q27-P27 -> 0 | S27: 3 | T27: =R27*S27 -> 0
H28: CASH PAYROLL EXPENSE | K28: 10 | N28: 25 | P28: ='9'!Q28 -> 0 | R28: =Q28-P28 -> 0 | S28: 2 | T28: =R28*S28 -> 0
H29: CASH PAYROLL PAID TO | J29: AMOUNT | K29: 11 | N29: 26 | P29: ='9'!Q29 -> 0 | R29: =Q29-P29 -> 0 | S29: 5 | T29: =R29*S29 -> 0
K30: 12 | N30: 27 | P30: ='9'!Q30 -> 0 | R30: =Q30-P30 -> 0 | S30: 3 | T30: =R30*S30 -> 0
K31: 13 | N31: 28 | P31: ='9'!Q31 -> 0 | R31: =Q31-P31 -> 0 | S31: 3 | T31: =R31*S31 -> 0
K32: 14 | N32: 29 | P32: ='9'!Q32 -> 0 | R32: =Q32-P32 -> 0 | S32: 2 | T32: =R32*S32 -> 0
D33: Total | F33: =SUM(F28:F32) -> 0 | K33: 15 | N33: 30 | P33: ='9'!Q33 -> 0 | R33: =Q33-P33 -> 0 | S33: 2 | T33: =R33*S33 -> 0
D34: Cash Expense | K34: 16 | N34: 31 | P34: ='9'!Q34 -> 0 | R34: =Q34-P34 -> 0 | S34: 2 | T34: =R34*S34 -> 0
D35: Description | F35: Amount | K35: 17 | N35: 32 | P35: ='9'!Q35 -> 0 | R35: =Q35-P35 -> 0 | S35: 2 | T35: =R35*S35 -> 0
K36: 18 | N36: 33 | P36: ='9'!Q36 -> 0 | R36: =Q36-P36 -> 0 | S36: 2 | T36: =R36*S36 -> 0
K37: 19 | N37: 34 | P37: ='9'!Q37 -> 0 | R37: =Q37-P37 -> 0 | S37: 1 | T37: =R37*S37 -> 0
K38: 20 | N38: 35 | P38: ='9'!Q38 -> 0 | R38: =Q38-P38 -> 0 | S38: 1 | T38: =R38*S38 -> 0
K39: 21 | N39: 36 | P39: ='9'!Q39 -> 0 | R39: =Q39-P39 -> 0 | S39: 2 | T39: =R39*S39 -> 0
A40: Total | C40: =SUM(C28:C39) -> 0 | D40: Total | F40: =SUM(F36:F39) -> 0 | H40: TOTAL | J40: =SUM(J30:J39) -> 0 | K40: TOTAL | L40: =SUM(L19:L39) -> 15056 | N40: 37 | P40: ='9'!Q40 -> 0 | R40: =Q40-P40 -> 0 | S40: 2 | T40: =R40*S40 -> 0
N41: 38 | P41: ='9'!Q41 -> 0 | R41: =Q41-P41 -> 0 | S41: 2 | T41: =R41*S41 -> 0
A42: Check Purchases | D42: Check Expenses | N42: 39 | P42: ='9'!Q42 -> 0 | R42: =Q42-P42 -> 0 | S42: 1 | T42: =R42*S42 -> 0
A43: Description | B43: Check | C43: Amount | D43: Description | E43: Check | F43: Amount | H43: CASH IN | K43: CASH OUT TO OTHER | N43: 40 | P43: ='9'!Q43 -> 0 | R43: =Q43-P43 -> 0 | S43: 1 | T43: =R43*S43 -> 0
H44: CASH IN FROM | J44: AMOUNT | K44: OTHER CASH OUT | M44: AMOUNT | N44: 41 | P44: ='9'!Q44 -> 0 | R44: =Q44-P44 -> 0 | S44: 10 | T44: =R44*S44 -> 0
H45: Side Expense In | J45: 551 | K45: LED Logistics LLC (21 Checks) | M45: 39897 | N45: 42 | P45: ='9'!Q45 -> 0 | R45: =Q45-P45 -> 0 | S45: 1 | T45: =R45*S45 -> 0
K46: Raquel Out | M46: 300 | N46: 43 | P46: ='9'!Q46 -> 0 | R46: =Q46-P46 -> 0 | S46: 1 | T46: =R46*S46 -> 0
D47: Total | F47: =SUM(F44:F46) -> 0 | N47: 44 | P47: ='9'!Q47 -> 0 | R47: =Q47-P47 -> 0 | S47: 1 | T47: =R47*S47 -> 0
D48: Rebates and Commissions | N48: 45 | P48: ='9'!Q48 -> 0 | R48: =Q48-P48 -> 0 | S48: 1 | T48: =R48*S48 -> 0
D49: Description | F49: Amount | N49: 46 | P49: ='9'!Q49 -> 0 | R49: =Q49-P49 -> 0 | S49: 1 | T49: =R49*S49 -> 0
N50: 47 | P50: ='9'!Q50 -> 0 | R50: =Q50-P50 -> 0 | S50: 1 | T50: =R50*S50 -> 0
N51: 48 | P51: ='9'!Q51 -> 0 | R51: =Q51-P51 -> 0 | S51: 1 | T51: =R51*S51 -> 0
O52: Total Lottery Sale | S52: =SUM(T4:T51) -> 0
A53: Total | C53: =SUM(C44:C52) -> 0 | D53: Total | F53: =SUM(F50:F52) -> 0 | H53: TOTAL | J53: =SUM(J45:J52) -> 551 | K53: TOTAL | M53: =SUM(M45:M52) -> 40197

Sheet 11
A1: ='1'!A1:F1 -> DINERO EXPRESS #8 (512) 8015655 | H1: =A1 -> DINERO EXPRESS #8 (512) 8015655 | M1: DATE
A2: Daily Report | D2: Date: | F2: ='10'!F2+1 -> 10 | H2: OTHER REPORTS | M2: =F2 -> 10 | O2: Lottery Sale
D3: Day: | M3: =F3 -> 0 | O3: Game # | P3: Open | Q3: Close | R3: Tic.Sold | S3: $ Value | T3: T. Sale
A4: Reciepts | C4: Amount | D4: Disbursments | F4: Amount | H4: MONEY TRANSFER | N4: 1 | P4: ='10'!Q4 -> 0 | R4: =Q4-P4 -> 0 | S4: 50 | T4: =R4*S4 -> 0
A5: ='1'!A5:B5 -> Taxable Sale | C5: 54 | D5: ='1'!D5:E5 -> Cash Purchases | F5: =C40 -> 0 | H5: Company | I5: Amount | J5: Fees | K5: Commission | L5: Individual Total Amount | N5: 2 | P5: ='10'!Q5 -> 0 | R5: =Q5-P5 -> 0 | S5: 20 | T5: =R5*S5 -> 0
A6: ='1'!A6:B6 -> Comm & Fee | D6: ='1'!D6:E6 -> Cash Expense | F6: =F40 -> 0 | H6: ='1'!H6 -> DINEX | L6: =SUM(I6:K6) -> 0 | N6: 3 | P6: ='10'!Q6 -> 0 | R6: =Q6-P6 -> 0 | S6: 20 | T6: =R6*S6 -> 0
A7: ='1'!A7:B7 -> Sales Tax | D7: ='1'!D7:E7 -> Check Purchases | F7: =C53 -> 0 | H7: ='1'!H7 -> INTERMEX | I7: 6487.93 | J7: 186 | L7: =SUM(I7:K7) -> 6673.93 | N7: 4 | P7: ='10'!Q7 -> 0 | R7: =Q7-P7 -> 0 | S7: 10 | T7: =R7*S7 -> 0
A8: ='1'!A8:B8 -> Money Transfers | C8: =L14 -> 12364.59 | D8: ='1'!D8:E8 -> Check Expense | F8: =F47 -> 0 | H8: ='1'!H8 -> SIGUE | L8: =SUM(I8:K8) -> 0 | N8: 5 | P8: ='10'!Q8 -> 0 | R8: =Q8-P8 -> 0 | S8: 10 | T8: =R8*S8 -> 0
A9: ='1'!A9:B9 -> Lottery Sales | C9: =S52 -> 0 | D9: ='1'!D9:E9 -> Lotto Paid Out | H9: ='1'!H9 -> AFEX | L9: =SUM(I9:K9) -> 0 | N9: 6 | P9: ='10'!Q9 -> 0 | R9: =Q9-P9 -> 0 | S9: 20 | T9: =R9*S9 -> 0
A10: ='1'!A10:B10 -> Lotto Net Sales | D10: ='1'!D10:E10 -> Lottery Paid Out | H10: ='1'!H10 -> MONEYGRAM | L10: =SUM(I10:K10) -> 0 | N10: 7 | P10: ='10'!Q10 -> 0 | R10: =Q10-P10 -> 0 | S10: 20 | T10: =R10*S10 -> 0
A11: ='1'!A11:B11 -> PhoneCard | D11: ='1'!D11:E11 -> ATM Drop | H11: ='1'!H11 -> BARRI | I11: 2706.65 | J11: 60 | L11: =SUM(I11:K11) -> 2766.65 | N11: 8 | P11: ='10'!Q11 -> 0 | R11: =Q11-P11 -> 0 | S11: 20 | T11: =R11*S11 -> 0
A12: ='1'!A12:B12 -> Boss Revolution | D12: ='1'!D12:E12 -> Credit Card | H12: ='1'!H12 -> MAXI | I12: 2812.01 | J12: 112 | L12: =SUM(I12:K12) -> 2924.01 | N12: 9 | P12: ='10'!Q12 -> 0 | R12: =Q12-P12 -> 0 | S12: 10 | T12: =R12*S12 -> 0
A13: ='1'!A13:B13 -> Bill Payment | D13: ='1'!D13:E13 -> Outside Cash & Drops | F13: =L40 -> 12350 | H13: ='1'!H13 -> AMIGO SIN PIN | L13: =SUM(I13:K13) -> 0 | N13: 10 | P13: ='10'!Q13 -> 0 | R13: =Q13-P13 -> 0 | S13: 10 | T13: =R13*S13 -> 0
A14: ='1'!A14:B14 -> VidaPay | D14: ='1'!D14:E14 -> Cash Deposit | H14: TOTAL | I14: =SUM(I6:I13) -> 12006.59 | J14: =SUM(J6:J13) -> 358 | K14: =SUM(K6:K13) -> 0 | L14: =SUM(L6:M13) -> 12364.59 | N14: 11 | P14: ='10'!Q14 -> 0 | R14: =Q14-P14 -> 0 | S14: 5 | T14: =R14*S14 -> 0
A15: ='1'!A15:B15 -> Boost Epay | D15: ='1'!D15:E15 -> Money Gram Payment | N15: 12 | P15: ='10'!Q15 -> 0 | R15: =Q15-P15 -> 0 | S15: 5 | T15: =R15*S15 -> 0
A16: ='1'!A16:B16 -> Epay | D16: ='1'!D16:E16 -> Vigo Payment | N16: 13 | P16: ='10'!Q16 -> 0 | R16: =Q16-P16 -> 0 | S16: 5 | T16: =R16*S16 -> 0
A17: ='1'!A17:B17 -> Check Cashing Fees | C17: 277.2 | D17: ='1'!D17:E17 -> Ria Payment | N17: 14 | P17: ='10'!Q17 -> 0 | R17: =Q17-P17 -> 0 | S17: 5 | T17: =R17*S17 -> 0
A18: ='1'!A18:B18 -> Money Order | D18: ='1'!D18:E18 -> Checks Deposit | F18: =J25 -> 53559.4 | H18: CHECK DEPOSITS | K18: DROPS | L18: AMOUNT | M18: TIME | N18: 15 | P18: ='10'!Q18 -> 0 | R18: =Q18-P18 -> 0 | S18: 5 | T18: =R18*S18 -> 0
A19: ='1'!A19:B19 -> Return Check Paid | C19: =F33 -> 0 | D19: ='1'!D19:E19 -> Safe Balance | F19: 36874 | H19: CHECK DEPOSITS TO BANK | J19: AMOUNT | K19: 1 | L19: 3960 | M19: 4:35PM | N19: 16 | P19: ='10'!Q19 -> 0 | R19: =Q19-P19 -> 0 | S19: 5 | T19: =R19*S19 -> 0
A20: ='1'!A20:B20 -> Forward Balance | C20: ='10'!F19+'10'!F13 -> 91987 | D20: ='1'!D20:E20 -> Payroll Expense | F20: =J40 -> 0 | H20: NIZARI (1 Check) In-Person Dep | J20: 12445.44 | K20: 2 | L20: 4210 | M20: 6:32PM | N20: 17 | P20: ='10'!Q20 -> 0 | R20: =Q20-P20 -> 0 | S20: 5 | T20: =R20*S20 -> 0
A21: ='1'!A21:B21 -> Cash From Bank | D21: ='1'!D21:E21 -> Other Cash Out | F21: =M53 -> 1900 | H21: NIZARI (3 Checks) | J21: 4007.71 | K21: 3 | L21: 4040 | M21: 8:19PM | N21: 18 | P21: ='10'!Q21 -> 0 | R21: =Q21-P21 -> 0 | S21: 5 | T21: =R21*S21 -> 0
A22: ='1'!A22:B22 -> Other Cash In | C22: =J53 -> 0 | D22: TOTAL PAYOUTS | F22: =SUM(F5:F21)-F7-F8 -> 104683.4 | H22: NIZARI (23 Checks) | J22: 21316.05 | K22: 4 | L22: 140 | M22: 9:02PM | N22: 19 | P22: ='10'!Q22 -> 0 | R22: =Q22-P22 -> 0 | S22: 5 | T22: =R22*S22 -> 0
A23: ='1'!A23:B23 -> Rebates & Commissions | C23: =F53 -> 0 | D23: Inside Over - (Short) | F23: =(F11+F14+F15+F16+F17+F18+F19+F20+F21+F5+F6)-(C17+C19+C20+C21+C22+C23) -> 69.2 | H23: NIZARI (9 Checks) | J23: 15790.2 | K23: 5 | N23: 20 | P23: ='10'!Q23 -> 0 | R23: =Q23-P23 -> 0 | S23: 5 | T23: =R23*S23 -> 0
A24: TOTAL RECEIPTS | C24: =SUM(C5:C23) -> 104682.79 | D24: Over All Over - (Short) | F24: =SUM(F22-C24) -> 0.61 | K24: 6 | N24: 21 | P24: ='10'!Q24 -> 0 | R24: =Q24-P24 -> 0 | S24: 5 | T24: =R24*S24 -> 0
A25: Out Side Over - (Short) | C25: =(F9+F10+F12+F13)-(C5+C6+C7+C8+C9+C10+C11+C12+C13+C14+C15+C16+C18) -> -68.59 | H25: TOTAL | J25: =SUM(J20:J24) -> 53559.4 | K25: 7 | N25: 22 | P25: ='10'!Q25 -> 0 | R25: =Q25-P25 -> 0 | S25: 5 | T25: =R25*S25 -> 0
A26: Cash Purchases | D26: Return Check Paid | K26: 8 | N26: 23 | P26: ='10'!Q26 -> 0 | R26: =Q26-P26 -> 0 | S26: 3 | T26: =R26*S26 -> 0
A27: Description | C27: Amount | D27: Description | F27: Amount | K27: 9 | N27: 24 | P27: ='10'!Q27 -> 0 | R27: =Q27-P27 -> 0 | S27: 3 | T27: =R27*S27 -> 0
H28: CASH PAYROLL EXPENSE | K28: 10 | N28: 25 | P28: ='10'!Q28 -> 0 | R28: =Q28-P28 -> 0 | S28: 2 | T28: =R28*S28 -> 0
H29: CASH PAYROLL PAID TO | J29: AMOUNT | K29: 11 | N29: 26 | P29: ='10'!Q29 -> 0 | R29: =Q29-P29 -> 0 | S29: 5 | T29: =R29*S29 -> 0
K30: 12 | N30: 27 | P30: ='10'!Q30 -> 0 | R30: =Q30-P30 -> 0 | S30: 3 | T30: =R30*S30 -> 0
K31: 13 | N31: 28 | P31: ='10'!Q31 -> 0 | R31: =Q31-P31 -> 0 | S31: 3 | T31: =R31*S31 -> 0
K32: 14 | N32: 29 | P32: ='10'!Q32 -> 0 | R32: =Q32-P32 -> 0 | S32: 2 | T32: =R32*S32 -> 0
D33: Total | F33: =SUM(F28:F32) -> 0 | K33: 15 | N33: 30 | P33: ='10'!Q33 -> 0 | R33: =Q33-P33 -> 0 | S33: 2 | T33: =R33*S33 -> 0
D34: Cash Expense | K34: 16 | N34: 31 | P34: ='10'!Q34 -> 0 | R34: =Q34-P34 -> 0 | S34: 2 | T34: =R34*S34 -> 0
D35: Description | F35: Amount | K35: 17 | N35: 32 | P35: ='10'!Q35 -> 0 | R35: =Q35-P35 -> 0 | S35: 2 | T35: =R35*S35 -> 0
K36: 18 | N36: 33 | P36: ='10'!Q36 -> 0 | R36: =Q36-P36 -> 0 | S36: 2 | T36: =R36*S36 -> 0
K37: 19 | N37: 34 | P37: ='10'!Q37 -> 0 | R37: =Q37-P37 -> 0 | S37: 1 | T37: =R37*S37 -> 0
K38: 20 | N38: 35 | P38: ='10'!Q38 -> 0 | R38: =Q38-P38 -> 0 | S38: 1 | T38: =R38*S38 -> 0
K39: 21 | N39: 36 | P39: ='10'!Q39 -> 0 | R39: =Q39-P39 -> 0 | S39: 2 | T39: =R39*S39 -> 0
A40: Total | C40: =SUM(C28:C39) -> 0 | D40: Total | F40: =SUM(F36:F39) -> 0 | H40: TOTAL | J40: =SUM(J30:J39) -> 0 | K40: TOTAL | L40: =SUM(L19:L39) -> 12350 | N40: 37 | P40: ='10'!Q40 -> 0 | R40: =Q40-P40 -> 0 | S40: 2 | T40: =R40*S40 -> 0
N41: 38 | P41: ='10'!Q41 -> 0 | R41: =Q41-P41 -> 0 | S41: 2 | T41: =R41*S41 -> 0
A42: Check Purchases | D42: Check Expenses | N42: 39 | P42: ='10'!Q42 -> 0 | R42: =Q42-P42 -> 0 | S42: 1 | T42: =R42*S42 -> 0
A43: Description | B43: Check | C43: Amount | D43: Description | E43: Check | F43: Amount | H43: CASH IN | K43: CASH OUT TO OTHER | N43: 40 | P43: ='10'!Q43 -> 0 | R43: =Q43-P43 -> 0 | S43: 1 | T43: =R43*S43 -> 0
H44: CASH IN FROM | J44: AMOUNT | K44: OTHER CASH OUT | M44: AMOUNT | N44: 41 | P44: ='10'!Q44 -> 0 | R44: =Q44-P44 -> 0 | S44: 10 | T44: =R44*S44 -> 0
K45: LED Logistics LLC (2 Checks) | M45: 1880 | N45: 42 | P45: ='10'!Q45 -> 0 | R45: =Q45-P45 -> 0 | S45: 1 | T45: =R45*S45 -> 0
K46: Game Machine | M46: 20 | N46: 43 | P46: ='10'!Q46 -> 0 | R46: =Q46-P46 -> 0 | S46: 1 | T46: =R46*S46 -> 0
D47: Total | F47: =SUM(F44:F46) -> 0 | N47: 44 | P47: ='10'!Q47 -> 0 | R47: =Q47-P47 -> 0 | S47: 1 | T47: =R47*S47 -> 0
D48: Rebates and Commissions | N48: 45 | P48: ='10'!Q48 -> 0 | R48: =Q48-P48 -> 0 | S48: 1 | T48: =R48*S48 -> 0
D49: Description | F49: Amount | N49: 46 | P49: ='10'!Q49 -> 0 | R49: =Q49-P49 -> 0 | S49: 1 | T49: =R49*S49 -> 0
N50: 47 | P50: ='10'!Q50 -> 0 | R50: =Q50-P50 -> 0 | S50: 1 | T50: =R50*S50 -> 0
N51: 48 | P51: ='10'!Q51 -> 0 | R51: =Q51-P51 -> 0 | S51: 1 | T51: =R51*S51 -> 0
O52: Total Lottery Sale | S52: =SUM(T4:T51) -> 0
A53: Total | C53: =SUM(C44:C52) -> 0 | D53: Total | F53: =SUM(F50:F52) -> 0 | H53: TOTAL | J53: =SUM(J45:J52) -> 0 | K53: TOTAL | M53: =SUM(M45:M52) -> 1900

Sheet 12
A1: ='1'!A1:F1 -> DINERO EXPRESS #8 (512) 8015655 | H1: =A1 -> DINERO EXPRESS #8 (512) 8015655 | M1: DATE
A2: Daily Report | D2: Date: | F2: ='11'!F2+1 -> 11 | H2: OTHER REPORTS | M2: =F2 -> 11 | O2: Lottery Sale
D3: Day: | M3: =F3 -> 0 | O3: Game # | P3: Open | Q3: Close | R3: Tic.Sold | S3: $ Value | T3: T. Sale
A4: Reciepts | C4: Amount | D4: Disbursments | F4: Amount | H4: MONEY TRANSFER | N4: 1 | P4: ='11'!Q4 -> 0 | R4: =Q4-P4 -> 0 | S4: 50 | T4: =R4*S4 -> 0
A5: ='1'!A5:B5 -> Taxable Sale | C5: 71 | D5: ='1'!D5:E5 -> Cash Purchases | F5: =C40 -> 0 | H5: Company | I5: Amount | J5: Fees | K5: Commission | L5: Individual Total Amount | N5: 2 | P5: ='11'!Q5 -> 0 | R5: =Q5-P5 -> 0 | S5: 20 | T5: =R5*S5 -> 0
A6: ='1'!A6:B6 -> Comm & Fee | D6: ='1'!D6:E6 -> Cash Expense | F6: =F40 -> 0 | H6: ='1'!H6 -> DINEX | L6: =SUM(I6:K6) -> 0 | N6: 3 | P6: ='11'!Q6 -> 0 | R6: =Q6-P6 -> 0 | S6: 20 | T6: =R6*S6 -> 0
A7: ='1'!A7:B7 -> Sales Tax | D7: ='1'!D7:E7 -> Check Purchases | F7: =C53 -> 0 | H7: ='1'!H7 -> INTERMEX | I7: 11752.69 | J7: 217.61 | L7: =SUM(I7:K7) -> 11970.3 | N7: 4 | P7: ='11'!Q7 -> 0 | R7: =Q7-P7 -> 0 | S7: 10 | T7: =R7*S7 -> 0
A8: ='1'!A8:B8 -> Money Transfers | C8: =L14 -> 17140.15 | D8: ='1'!D8:E8 -> Check Expense | F8: =F47 -> 0 | H8: ='1'!H8 -> SIGUE | L8: =SUM(I8:K8) -> 0 | N8: 5 | P8: ='11'!Q8 -> 0 | R8: =Q8-P8 -> 0 | S8: 10 | T8: =R8*S8 -> 0
A9: ='1'!A9:B9 -> Lottery Sales | C9: =S52 -> 0 | D9: ='1'!D9:E9 -> Lotto Paid Out | H9: ='1'!H9 -> AFEX | L9: =SUM(I9:K9) -> 0 | N9: 6 | P9: ='11'!Q9 -> 0 | R9: =Q9-P9 -> 0 | S9: 20 | T9: =R9*S9 -> 0
A10: ='1'!A10:B10 -> Lotto Net Sales | D10: ='1'!D10:E10 -> Lottery Paid Out | H10: ='1'!H10 -> MONEYGRAM | L10: =SUM(I10:K10) -> 0 | N10: 7 | P10: ='11'!Q10 -> 0 | R10: =Q10-P10 -> 0 | S10: 20 | T10: =R10*S10 -> 0
A11: ='1'!A11:B11 -> PhoneCard | D11: ='1'!D11:E11 -> ATM Drop | H11: ='1'!H11 -> BARRI | I11: 90 | J11: 10 | L11: =SUM(I11:K11) -> 100 | N11: 8 | P11: ='11'!Q11 -> 0 | R11: =Q11-P11 -> 0 | S11: 20 | T11: =R11*S11 -> 0
A12: ='1'!A12:B12 -> Boss Revolution | D12: ='1'!D12:E12 -> Credit Card | H12: ='1'!H12 -> MAXI | I12: 4936.85 | J12: 133 | L12: =SUM(I12:K12) -> 5069.85 | N12: 9 | P12: ='11'!Q12 -> 0 | R12: =Q12-P12 -> 0 | S12: 10 | T12: =R12*S12 -> 0
A13: ='1'!A13:B13 -> Bill Payment | D13: ='1'!D13:E13 -> Outside Cash & Drops | F13: =L40 -> 17145 | H13: ='1'!H13 -> AMIGO SIN PIN | L13: =SUM(I13:K13) -> 0 | N13: 10 | P13: ='11'!Q13 -> 0 | R13: =Q13-P13 -> 0 | S13: 10 | T13: =R13*S13 -> 0
A14: ='1'!A14:B14 -> VidaPay | D14: ='1'!D14:E14 -> Cash Deposit | H14: TOTAL | I14: =SUM(I6:I13) -> 16779.54 | J14: =SUM(J6:J13) -> 360.61 | K14: =SUM(K6:K13) -> 0 | L14: =SUM(L6:M13) -> 17140.15 | N14: 11 | P14: ='11'!Q14 -> 0 | R14: =Q14-P14 -> 0 | S14: 5 | T14: =R14*S14 -> 0
A15: ='1'!A15:B15 -> Boost Epay | D15: ='1'!D15:E15 -> Money Gram Payment | N15: 12 | P15: ='11'!Q15 -> 0 | R15: =Q15-P15 -> 0 | S15: 5 | T15: =R15*S15 -> 0
A16: ='1'!A16:B16 -> Epay | D16: ='1'!D16:E16 -> Vigo Payment | N16: 13 | P16: ='11'!Q16 -> 0 | R16: =Q16-P16 -> 0 | S16: 5 | T16: =R16*S16 -> 0
A17: ='1'!A17:B17 -> Check Cashing Fees | C17: 102.65 | D17: ='1'!D17:E17 -> Ria Payment | N17: 14 | P17: ='11'!Q17 -> 0 | R17: =Q17-P17 -> 0 | S17: 5 | T17: =R17*S17 -> 0
A18: ='1'!A18:B18 -> Money Order | D18: ='1'!D18:E18 -> Checks Deposit | F18: =J25 -> 20189.13 | H18: CHECK DEPOSITS | K18: DROPS | L18: AMOUNT | M18: TIME | N18: 15 | P18: ='11'!Q18 -> 0 | R18: =Q18-P18 -> 0 | S18: 5 | T18: =R18*S18 -> 0
A19: ='1'!A19:B19 -> Return Check Paid | C19: =F33 -> 0 | D19: ='1'!D19:E19 -> Safe Balance | F19: 34966 | H19: CHECK DEPOSITS TO BANK | J19: AMOUNT | K19: 1 | L19: 1800 | M19: 9:21AM | N19: 16 | P19: ='11'!Q19 -> 0 | R19: =Q19-P19 -> 0 | S19: 5 | T19: =R19*S19 -> 0
A20: ='1'!A20:B20 -> Forward Balance | C20: ='11'!F19+'11'!F13 -> 49224 | D20: ='1'!D20:E20 -> Payroll Expense | F20: =J40 -> 0 | H20: NIZARI (27 Checks) | J20: 20189.13 | K20: 2 | L20: 2900 | M20: 12:28PM | N20: 17 | P20: ='11'!Q20 -> 0 | R20: =Q20-P20 -> 0 | S20: 5 | T20: =R20*S20 -> 0
A21: ='1'!A21:B21 -> Cash From Bank | C21: 6000 | D21: ='1'!D21:E21 -> Other Cash Out | F21: =M53 -> 340 | K21: 3 | L21: 2950 | M21: 1:29PM | N21: 18 | P21: ='11'!Q21 -> 0 | R21: =Q21-P21 -> 0 | S21: 5 | T21: =R21*S21 -> 0
A22: ='1'!A22:B22 -> Other Cash In | C22: =J53 -> 102 | D22: TOTAL PAYOUTS | F22: =SUM(F5:F21)-F7-F8 -> 72640.13 | K22: 4 | L22: 1250 | M22: 3:17PM | N22: 19 | P22: ='11'!Q22 -> 0 | R22: =Q22-P22 -> 0 | S22: 5 | T22: =R22*S22 -> 0
A23: ='1'!A23:B23 -> Rebates & Commissions | C23: =F53 -> 0 | D23: Inside Over - (Short) | F23: =(F11+F14+F15+F16+F17+F18+F19+F20+F21+F5+F6)-(C17+C19+C20+C21+C22+C23) -> 66.48 | K23: 5 | L23: 2600 | M23: 4:07PM | N23: 20 | P23: ='11'!Q23 -> 0 | R23: =Q23-P23 -> 0 | S23: 5 | T23: =R23*S23 -> 0
A24: TOTAL RECEIPTS | C24: =SUM(C5:C23) -> 72639.8 | D24: Over All Over - (Short) | F24: =SUM(F22-C24) -> 0.33 | K24: 6 | L24: 3145 | M24: 8:47PM | N24: 21 | P24: ='11'!Q24 -> 0 | R24: =Q24-P24 -> 0 | S24: 5 | T24: =R24*S24 -> 0
A25: Out Side Over - (Short) | C25: =(F9+F10+F12+F13)-(C5+C6+C7+C8+C9+C10+C11+C12+C13+C14+C15+C16+C18) -> -66.15 | H25: TOTAL | J25: =SUM(J20:J24) -> 20189.13 | K25: 7 | L25: 2500 | M25: 8:02PM | N25: 22 | P25: ='11'!Q25 -> 0 | R25: =Q25-P25 -> 0 | S25: 5 | T25: =R25*S25 -> 0
A26: Cash Purchases | D26: Return Check Paid | K26: 8 | N26: 23 | P26: ='11'!Q26 -> 0 | R26: =Q26-P26 -> 0 | S26: 3 | T26: =R26*S26 -> 0
A27: Description | C27: Amount | D27: Description | F27: Amount | K27: 9 | N27: 24 | P27: ='11'!Q27 -> 0 | R27: =Q27-P27 -> 0 | S27: 3 | T27: =R27*S27 -> 0
H28: CASH PAYROLL EXPENSE | K28: 10 | N28: 25 | P28: ='11'!Q28 -> 0 | R28: =Q28-P28 -> 0 | S28: 2 | T28: =R28*S28 -> 0
H29: CASH PAYROLL PAID TO | J29: AMOUNT | K29: 11 | N29: 26 | P29: ='11'!Q29 -> 0 | R29: =Q29-P29 -> 0 | S29: 5 | T29: =R29*S29 -> 0
K30: 12 | N30: 27 | P30: ='11'!Q30 -> 0 | R30: =Q30-P30 -> 0 | S30: 3 | T30: =R30*S30 -> 0
K31: 13 | N31: 28 | P31: ='11'!Q31 -> 0 | R31: =Q31-P31 -> 0 | S31: 3 | T31: =R31*S31 -> 0
K32: 14 | N32: 29 | P32: ='11'!Q32 -> 0 | R32: =Q32-P32 -> 0 | S32: 2 | T32: =R32*S32 -> 0
D33: Total | F33: =SUM(F28:F32) -> 0 | K33: 15 | N33: 30 | P33: ='11'!Q33 -> 0 | R33: =Q33-P33 -> 0 | S33: 2 | T33: =R33*S33 -> 0
D34: Cash Expense | K34: 16 | N34: 31 | P34: ='11'!Q34 -> 0 | R34: =Q34-P34 -> 0 | S34: 2 | T34: =R34*S34 -> 0
D35: Description | F35: Amount | K35: 17 | N35: 32 | P35: ='11'!Q35 -> 0 | R35: =Q35-P35 -> 0 | S35: 2 | T35: =R35*S35 -> 0
K36: 18 | N36: 33 | P36: ='11'!Q36 -> 0 | R36: =Q36-P36 -> 0 | S36: 2 | T36: =R36*S36 -> 0
K37: 19 | N37: 34 | P37: ='11'!Q37 -> 0 | R37: =Q37-P37 -> 0 | S37: 1 | T37: =R37*S37 -> 0
K38: 20 | N38: 35 | P38: ='11'!Q38 -> 0 | R38: =Q38-P38 -> 0 | S38: 1 | T38: =R38*S38 -> 0
K39: 21 | N39: 36 | P39: ='11'!Q39 -> 0 | R39: =Q39-P39 -> 0 | S39: 2 | T39: =R39*S39 -> 0
A40: Total | C40: =SUM(C28:C39) -> 0 | D40: Total | F40: =SUM(F36:F39) -> 0 | H40: TOTAL | J40: =SUM(J30:J39) -> 0 | K40: TOTAL | L40: =SUM(L19:L39) -> 17145 | N40: 37 | P40: ='11'!Q40 -> 0 | R40: =Q40-P40 -> 0 | S40: 2 | T40: =R40*S40 -> 0
N41: 38 | P41: ='11'!Q41 -> 0 | R41: =Q41-P41 -> 0 | S41: 2 | T41: =R41*S41 -> 0
A42: Check Purchases | D42: Check Expenses | N42: 39 | P42: ='11'!Q42 -> 0 | R42: =Q42-P42 -> 0 | S42: 1 | T42: =R42*S42 -> 0
A43: Description | B43: Check | C43: Amount | D43: Description | E43: Check | F43: Amount | H43: CASH IN | K43: CASH OUT TO OTHER | N43: 40 | P43: ='11'!Q43 -> 0 | R43: =Q43-P43 -> 0 | S43: 1 | T43: =R43*S43 -> 0
H44: CASH IN FROM | J44: AMOUNT | K44: OTHER CASH OUT | M44: AMOUNT | N44: 41 | P44: ='11'!Q44 -> 0 | R44: =Q44-P44 -> 0 | S44: 10 | T44: =R44*S44 -> 0
H45: Side Expense In | J45: 102 | K45: LED Logistics LLC (1 Check) | M45: 340 | N45: 42 | P45: ='11'!Q45 -> 0 | R45: =Q45-P45 -> 0 | S45: 1 | T45: =R45*S45 -> 0
N46: 43 | P46: ='11'!Q46 -> 0 | R46: =Q46-P46 -> 0 | S46: 1 | T46: =R46*S46 -> 0
D47: Total | F47: =SUM(F44:F46) -> 0 | N47: 44 | P47: ='11'!Q47 -> 0 | R47: =Q47-P47 -> 0 | S47: 1 | T47: =R47*S47 -> 0
D48: Rebates and Commissions | N48: 45 | P48: ='11'!Q48 -> 0 | R48: =Q48-P48 -> 0 | S48: 1 | T48: =R48*S48 -> 0
D49: Description | F49: Amount | N49: 46 | P49: ='11'!Q49 -> 0 | R49: =Q49-P49 -> 0 | S49: 1 | T49: =R49*S49 -> 0
N50: 47 | P50: ='11'!Q50 -> 0 | R50: =Q50-P50 -> 0 | S50: 1 | T50: =R50*S50 -> 0
N51: 48 | P51: ='11'!Q51 -> 0 | R51: =Q51-P51 -> 0 | S51: 1 | T51: =R51*S51 -> 0
O52: Total Lottery Sale | S52: =SUM(T4:T51) -> 0
A53: Total | C53: =SUM(C44:C52) -> 0 | D53: Total | F53: =SUM(F50:F52) -> 0 | H53: TOTAL | J53: =SUM(J45:J52) -> 102 | K53: TOTAL | M53: =SUM(M45:M52) -> 340

Sheet 13
A1: ='1'!A1:F1 -> DINERO EXPRESS #8 (512) 8015655 | H1: =A1 -> DINERO EXPRESS #8 (512) 8015655 | M1: DATE
A2: Daily Report | D2: Date: | F2: ='12'!F2+1 -> 12 | H2: OTHER REPORTS | M2: =F2 -> 12 | O2: Lottery Sale
D3: Day: | M3: =F3 -> 0 | O3: Game # | P3: Open | Q3: Close | R3: Tic.Sold | S3: $ Value | T3: T. Sale
A4: Reciepts | C4: Amount | D4: Disbursments | F4: Amount | H4: MONEY TRANSFER | N4: 1 | P4: ='12'!Q4 -> 0 | R4: =Q4-P4 -> 0 | S4: 50 | T4: =R4*S4 -> 0
A5: ='1'!A5:B5 -> Taxable Sale | C5: 24 | D5: ='1'!D5:E5 -> Cash Purchases | F5: =C40 -> 0 | H5: Company | I5: Amount | J5: Fees | K5: Commission | L5: Individual Total Amount | N5: 2 | P5: ='12'!Q5 -> 0 | R5: =Q5-P5 -> 0 | S5: 20 | T5: =R5*S5 -> 0
A6: ='1'!A6:B6 -> Comm & Fee | C6: 6 | D6: ='1'!D6:E6 -> Cash Expense | F6: =F40 -> 0 | H6: ='1'!H6 -> DINEX | L6: =SUM(I6:K6) -> 0 | N6: 3 | P6: ='12'!Q6 -> 0 | R6: =Q6-P6 -> 0 | S6: 20 | T6: =R6*S6 -> 0
A7: ='1'!A7:B7 -> Sales Tax | D7: ='1'!D7:E7 -> Check Purchases | F7: =C53 -> 0 | H7: ='1'!H7 -> INTERMEX | I7: 14361.48 | J7: 228 | L7: =SUM(I7:K7) -> 14589.48 | N7: 4 | P7: ='12'!Q7 -> 0 | R7: =Q7-P7 -> 0 | S7: 10 | T7: =R7*S7 -> 0
A8: ='1'!A8:B8 -> Money Transfers | C8: =L14 -> 22923.14 | D8: ='1'!D8:E8 -> Check Expense | F8: =F47 -> 0 | H8: ='1'!H8 -> SIGUE | L8: =SUM(I8:K8) -> 0 | N8: 5 | P8: ='12'!Q8 -> 0 | R8: =Q8-P8 -> 0 | S8: 10 | T8: =R8*S8 -> 0
A9: ='1'!A9:B9 -> Lottery Sales | C9: =S52 -> 0 | D9: ='1'!D9:E9 -> Lotto Paid Out | H9: ='1'!H9 -> AFEX | L9: =SUM(I9:K9) -> 0 | N9: 6 | P9: ='12'!Q9 -> 0 | R9: =Q9-P9 -> 0 | S9: 20 | T9: =R9*S9 -> 0
A10: ='1'!A10:B10 -> Lotto Net Sales | D10: ='1'!D10:E10 -> Lottery Paid Out | H10: ='1'!H10 -> MONEYGRAM | L10: =SUM(I10:K10) -> 0 | N10: 7 | P10: ='12'!Q10 -> 0 | R10: =Q10-P10 -> 0 | S10: 20 | T10: =R10*S10 -> 0
A11: ='1'!A11:B11 -> PhoneCard | D11: ='1'!D11:E11 -> ATM Drop | H11: ='1'!H11 -> BARRI | I11: 1338.46 | J11: 22 | L11: =SUM(I11:K11) -> 1360.46 | N11: 8 | P11: ='12'!Q11 -> 0 | R11: =Q11-P11 -> 0 | S11: 20 | T11: =R11*S11 -> 0
A12: ='1'!A12:B12 -> Boss Revolution | D12: ='1'!D12:E12 -> Credit Card | H12: ='1'!H12 -> MAXI | I12: 6812.2 | J12: 161 | L12: =SUM(I12:K12) -> 6973.2 | N12: 9 | P12: ='12'!Q12 -> 0 | R12: =Q12-P12 -> 0 | S12: 10 | T12: =R12*S12 -> 0
A13: ='1'!A13:B13 -> Bill Payment | D13: ='1'!D13:E13 -> Outside Cash & Drops | F13: =L40 -> 23462 | H13: ='1'!H13 -> AMIGO SIN PIN | L13: =SUM(I13:K13) -> 0 | N13: 10 | P13: ='12'!Q13 -> 0 | R13: =Q13-P13 -> 0 | S13: 10 | T13: =R13*S13 -> 0
A14: ='1'!A14:B14 -> VidaPay | D14: ='1'!D14:E14 -> Cash Deposit | H14: TOTAL | I14: =SUM(I6:I13) -> 22512.14 | J14: =SUM(J6:J13) -> 411 | K14: =SUM(K6:K13) -> 0 | L14: =SUM(L6:M13) -> 22923.14 | N14: 11 | P14: ='12'!Q14 -> 0 | R14: =Q14-P14 -> 0 | S14: 5 | T14: =R14*S14 -> 0
A15: ='1'!A15:B15 -> Boost Epay | D15: ='1'!D15:E15 -> Money Gram Payment | N15: 12 | P15: ='12'!Q15 -> 0 | R15: =Q15-P15 -> 0 | S15: 5 | T15: =R15*S15 -> 0
A16: ='1'!A16:B16 -> Epay | D16: ='1'!D16:E16 -> Vigo Payment | N16: 13 | P16: ='12'!Q16 -> 0 | R16: =Q16-P16 -> 0 | S16: 5 | T16: =R16*S16 -> 0
A17: ='1'!A17:B17 -> Check Cashing Fees | C17: 197.06 | D17: ='1'!D17:E17 -> Ria Payment | N17: 14 | P17: ='12'!Q17 -> 0 | R17: =Q17-P17 -> 0 | S17: 5 | T17: =R17*S17 -> 0
A18: ='1'!A18:B18 -> Money Order | C18: 1253 | D18: ='1'!D18:E18 -> Checks Deposit | F18: =J25 -> 39112.11 | H18: CHECK DEPOSITS | K18: DROPS | L18: AMOUNT | M18: TIME | N18: 15 | P18: ='12'!Q18 -> 0 | R18: =Q18-P18 -> 0 | S18: 5 | T18: =R18*S18 -> 0
A19: ='1'!A19:B19 -> Return Check Paid | C19: =F33 -> 0 | D19: ='1'!D19:E19 -> Safe Balance | F19: 14353 | H19: CHECK DEPOSITS TO BANK | J19: AMOUNT | K19: 1 | L19: 1900 | M19: 10:53AM | N19: 16 | P19: ='12'!Q19 -> 0 | R19: =Q19-P19 -> 0 | S19: 5 | T19: =R19*S19 -> 0
A20: ='1'!A20:B20 -> Forward Balance | C20: ='12'!F19+'12'!F13 -> 52111 | D20: ='1'!D20:E20 -> Payroll Expense | F20: =J40 -> 0 | H20: NIZARI (15 Checks) | J20: 39112.11 | K20: 2 | L20: 10000 | M20: 5:00PM | N20: 17 | P20: ='12'!Q20 -> 0 | R20: =Q20-P20 -> 0 | S20: 5 | T20: =R20*S20 -> 0
A21: ='1'!A21:B21 -> Cash From Bank | D21: ='1'!D21:E21 -> Other Cash Out | F21: =M53 -> 300 | K21: 3 | L21: 2000 | M21: 5:50PM | N21: 18 | P21: ='12'!Q21 -> 0 | R21: =Q21-P21 -> 0 | S21: 5 | T21: =R21*S21 -> 0
A22: ='1'!A22:B22 -> Other Cash In | C22: =J53 -> 712 | D22: TOTAL PAYOUTS | F22: =SUM(F5:F21)-F7-F8 -> 77227.11 | K22: 4 | L22: 2000 | M22: 7:37PM | N22: 19 | P22: ='12'!Q22 -> 0 | R22: =Q22-P22 -> 0 | S22: 5 | T22: =R22*S22 -> 0
A23: ='1'!A23:B23 -> Rebates & Commissions | C23: =F53 -> 0 | D23: Inside Over - (Short) | F23: =(F11+F14+F15+F16+F17+F18+F19+F20+F21+F5+F6)-(C17+C19+C20+C21+C22+C23) -> 745.05 | K23: 5 | L23: 7562 | M23: 8:50PM | N23: 20 | P23: ='12'!Q23 -> 0 | R23: =Q23-P23 -> 0 | S23: 5 | T23: =R23*S23 -> 0
A24: TOTAL RECEIPTS | C24: =SUM(C5:C23) -> 77226.2 | D24: Over All Over - (Short) | F24: =SUM(F22-C24) -> 0.91 | K24: 6 | N24: 21 | P24: ='12'!Q24 -> 0 | R24: =Q24-P24 -> 0 | S24: 5 | T24: =R24*S24 -> 0
A25: Out Side Over - (Short) | C25: =(F9+F10+F12+F13)-(C5+C6+C7+C8+C9+C10+C11+C12+C13+C14+C15+C16+C18) -> -744.14 | H25: TOTAL | J25: =SUM(J20:J24) -> 39112.11 | K25: 7 | N25: 22 | P25: ='12'!Q25 -> 0 | R25: =Q25-P25 -> 0 | S25: 5 | T25: =R25*S25 -> 0
A26: Cash Purchases | D26: Return Check Paid | K26: 8 | N26: 23 | P26: ='12'!Q26 -> 0 | R26: =Q26-P26 -> 0 | S26: 3 | T26: =R26*S26 -> 0
A27: Description | C27: Amount | D27: Description | F27: Amount | K27: 9 | N27: 24 | P27: ='12'!Q27 -> 0 | R27: =Q27-P27 -> 0 | S27: 3 | T27: =R27*S27 -> 0
H28: CASH PAYROLL EXPENSE | K28: 10 | N28: 25 | P28: ='12'!Q28 -> 0 | R28: =Q28-P28 -> 0 | S28: 2 | T28: =R28*S28 -> 0
H29: CASH PAYROLL PAID TO | J29: AMOUNT | K29: 11 | N29: 26 | P29: ='12'!Q29 -> 0 | R29: =Q29-P29 -> 0 | S29: 5 | T29: =R29*S29 -> 0
K30: 12 | N30: 27 | P30: ='12'!Q30 -> 0 | R30: =Q30-P30 -> 0 | S30: 3 | T30: =R30*S30 -> 0
K31: 13 | N31: 28 | P31: ='12'!Q31 -> 0 | R31: =Q31-P31 -> 0 | S31: 3 | T31: =R31*S31 -> 0
K32: 14 | N32: 29 | P32: ='12'!Q32 -> 0 | R32: =Q32-P32 -> 0 | S32: 2 | T32: =R32*S32 -> 0
D33: Total | F33: =SUM(F28:F32) -> 0 | K33: 15 | N33: 30 | P33: ='12'!Q33 -> 0 | R33: =Q33-P33 -> 0 | S33: 2 | T33: =R33*S33 -> 0
D34: Cash Expense | K34: 16 | N34: 31 | P34: ='12'!Q34 -> 0 | R34: =Q34-P34 -> 0 | S34: 2 | T34: =R34*S34 -> 0
D35: Description | F35: Amount | K35: 17 | N35: 32 | P35: ='12'!Q35 -> 0 | R35: =Q35-P35 -> 0 | S35: 2 | T35: =R35*S35 -> 0
K36: 18 | N36: 33 | P36: ='12'!Q36 -> 0 | R36: =Q36-P36 -> 0 | S36: 2 | T36: =R36*S36 -> 0
K37: 19 | N37: 34 | P37: ='12'!Q37 -> 0 | R37: =Q37-P37 -> 0 | S37: 1 | T37: =R37*S37 -> 0
K38: 20 | N38: 35 | P38: ='12'!Q38 -> 0 | R38: =Q38-P38 -> 0 | S38: 1 | T38: =R38*S38 -> 0
K39: 21 | N39: 36 | P39: ='12'!Q39 -> 0 | R39: =Q39-P39 -> 0 | S39: 2 | T39: =R39*S39 -> 0
A40: Total | C40: =SUM(C28:C39) -> 0 | D40: Total | F40: =SUM(F36:F39) -> 0 | H40: TOTAL | J40: =SUM(J30:J39) -> 0 | K40: TOTAL | L40: =SUM(L19:L39) -> 23462 | N40: 37 | P40: ='12'!Q40 -> 0 | R40: =Q40-P40 -> 0 | S40: 2 | T40: =R40*S40 -> 0
N41: 38 | P41: ='12'!Q41 -> 0 | R41: =Q41-P41 -> 0 | S41: 2 | T41: =R41*S41 -> 0
A42: Check Purchases | D42: Check Expenses | N42: 39 | P42: ='12'!Q42 -> 0 | R42: =Q42-P42 -> 0 | S42: 1 | T42: =R42*S42 -> 0
A43: Description | B43: Check | C43: Amount | D43: Description | E43: Check | F43: Amount | H43: CASH IN | K43: CASH OUT TO OTHER | N43: 40 | P43: ='12'!Q43 -> 0 | R43: =Q43-P43 -> 0 | S43: 1 | T43: =R43*S43 -> 0
H44: CASH IN FROM | J44: AMOUNT | K44: OTHER CASH OUT | M44: AMOUNT | N44: 41 | P44: ='12'!Q44 -> 0 | R44: =Q44-P44 -> 0 | S44: 10 | T44: =R44*S44 -> 0
H45: Maxi Rejected (#6104) | J45: 515 | K45: LED Logistics LLC (1 Check) | M45: 300 | N45: 42 | P45: ='12'!Q45 -> 0 | R45: =Q45-P45 -> 0 | S45: 1 | T45: =R45*S45 -> 0
H46: Side Expense In | J46: 197 | N46: 43 | P46: ='12'!Q46 -> 0 | R46: =Q46-P46 -> 0 | S46: 1 | T46: =R46*S46 -> 0
D47: Total | F47: =SUM(F44:F46) -> 0 | N47: 44 | P47: ='12'!Q47 -> 0 | R47: =Q47-P47 -> 0 | S47: 1 | T47: =R47*S47 -> 0
D48: Rebates and Commissions | N48: 45 | P48: ='12'!Q48 -> 0 | R48: =Q48-P48 -> 0 | S48: 1 | T48: =R48*S48 -> 0
D49: Description | F49: Amount | N49: 46 | P49: ='12'!Q49 -> 0 | R49: =Q49-P49 -> 0 | S49: 1 | T49: =R49*S49 -> 0
N50: 47 | P50: ='12'!Q50 -> 0 | R50: =Q50-P50 -> 0 | S50: 1 | T50: =R50*S50 -> 0
N51: 48 | P51: ='12'!Q51 -> 0 | R51: =Q51-P51 -> 0 | S51: 1 | T51: =R51*S51 -> 0
O52: Total Lottery Sale | S52: =SUM(T4:T51) -> 0
A53: Total | C53: =SUM(C44:C52) -> 0 | D53: Total | F53: =SUM(F50:F52) -> 0 | H53: TOTAL | J53: =SUM(J45:J52) -> 712 | K53: TOTAL | M53: =SUM(M45:M52) -> 300

Sheet 14
A1: ='1'!A1:F1 -> DINERO EXPRESS #8 (512) 8015655 | H1: =A1 -> DINERO EXPRESS #8 (512) 8015655 | M1: DATE
A2: Daily Report | D2: Date: | F2: ='13'!F2+1 -> 13 | H2: OTHER REPORTS | M2: =F2 -> 13 | O2: Lottery Sale
D3: Day: | M3: =F3 -> 0 | O3: Game # | P3: Open | Q3: Close | R3: Tic.Sold | S3: $ Value | T3: T. Sale
A4: Reciepts | C4: Amount | D4: Disbursments | F4: Amount | H4: MONEY TRANSFER | N4: 1 | P4: ='13'!Q4 -> 0 | R4: =Q4-P4 -> 0 | S4: 50 | T4: =R4*S4 -> 0
A5: ='1'!A5:B5 -> Taxable Sale | D5: ='1'!D5:E5 -> Cash Purchases | F5: =C40 -> 0 | H5: Company | I5: Amount | J5: Fees | K5: Commission | L5: Individual Total Amount | N5: 2 | P5: ='13'!Q5 -> 0 | R5: =Q5-P5 -> 0 | S5: 20 | T5: =R5*S5 -> 0
A6: ='1'!A6:B6 -> Comm & Fee | D6: ='1'!D6:E6 -> Cash Expense | F6: =F40 -> 0 | H6: ='1'!H6 -> DINEX | L6: =SUM(I6:K6) -> 0 | N6: 3 | P6: ='13'!Q6 -> 0 | R6: =Q6-P6 -> 0 | S6: 20 | T6: =R6*S6 -> 0
A7: ='1'!A7:B7 -> Sales Tax | D7: ='1'!D7:E7 -> Check Purchases | F7: =C53 -> 0 | H7: ='1'!H7 -> INTERMEX | I7: 2899.5 | J7: 84 | L7: =SUM(I7:K7) -> 2983.5 | N7: 4 | P7: ='13'!Q7 -> 0 | R7: =Q7-P7 -> 0 | S7: 10 | T7: =R7*S7 -> 0
A8: ='1'!A8:B8 -> Money Transfers | C8: =L14 -> 8416 | D8: ='1'!D8:E8 -> Check Expense | F8: =F47 -> 0 | H8: ='1'!H8 -> SIGUE | L8: =SUM(I8:K8) -> 0 | N8: 5 | P8: ='13'!Q8 -> 0 | R8: =Q8-P8 -> 0 | S8: 10 | T8: =R8*S8 -> 0
A9: ='1'!A9:B9 -> Lottery Sales | C9: =S52 -> 0 | D9: ='1'!D9:E9 -> Lotto Paid Out | H9: ='1'!H9 -> AFEX | L9: =SUM(I9:K9) -> 0 | N9: 6 | P9: ='13'!Q9 -> 0 | R9: =Q9-P9 -> 0 | S9: 20 | T9: =R9*S9 -> 0
A10: ='1'!A10:B10 -> Lotto Net Sales | D10: ='1'!D10:E10 -> Lottery Paid Out | H10: ='1'!H10 -> MONEYGRAM | L10: =SUM(I10:K10) -> 0 | N10: 7 | P10: ='13'!Q10 -> 0 | R10: =Q10-P10 -> 0 | S10: 20 | T10: =R10*S10 -> 0
A11: ='1'!A11:B11 -> PhoneCard | D11: ='1'!D11:E11 -> ATM Drop | H11: ='1'!H11 -> BARRI | L11: =SUM(I11:K11) -> 0 | N11: 8 | P11: ='13'!Q11 -> 0 | R11: =Q11-P11 -> 0 | S11: 20 | T11: =R11*S11 -> 0
A12: ='1'!A12:B12 -> Boss Revolution | D12: ='1'!D12:E12 -> Credit Card | H12: ='1'!H12 -> MAXI | I12: 5353.5 | J12: 79 | L12: =SUM(I12:K12) -> 5432.5 | N12: 9 | P12: ='13'!Q12 -> 0 | R12: =Q12-P12 -> 0 | S12: 10 | T12: =R12*S12 -> 0
A13: ='1'!A13:B13 -> Bill Payment | D13: ='1'!D13:E13 -> Outside Cash & Drops | F13: =L40 -> 7903 | H13: ='1'!H13 -> AMIGO SIN PIN | L13: =SUM(I13:K13) -> 0 | N13: 10 | P13: ='13'!Q13 -> 0 | R13: =Q13-P13 -> 0 | S13: 10 | T13: =R13*S13 -> 0
A14: ='1'!A14:B14 -> VidaPay | D14: ='1'!D14:E14 -> Cash Deposit | H14: TOTAL | I14: =SUM(I6:I13) -> 8253 | J14: =SUM(J6:J13) -> 163 | K14: =SUM(K6:K13) -> 0 | L14: =SUM(L6:M13) -> 8416 | N14: 11 | P14: ='13'!Q14 -> 0 | R14: =Q14-P14 -> 0 | S14: 5 | T14: =R14*S14 -> 0
A15: ='1'!A15:B15 -> Boost Epay | D15: ='1'!D15:E15 -> Money Gram Payment | N15: 12 | P15: ='13'!Q15 -> 0 | R15: =Q15-P15 -> 0 | S15: 5 | T15: =R15*S15 -> 0
A16: ='1'!A16:B16 -> Epay | D16: ='1'!D16:E16 -> Vigo Payment | N16: 13 | P16: ='13'!Q16 -> 0 | R16: =Q16-P16 -> 0 | S16: 5 | T16: =R16*S16 -> 0
A17: ='1'!A17:B17 -> Check Cashing Fees | C17: 41.53 | D17: ='1'!D17:E17 -> Ria Payment | N17: 14 | P17: ='13'!Q17 -> 0 | R17: =Q17-P17 -> 0 | S17: 5 | T17: =R17*S17 -> 0
A18: ='1'!A18:B18 -> Money Order | C18: 1028.09 | D18: ='1'!D18:E18 -> Checks Deposit | F18: =J25 -> 8305.72 | H18: CHECK DEPOSITS | K18: DROPS | L18: AMOUNT | M18: TIME | N18: 15 | P18: ='13'!Q18 -> 0 | R18: =Q18-P18 -> 0 | S18: 5 | T18: =R18*S18 -> 0
A19: ='1'!A19:B19 -> Return Check Paid | C19: =F33 -> 12041 | D19: ='1'!D19:E19 -> Safe Balance | F19: 77968 | H19: CHECK DEPOSITS TO BANK | J19: AMOUNT | K19: 1 | L19: 3890 | M19: 2:46PM | N19: 16 | P19: ='13'!Q19 -> 0 | R19: =Q19-P19 -> 0 | S19: 5 | T19: =R19*S19 -> 0
A20: ='1'!A20:B20 -> Forward Balance | C20: ='13'!F19+'13'!F13 -> 37815 | D20: ='1'!D20:E20 -> Payroll Expense | F20: =J40 -> 0 | H20: NIZARI (14 Checks) | J20: 8305.72 | K20: 2 | L20: 1440 | M20: 6:52PM | N20: 17 | P20: ='13'!Q20 -> 0 | R20: =Q20-P20 -> 0 | S20: 5 | T20: =R20*S20 -> 0
A21: ='1'!A21:B21 -> Cash From Bank | C21: 35000 | D21: ='1'!D21:E21 -> Other Cash Out | F21: =M53 -> 515 | K21: 3 | L21: 1600 | M21: 8:04PM | N21: 18 | P21: ='13'!Q21 -> 0 | R21: =Q21-P21 -> 0 | S21: 5 | T21: =R21*S21 -> 0
A22: ='1'!A22:B22 -> Other Cash In | C22: =J53 -> 350 | D22: TOTAL PAYOUTS | F22: =SUM(F5:F21)-F7-F8 -> 94691.72 | K22: 4 | L22: 973 | M22: 8:52PM | N22: 19 | P22: ='13'!Q22 -> 0 | R22: =Q22-P22 -> 0 | S22: 5 | T22: =R22*S22 -> 0
A23: ='1'!A23:B23 -> Rebates & Commissions | C23: =F53 -> 0 | D23: Inside Over - (Short) | F23: =(F11+F14+F15+F16+F17+F18+F19+F20+F21+F5+F6)-(C17+C19+C20+C21+C22+C23) -> 1541.19 | K23: 5 | N23: 20 | P23: ='13'!Q23 -> 0 | R23: =Q23-P23 -> 0 | S23: 5 | T23: =R23*S23 -> 0
A24: TOTAL RECEIPTS | C24: =SUM(C5:C23) -> 94691.62 | D24: Over All Over - (Short) | F24: =SUM(F22-C24) -> 0.1 | K24: 6 | N24: 21 | P24: ='13'!Q24 -> 0 | R24: =Q24-P24 -> 0 | S24: 5 | T24: =R24*S24 -> 0
A25: Out Side Over - (Short) | C25: =(F9+F10+F12+F13)-(C5+C6+C7+C8+C9+C10+C11+C12+C13+C14+C15+C16+C18) -> -1541.09 | H25: TOTAL | J25: =SUM(J20:J24) -> 8305.72 | K25: 7 | N25: 22 | P25: ='13'!Q25 -> 0 | R25: =Q25-P25 -> 0 | S25: 5 | T25: =R25*S25 -> 0
A26: Cash Purchases | D26: Return Check Paid | K26: 8 | N26: 23 | P26: ='13'!Q26 -> 0 | R26: =Q26-P26 -> 0 | S26: 3 | T26: =R26*S26 -> 0
A27: Description | C27: Amount | D27: Description | F27: Amount | K27: 9 | N27: 24 | P27: ='13'!Q27 -> 0 | R27: =Q27-P27 -> 0 | S27: 3 | T27: =R27*S27 -> 0
D28: M&E Group (2242&2245) | F28: 12041 | H28: CASH PAYROLL EXPENSE | K28: 10 | N28: 25 | P28: ='13'!Q28 -> 0 | R28: =Q28-P28 -> 0 | S28: 2 | T28: =R28*S28 -> 0
H29: CASH PAYROLL PAID TO | J29: AMOUNT | K29: 11 | N29: 26 | P29: ='13'!Q29 -> 0 | R29: =Q29-P29 -> 0 | S29: 5 | T29: =R29*S29 -> 0
K30: 12 | N30: 27 | P30: ='13'!Q30 -> 0 | R30: =Q30-P30 -> 0 | S30: 3 | T30: =R30*S30 -> 0
K31: 13 | N31: 28 | P31: ='13'!Q31 -> 0 | R31: =Q31-P31 -> 0 | S31: 3 | T31: =R31*S31 -> 0
K32: 14 | N32: 29 | P32: ='13'!Q32 -> 0 | R32: =Q32-P32 -> 0 | S32: 2 | T32: =R32*S32 -> 0
D33: Total | F33: =SUM(F28:F32) -> 12041 | K33: 15 | N33: 30 | P33: ='13'!Q33 -> 0 | R33: =Q33-P33 -> 0 | S33: 2 | T33: =R33*S33 -> 0
D34: Cash Expense | K34: 16 | N34: 31 | P34: ='13'!Q34 -> 0 | R34: =Q34-P34 -> 0 | S34: 2 | T34: =R34*S34 -> 0
D35: Description | F35: Amount | K35: 17 | N35: 32 | P35: ='13'!Q35 -> 0 | R35: =Q35-P35 -> 0 | S35: 2 | T35: =R35*S35 -> 0
K36: 18 | N36: 33 | P36: ='13'!Q36 -> 0 | R36: =Q36-P36 -> 0 | S36: 2 | T36: =R36*S36 -> 0
K37: 19 | N37: 34 | P37: ='13'!Q37 -> 0 | R37: =Q37-P37 -> 0 | S37: 1 | T37: =R37*S37 -> 0
K38: 20 | N38: 35 | P38: ='13'!Q38 -> 0 | R38: =Q38-P38 -> 0 | S38: 1 | T38: =R38*S38 -> 0
K39: 21 | N39: 36 | P39: ='13'!Q39 -> 0 | R39: =Q39-P39 -> 0 | S39: 2 | T39: =R39*S39 -> 0
A40: Total | C40: =SUM(C28:C39) -> 0 | D40: Total | F40: =SUM(F36:F39) -> 0 | H40: TOTAL | J40: =SUM(J30:J39) -> 0 | K40: TOTAL | L40: =SUM(L19:L39) -> 7903 | N40: 37 | P40: ='13'!Q40 -> 0 | R40: =Q40-P40 -> 0 | S40: 2 | T40: =R40*S40 -> 0
N41: 38 | P41: ='13'!Q41 -> 0 | R41: =Q41-P41 -> 0 | S41: 2 | T41: =R41*S41 -> 0
A42: Check Purchases | D42: Check Expenses | N42: 39 | P42: ='13'!Q42 -> 0 | R42: =Q42-P42 -> 0 | S42: 1 | T42: =R42*S42 -> 0
A43: Description | B43: Check | C43: Amount | D43: Description | E43: Check | F43: Amount | H43: CASH IN | K43: CASH OUT TO OTHER | N43: 40 | P43: ='13'!Q43 -> 0 | R43: =Q43-P43 -> 0 | S43: 1 | T43: =R43*S43 -> 0
H44: CASH IN FROM | J44: AMOUNT | K44: OTHER CASH OUT | M44: AMOUNT | N44: 41 | P44: ='13'!Q44 -> 0 | R44: =Q44-P44 -> 0 | S44: 10 | T44: =R44*S44 -> 0
H45: Side Expense In | J45: 350 | K45: Re-Envios (Maxi #6104) | M45: 515 | N45: 42 | P45: ='13'!Q45 -> 0 | R45: =Q45-P45 -> 0 | S45: 1 | T45: =R45*S45 -> 0
N46: 43 | P46: ='13'!Q46 -> 0 | R46: =Q46-P46 -> 0 | S46: 1 | T46: =R46*S46 -> 0
D47: Total | F47: =SUM(F44:F46) -> 0 | N47: 44 | P47: ='13'!Q47 -> 0 | R47: =Q47-P47 -> 0 | S47: 1 | T47: =R47*S47 -> 0
D48: Rebates and Commissions | N48: 45 | P48: ='13'!Q48 -> 0 | R48: =Q48-P48 -> 0 | S48: 1 | T48: =R48*S48 -> 0
D49: Description | F49: Amount | N49: 46 | P49: ='13'!Q49 -> 0 | R49: =Q49-P49 -> 0 | S49: 1 | T49: =R49*S49 -> 0
N50: 47 | P50: ='13'!Q50 -> 0 | R50: =Q50-P50 -> 0 | S50: 1 | T50: =R50*S50 -> 0
N51: 48 | P51: ='13'!Q51 -> 0 | R51: =Q51-P51 -> 0 | S51: 1 | T51: =R51*S51 -> 0
O52: Total Lottery Sale | S52: =SUM(T4:T51) -> 0
A53: Total | C53: =SUM(C44:C52) -> 0 | D53: Total | F53: =SUM(F50:F52) -> 0 | H53: TOTAL | J53: =SUM(J45:J52) -> 350 | K53: TOTAL | M53: =SUM(M45:M52) -> 515

Sheet 15
A1: ='1'!A1:F1 -> DINERO EXPRESS #8 (512) 8015655 | H1: =A1 -> DINERO EXPRESS #8 (512) 8015655 | M1: DATE
A2: Daily Report | D2: Date: | F2: ='14'!F2+1 -> 14 | H2: OTHER REPORTS | M2: =F2 -> 14 | O2: Lottery Sale
D3: Day: | M3: =F3 -> 0 | O3: Game # | P3: Open | Q3: Close | R3: Tic.Sold | S3: $ Value | T3: T. Sale
A4: Reciepts | C4: Amount | D4: Disbursments | F4: Amount | H4: MONEY TRANSFER | N4: 1 | P4: ='14'!Q4 -> 0 | R4: =Q4-P4 -> 0 | S4: 50 | T4: =R4*S4 -> 0
A5: ='1'!A5:B5 -> Taxable Sale | C5: 7 | D5: ='1'!D5:E5 -> Cash Purchases | F5: =C40 -> 0 | H5: Company | I5: Amount | J5: Fees | K5: Commission | L5: Individual Total Amount | N5: 2 | P5: ='14'!Q5 -> 0 | R5: =Q5-P5 -> 0 | S5: 20 | T5: =R5*S5 -> 0
A6: ='1'!A6:B6 -> Comm & Fee | C6: 5 | D6: ='1'!D6:E6 -> Cash Expense | F6: =F40 -> 0 | H6: ='1'!H6 -> DINEX | L6: =SUM(I6:K6) -> 0 | N6: 3 | P6: ='14'!Q6 -> 0 | R6: =Q6-P6 -> 0 | S6: 20 | T6: =R6*S6 -> 0
A7: ='1'!A7:B7 -> Sales Tax | D7: ='1'!D7:E7 -> Check Purchases | F7: =C53 -> 0 | H7: ='1'!H7 -> INTERMEX | I7: 9723.62 | J7: 186 | L7: =SUM(I7:K7) -> 9909.62 | N7: 4 | P7: ='14'!Q7 -> 0 | R7: =Q7-P7 -> 0 | S7: 10 | T7: =R7*S7 -> 0
A8: ='1'!A8:B8 -> Money Transfers | C8: =L14 -> 14522.36 | D8: ='1'!D8:E8 -> Check Expense | F8: =F47 -> 0 | H8: ='1'!H8 -> SIGUE | L8: =SUM(I8:K8) -> 0 | N8: 5 | P8: ='14'!Q8 -> 0 | R8: =Q8-P8 -> 0 | S8: 10 | T8: =R8*S8 -> 0
A9: ='1'!A9:B9 -> Lottery Sales | C9: =S52 -> 0 | D9: ='1'!D9:E9 -> Lotto Paid Out | H9: ='1'!H9 -> AFEX | L9: =SUM(I9:K9) -> 0 | N9: 6 | P9: ='14'!Q9 -> 0 | R9: =Q9-P9 -> 0 | S9: 20 | T9: =R9*S9 -> 0
A10: ='1'!A10:B10 -> Lotto Net Sales | D10: ='1'!D10:E10 -> Lottery Paid Out | H10: ='1'!H10 -> MONEYGRAM | L10: =SUM(I10:K10) -> 0 | N10: 7 | P10: ='14'!Q10 -> 0 | R10: =Q10-P10 -> 0 | S10: 20 | T10: =R10*S10 -> 0
A11: ='1'!A11:B11 -> PhoneCard | D11: ='1'!D11:E11 -> ATM Drop | H11: ='1'!H11 -> BARRI | L11: =SUM(I11:K11) -> 0 | N11: 8 | P11: ='14'!Q11 -> 0 | R11: =Q11-P11 -> 0 | S11: 20 | T11: =R11*S11 -> 0
A12: ='1'!A12:B12 -> Boss Revolution | D12: ='1'!D12:E12 -> Credit Card | H12: ='1'!H12 -> MAXI | I12: 4461.74 | J12: 151 | L12: =SUM(I12:K12) -> 4612.74 | N12: 9 | P12: ='14'!Q12 -> 0 | R12: =Q12-P12 -> 0 | S12: 10 | T12: =R12*S12 -> 0
A13: ='1'!A13:B13 -> Bill Payment | D13: ='1'!D13:E13 -> Outside Cash & Drops | F13: =L40 -> 16557 | H13: ='1'!H13 -> AMIGO SIN PIN | L13: =SUM(I13:K13) -> 0 | N13: 10 | P13: ='14'!Q13 -> 0 | R13: =Q13-P13 -> 0 | S13: 10 | T13: =R13*S13 -> 0
A14: ='1'!A14:B14 -> VidaPay | D14: ='1'!D14:E14 -> Cash Deposit | H14: TOTAL | I14: =SUM(I6:I13) -> 14185.36 | J14: =SUM(J6:J13) -> 337 | K14: =SUM(K6:K13) -> 0 | L14: =SUM(L6:M13) -> 14522.36 | N14: 11 | P14: ='14'!Q14 -> 0 | R14: =Q14-P14 -> 0 | S14: 5 | T14: =R14*S14 -> 0
A15: ='1'!A15:B15 -> Boost Epay | D15: ='1'!D15:E15 -> Money Gram Payment | N15: 12 | P15: ='14'!Q15 -> 0 | R15: =Q15-P15 -> 0 | S15: 5 | T15: =R15*S15 -> 0
A16: ='1'!A16:B16 -> Epay | D16: ='1'!D16:E16 -> Vigo Payment | N16: 13 | P16: ='14'!Q16 -> 0 | R16: =Q16-P16 -> 0 | S16: 5 | T16: =R16*S16 -> 0
A17: ='1'!A17:B17 -> Check Cashing Fees | C17: 241.41 | D17: ='1'!D17:E17 -> Ria Payment | N17: 14 | P17: ='14'!Q17 -> 0 | R17: =Q17-P17 -> 0 | S17: 5 | T17: =R17*S17 -> 0
A18: ='1'!A18:B18 -> Money Order | C18: 1120 | D18: ='1'!D18:E18 -> Checks Deposit | F18: =J25 -> 48282.85 | H18: CHECK DEPOSITS | K18: DROPS | L18: AMOUNT | M18: TIME | N18: 15 | P18: ='14'!Q18 -> 0 | R18: =Q18-P18 -> 0 | S18: 5 | T18: =R18*S18 -> 0
A19: ='1'!A19:B19 -> Return Check Paid | C19: =F33 -> 0 | D19: ='1'!D19:E19 -> Safe Balance | F19: 49515 | H19: CHECK DEPOSITS TO BANK | J19: AMOUNT | K19: 1 | L19: 3340 | M19: 1:47PM | N19: 16 | P19: ='14'!Q19 -> 0 | R19: =Q19-P19 -> 0 | S19: 5 | T19: =R19*S19 -> 0
A20: ='1'!A20:B20 -> Forward Balance | C20: ='14'!F19+'14'!F13 -> 85871 | D20: ='1'!D20:E20 -> Payroll Expense | F20: =J40 -> 0 | H20: NIZARI (32 Checks) | J20: 48282.85 | K20: 2 | L20: 10000 | M20: 5:00PM | N20: 17 | P20: ='14'!Q20 -> 0 | R20: =Q20-P20 -> 0 | S20: 5 | T20: =R20*S20 -> 0
A21: ='1'!A21:B21 -> Cash From Bank | C21: 10000 | D21: ='1'!D21:E21 -> Other Cash Out | F21: =M53 -> 0 | K21: 3 | L21: 3217 | M21: 8:24PM | N21: 18 | P21: ='14'!Q21 -> 0 | R21: =Q21-P21 -> 0 | S21: 5 | T21: =R21*S21 -> 0
A22: ='1'!A22:B22 -> Other Cash In | C22: =J53 -> 2588 | D22: TOTAL PAYOUTS | F22: =SUM(F5:F21)-F7-F8 -> 114354.85 | K22: 4 | N22: 19 | P22: ='14'!Q22 -> 0 | R22: =Q22-P22 -> 0 | S22: 5 | T22: =R22*S22 -> 0
A23: ='1'!A23:B23 -> Rebates & Commissions | C23: =F53 -> 0 | D23: Inside Over - (Short) | F23: =(F11+F14+F15+F16+F17+F18+F19+F20+F21+F5+F6)-(C17+C19+C20+C21+C22+C23) -> -902.56 | K23: 5 | N23: 20 | P23: ='14'!Q23 -> 0 | R23: =Q23-P23 -> 0 | S23: 5 | T23: =R23*S23 -> 0
A24: TOTAL RECEIPTS | C24: =SUM(C5:C23) -> 114354.77 | D24: Over All Over - (Short) | F24: =SUM(F22-C24) -> 0.08 | K24: 6 | N24: 21 | P24: ='14'!Q24 -> 0 | R24: =Q24-P24 -> 0 | S24: 5 | T24: =R24*S24 -> 0
A25: Out Side Over - (Short) | C25: =(F9+F10+F12+F13)-(C5+C6+C7+C8+C9+C10+C11+C12+C13+C14+C15+C16+C18) -> 902.64 | H25: TOTAL | J25: =SUM(J20:J24) -> 48282.85 | K25: 7 | N25: 22 | P25: ='14'!Q25 -> 0 | R25: =Q25-P25 -> 0 | S25: 5 | T25: =R25*S25 -> 0
A26: Cash Purchases | D26: Return Check Paid | K26: 8 | N26: 23 | P26: ='14'!Q26 -> 0 | R26: =Q26-P26 -> 0 | S26: 3 | T26: =R26*S26 -> 0
A27: Description | C27: Amount | D27: Description | F27: Amount | K27: 9 | N27: 24 | P27: ='14'!Q27 -> 0 | R27: =Q27-P27 -> 0 | S27: 3 | T27: =R27*S27 -> 0
H28: CASH PAYROLL EXPENSE | K28: 10 | N28: 25 | P28: ='14'!Q28 -> 0 | R28: =Q28-P28 -> 0 | S28: 2 | T28: =R28*S28 -> 0
H29: CASH PAYROLL PAID TO | J29: AMOUNT | K29: 11 | N29: 26 | P29: ='14'!Q29 -> 0 | R29: =Q29-P29 -> 0 | S29: 5 | T29: =R29*S29 -> 0
K30: 12 | N30: 27 | P30: ='14'!Q30 -> 0 | R30: =Q30-P30 -> 0 | S30: 3 | T30: =R30*S30 -> 0
K31: 13 | N31: 28 | P31: ='14'!Q31 -> 0 | R31: =Q31-P31 -> 0 | S31: 3 | T31: =R31*S31 -> 0
K32: 14 | N32: 29 | P32: ='14'!Q32 -> 0 | R32: =Q32-P32 -> 0 | S32: 2 | T32: =R32*S32 -> 0
D33: Total | F33: =SUM(F28:F32) -> 0 | K33: 15 | N33: 30 | P33: ='14'!Q33 -> 0 | R33: =Q33-P33 -> 0 | S33: 2 | T33: =R33*S33 -> 0
D34: Cash Expense | K34: 16 | N34: 31 | P34: ='14'!Q34 -> 0 | R34: =Q34-P34 -> 0 | S34: 2 | T34: =R34*S34 -> 0
D35: Description | F35: Amount | K35: 17 | N35: 32 | P35: ='14'!Q35 -> 0 | R35: =Q35-P35 -> 0 | S35: 2 | T35: =R35*S35 -> 0
K36: 18 | N36: 33 | P36: ='14'!Q36 -> 0 | R36: =Q36-P36 -> 0 | S36: 2 | T36: =R36*S36 -> 0
K37: 19 | N37: 34 | P37: ='14'!Q37 -> 0 | R37: =Q37-P37 -> 0 | S37: 1 | T37: =R37*S37 -> 0
K38: 20 | N38: 35 | P38: ='14'!Q38 -> 0 | R38: =Q38-P38 -> 0 | S38: 1 | T38: =R38*S38 -> 0
K39: 21 | N39: 36 | P39: ='14'!Q39 -> 0 | R39: =Q39-P39 -> 0 | S39: 2 | T39: =R39*S39 -> 0
A40: Total | C40: =SUM(C28:C39) -> 0 | D40: Total | F40: =SUM(F36:F39) -> 0 | H40: TOTAL | J40: =SUM(J30:J39) -> 0 | K40: TOTAL | L40: =SUM(L19:L39) -> 16557 | N40: 37 | P40: ='14'!Q40 -> 0 | R40: =Q40-P40 -> 0 | S40: 2 | T40: =R40*S40 -> 0
N41: 38 | P41: ='14'!Q41 -> 0 | R41: =Q41-P41 -> 0 | S41: 2 | T41: =R41*S41 -> 0
A42: Check Purchases | D42: Check Expenses | N42: 39 | P42: ='14'!Q42 -> 0 | R42: =Q42-P42 -> 0 | S42: 1 | T42: =R42*S42 -> 0
A43: Description | B43: Check | C43: Amount | D43: Description | E43: Check | F43: Amount | H43: CASH IN | K43: CASH OUT TO OTHER | N43: 40 | P43: ='14'!Q43 -> 0 | R43: =Q43-P43 -> 0 | S43: 1 | T43: =R43*S43 -> 0
H44: CASH IN FROM | J44: AMOUNT | K44: OTHER CASH OUT | M44: AMOUNT | N44: 41 | P44: ='14'!Q44 -> 0 | R44: =Q44-P44 -> 0 | S44: 10 | T44: =R44*S44 -> 0
H45: Take Raquel $300 | J45: 300 | N45: 42 | P45: ='14'!Q45 -> 0 | R45: =Q45-P45 -> 0 | S45: 1 | T45: =R45*S45 -> 0
H46: Intermex Rejected (#8759) | J46: 2035 | N46: 43 | P46: ='14'!Q46 -> 0 | R46: =Q46-P46 -> 0 | S46: 1 | T46: =R46*S46 -> 0
D47: Total | F47: =SUM(F44:F46) -> 0 | H47: Side Expense In | J47: 253 | N47: 44 | P47: ='14'!Q47 -> 0 | R47: =Q47-P47 -> 0 | S47: 1 | T47: =R47*S47 -> 0
D48: Rebates and Commissions | N48: 45 | P48: ='14'!Q48 -> 0 | R48: =Q48-P48 -> 0 | S48: 1 | T48: =R48*S48 -> 0
D49: Description | F49: Amount | N49: 46 | P49: ='14'!Q49 -> 0 | R49: =Q49-P49 -> 0 | S49: 1 | T49: =R49*S49 -> 0
N50: 47 | P50: ='14'!Q50 -> 0 | R50: =Q50-P50 -> 0 | S50: 1 | T50: =R50*S50 -> 0
N51: 48 | P51: ='14'!Q51 -> 0 | R51: =Q51-P51 -> 0 | S51: 1 | T51: =R51*S51 -> 0
O52: Total Lottery Sale | S52: =SUM(T4:T51) -> 0
A53: Total | C53: =SUM(C44:C52) -> 0 | D53: Total | F53: =SUM(F50:F52) -> 0 | H53: TOTAL | J53: =SUM(J45:J52) -> 2588 | K53: TOTAL | M53: =SUM(M45:M52) -> 0

Sheet 16
A1: ='1'!A1:F1 -> DINERO EXPRESS #8 (512) 8015655 | H1: =A1 -> DINERO EXPRESS #8 (512) 8015655 | M1: DATE
A2: Daily Report | D2: Date: | F2: ='15'!F2+1 -> 15 | H2: OTHER REPORTS | M2: =F2 -> 15 | O2: Lottery Sale
D3: Day: | M3: =F3 -> 0 | O3: Game # | P3: Open | Q3: Close | R3: Tic.Sold | S3: $ Value | T3: T. Sale
A4: Reciepts | C4: Amount | D4: Disbursments | F4: Amount | H4: MONEY TRANSFER | N4: 1 | P4: ='15'!Q4 -> 0 | R4: =Q4-P4 -> 0 | S4: 50 | T4: =R4*S4 -> 0
A5: ='1'!A5:B5 -> Taxable Sale | C5: 32 | D5: ='1'!D5:E5 -> Cash Purchases | F5: =C40 -> 0 | H5: Company | I5: Amount | J5: Fees | K5: Commission | L5: Individual Total Amount | N5: 2 | P5: ='15'!Q5 -> 0 | R5: =Q5-P5 -> 0 | S5: 20 | T5: =R5*S5 -> 0
A6: ='1'!A6:B6 -> Comm & Fee | C6: 3 | D6: ='1'!D6:E6 -> Cash Expense | F6: =F40 -> 0 | H6: ='1'!H6 -> DINEX | L6: =SUM(I6:K6) -> 0 | N6: 3 | P6: ='15'!Q6 -> 0 | R6: =Q6-P6 -> 0 | S6: 20 | T6: =R6*S6 -> 0
A7: ='1'!A7:B7 -> Sales Tax | D7: ='1'!D7:E7 -> Check Purchases | F7: =C53 -> 0 | H7: ='1'!H7 -> INTERMEX | I7: 4388.52 | J7: 131.4 | L7: =SUM(I7:K7) -> 4519.92 | N7: 4 | P7: ='15'!Q7 -> 0 | R7: =Q7-P7 -> 0 | S7: 10 | T7: =R7*S7 -> 0
A8: ='1'!A8:B8 -> Money Transfers | C8: =L14 -> 11850.93 | D8: ='1'!D8:E8 -> Check Expense | F8: =F47 -> 0 | H8: ='1'!H8 -> SIGUE | L8: =SUM(I8:K8) -> 0 | N8: 5 | P8: ='15'!Q8 -> 0 | R8: =Q8-P8 -> 0 | S8: 10 | T8: =R8*S8 -> 0
A9: ='1'!A9:B9 -> Lottery Sales | C9: =S52 -> 0 | D9: ='1'!D9:E9 -> Lotto Paid Out | H9: ='1'!H9 -> AFEX | L9: =SUM(I9:K9) -> 0 | N9: 6 | P9: ='15'!Q9 -> 0 | R9: =Q9-P9 -> 0 | S9: 20 | T9: =R9*S9 -> 0
A10: ='1'!A10:B10 -> Lotto Net Sales | D10: ='1'!D10:E10 -> Lottery Paid Out | H10: ='1'!H10 -> MONEYGRAM | L10: =SUM(I10:K10) -> 0 | N10: 7 | P10: ='15'!Q10 -> 0 | R10: =Q10-P10 -> 0 | S10: 20 | T10: =R10*S10 -> 0
A11: ='1'!A11:B11 -> PhoneCard | D11: ='1'!D11:E11 -> ATM Drop | H11: ='1'!H11 -> BARRI | I11: 941.51 | J11: 20 | L11: =SUM(I11:K11) -> 961.51 | N11: 8 | P11: ='15'!Q11 -> 0 | R11: =Q11-P11 -> 0 | S11: 20 | T11: =R11*S11 -> 0
A12: ='1'!A12:B12 -> Boss Revolution | D12: ='1'!D12:E12 -> Credit Card | H12: ='1'!H12 -> MAXI | I12: 6248.5 | J12: 121 | L12: =SUM(I12:K12) -> 6369.5 | N12: 9 | P12: ='15'!Q12 -> 0 | R12: =Q12-P12 -> 0 | S12: 10 | T12: =R12*S12 -> 0
A13: ='1'!A13:B13 -> Bill Payment | D13: ='1'!D13:E13 -> Outside Cash & Drops | F13: =L40 -> 9967 | H13: ='1'!H13 -> AMIGO SIN PIN | L13: =SUM(I13:K13) -> 0 | N13: 10 | P13: ='15'!Q13 -> 0 | R13: =Q13-P13 -> 0 | S13: 10 | T13: =R13*S13 -> 0
A14: ='1'!A14:B14 -> VidaPay | D14: ='1'!D14:E14 -> Cash Deposit | H14: TOTAL | I14: =SUM(I6:I13) -> 11578.53 | J14: =SUM(J6:J13) -> 272.4 | K14: =SUM(K6:K13) -> 0 | L14: =SUM(L6:M13) -> 11850.93 | N14: 11 | P14: ='15'!Q14 -> 0 | R14: =Q14-P14 -> 0 | S14: 5 | T14: =R14*S14 -> 0
A15: ='1'!A15:B15 -> Boost Epay | D15: ='1'!D15:E15 -> Money Gram Payment | N15: 12 | P15: ='15'!Q15 -> 0 | R15: =Q15-P15 -> 0 | S15: 5 | T15: =R15*S15 -> 0
A16: ='1'!A16:B16 -> Epay | D16: ='1'!D16:E16 -> Vigo Payment | N16: 13 | P16: ='15'!Q16 -> 0 | R16: =Q16-P16 -> 0 | S16: 5 | T16: =R16*S16 -> 0
A17: ='1'!A17:B17 -> Check Cashing Fees | C17: 73.21 | D17: ='1'!D17:E17 -> Ria Payment | N17: 14 | P17: ='15'!Q17 -> 0 | R17: =Q17-P17 -> 0 | S17: 5 | T17: =R17*S17 -> 0
A18: ='1'!A18:B18 -> Money Order | C18: 920 | D18: ='1'!D18:E18 -> Checks Deposit | F18: =J25 -> 14641.03 | H18: CHECK DEPOSITS | K18: DROPS | L18: AMOUNT | M18: TIME | N18: 15 | P18: ='15'!Q18 -> 0 | R18: =Q18-P18 -> 0 | S18: 5 | T18: =R18*S18 -> 0
A19: ='1'!A19:B19 -> Return Check Paid | C19: =F33 -> 0 | D19: ='1'!D19:E19 -> Safe Balance | F19: 52528 | H19: CHECK DEPOSITS TO BANK | J19: AMOUNT | K19: 1 | L19: 2247 | M19: 11:58AM | N19: 16 | P19: ='15'!Q19 -> 0 | R19: =Q19-P19 -> 0 | S19: 5 | T19: =R19*S19 -> 0
A20: ='1'!A20:B20 -> Forward Balance | C20: ='15'!F19+'15'!F13 -> 66072 | D20: ='1'!D20:E20 -> Payroll Expense | F20: =J40 -> 0 | H20: NIZARI (14 Checks) | J20: 14641.03 | K20: 2 | L20: 4160 | M20: 7:19PM | N20: 17 | P20: ='15'!Q20 -> 0 | R20: =Q20-P20 -> 0 | S20: 5 | T20: =R20*S20 -> 0
A21: ='1'!A21:B21 -> Cash From Bank | D21: ='1'!D21:E21 -> Other Cash Out | F21: =M53 -> 2035 | K21: 3 | L21: 2396 | M21: 8:42PM | N21: 18 | P21: ='15'!Q21 -> 0 | R21: =Q21-P21 -> 0 | S21: 5 | T21: =R21*S21 -> 0
A22: ='1'!A22:B22 -> Other Cash In | C22: =J53 -> 219 | D22: TOTAL PAYOUTS | F22: =SUM(F5:F21)-F7-F8 -> 79171.03 | K22: 4 | L22: 1164 | M22: 9:25PM | N22: 19 | P22: ='15'!Q22 -> 0 | R22: =Q22-P22 -> 0 | S22: 5 | T22: =R22*S22 -> 0
A23: ='1'!A23:B23 -> Rebates & Commissions | C23: =F53 -> 0 | D23: Inside Over - (Short) | F23: =(F11+F14+F15+F16+F17+F18+F19+F20+F21+F5+F6)-(C17+C19+C20+C21+C22+C23) -> 2839.82 | K23: 5 | N23: 20 | P23: ='15'!Q23 -> 0 | R23: =Q23-P23 -> 0 | S23: 5 | T23: =R23*S23 -> 0
A24: TOTAL RECEIPTS | C24: =SUM(C5:C23) -> 79170.14 | D24: Over All Over - (Short) | F24: =SUM(F22-C24) -> 0.89 | K24: 6 | N24: 21 | P24: ='15'!Q24 -> 0 | R24: =Q24-P24 -> 0 | S24: 5 | T24: =R24*S24 -> 0
A25: Out Side Over - (Short) | C25: =(F9+F10+F12+F13)-(C5+C6+C7+C8+C9+C10+C11+C12+C13+C14+C15+C16+C18) -> -2838.93 | H25: TOTAL | J25: =SUM(J20:J24) -> 14641.03 | K25: 7 | N25: 22 | P25: ='15'!Q25 -> 0 | R25: =Q25-P25 -> 0 | S25: 5 | T25: =R25*S25 -> 0
A26: Cash Purchases | D26: Return Check Paid | K26: 8 | N26: 23 | P26: ='15'!Q26 -> 0 | R26: =Q26-P26 -> 0 | S26: 3 | T26: =R26*S26 -> 0
A27: Description | C27: Amount | D27: Description | F27: Amount | K27: 9 | N27: 24 | P27: ='15'!Q27 -> 0 | R27: =Q27-P27 -> 0 | S27: 3 | T27: =R27*S27 -> 0
H28: CASH PAYROLL EXPENSE | K28: 10 | N28: 25 | P28: ='15'!Q28 -> 0 | R28: =Q28-P28 -> 0 | S28: 2 | T28: =R28*S28 -> 0
H29: CASH PAYROLL PAID TO | J29: AMOUNT | K29: 11 | N29: 26 | P29: ='15'!Q29 -> 0 | R29: =Q29-P29 -> 0 | S29: 5 | T29: =R29*S29 -> 0
K30: 12 | N30: 27 | P30: ='15'!Q30 -> 0 | R30: =Q30-P30 -> 0 | S30: 3 | T30: =R30*S30 -> 0
K31: 13 | N31: 28 | P31: ='15'!Q31 -> 0 | R31: =Q31-P31 -> 0 | S31: 3 | T31: =R31*S31 -> 0
K32: 14 | N32: 29 | P32: ='15'!Q32 -> 0 | R32: =Q32-P32 -> 0 | S32: 2 | T32: =R32*S32 -> 0
D33: Total | F33: =SUM(F28:F32) -> 0 | K33: 15 | N33: 30 | P33: ='15'!Q33 -> 0 | R33: =Q33-P33 -> 0 | S33: 2 | T33: =R33*S33 -> 0
D34: Cash Expense | K34: 16 | N34: 31 | P34: ='15'!Q34 -> 0 | R34: =Q34-P34 -> 0 | S34: 2 | T34: =R34*S34 -> 0
D35: Description | F35: Amount | K35: 17 | N35: 32 | P35: ='15'!Q35 -> 0 | R35: =Q35-P35 -> 0 | S35: 2 | T35: =R35*S35 -> 0
K36: 18 | N36: 33 | P36: ='15'!Q36 -> 0 | R36: =Q36-P36 -> 0 | S36: 2 | T36: =R36*S36 -> 0
K37: 19 | N37: 34 | P37: ='15'!Q37 -> 0 | R37: =Q37-P37 -> 0 | S37: 1 | T37: =R37*S37 -> 0
K38: 20 | N38: 35 | P38: ='15'!Q38 -> 0 | R38: =Q38-P38 -> 0 | S38: 1 | T38: =R38*S38 -> 0
K39: 21 | N39: 36 | P39: ='15'!Q39 -> 0 | R39: =Q39-P39 -> 0 | S39: 2 | T39: =R39*S39 -> 0
A40: Total | C40: =SUM(C28:C39) -> 0 | D40: Total | F40: =SUM(F36:F39) -> 0 | H40: TOTAL | J40: =SUM(J30:J39) -> 0 | K40: TOTAL | L40: =SUM(L19:L39) -> 9967 | N40: 37 | P40: ='15'!Q40 -> 0 | R40: =Q40-P40 -> 0 | S40: 2 | T40: =R40*S40 -> 0
N41: 38 | P41: ='15'!Q41 -> 0 | R41: =Q41-P41 -> 0 | S41: 2 | T41: =R41*S41 -> 0
A42: Check Purchases | D42: Check Expenses | N42: 39 | P42: ='15'!Q42 -> 0 | R42: =Q42-P42 -> 0 | S42: 1 | T42: =R42*S42 -> 0
A43: Description | B43: Check | C43: Amount | D43: Description | E43: Check | F43: Amount | H43: CASH IN | K43: CASH OUT TO OTHER | N43: 40 | P43: ='15'!Q43 -> 0 | R43: =Q43-P43 -> 0 | S43: 1 | T43: =R43*S43 -> 0
H44: CASH IN FROM | J44: AMOUNT | K44: OTHER CASH OUT | M44: AMOUNT | N44: 41 | P44: ='15'!Q44 -> 0 | R44: =Q44-P44 -> 0 | S44: 10 | T44: =R44*S44 -> 0
H45: Maxi Cancel (#6139) | J45: 150 | K45: Intermex Yesterday Refund (#8759) | M45: 2035 | N45: 42 | P45: ='15'!Q45 -> 0 | R45: =Q45-P45 -> 0 | S45: 1 | T45: =R45*S45 -> 0
H46: Side Expense In | J46: 69 | N46: 43 | P46: ='15'!Q46 -> 0 | R46: =Q46-P46 -> 0 | S46: 1 | T46: =R46*S46 -> 0
D47: Total | F47: =SUM(F44:F46) -> 0 | N47: 44 | P47: ='15'!Q47 -> 0 | R47: =Q47-P47 -> 0 | S47: 1 | T47: =R47*S47 -> 0
D48: Rebates and Commissions | N48: 45 | P48: ='15'!Q48 -> 0 | R48: =Q48-P48 -> 0 | S48: 1 | T48: =R48*S48 -> 0
D49: Description | F49: Amount | N49: 46 | P49: ='15'!Q49 -> 0 | R49: =Q49-P49 -> 0 | S49: 1 | T49: =R49*S49 -> 0
N50: 47 | P50: ='15'!Q50 -> 0 | R50: =Q50-P50 -> 0 | S50: 1 | T50: =R50*S50 -> 0
N51: 48 | P51: ='15'!Q51 -> 0 | R51: =Q51-P51 -> 0 | S51: 1 | T51: =R51*S51 -> 0
O52: Total Lottery Sale | S52: =SUM(T4:T51) -> 0
A53: Total | C53: =SUM(C44:C52) -> 0 | D53: Total | F53: =SUM(F50:F52) -> 0 | H53: TOTAL | J53: =SUM(J45:J52) -> 219 | K53: TOTAL | M53: =SUM(M45:M52) -> 2035

Sheet 17
A1: ='1'!A1:F1 -> DINERO EXPRESS #8 (512) 8015655 | H1: =A1 -> DINERO EXPRESS #8 (512) 8015655 | M1: DATE
A2: Daily Report | D2: Date: | F2: ='16'!F2+1 -> 16 | H2: OTHER REPORTS | M2: =F2 -> 16 | O2: Lottery Sale
D3: Day: | M3: =F3 -> 0 | O3: Game # | P3: Open | Q3: Close | R3: Tic.Sold | S3: $ Value | T3: T. Sale
A4: Reciepts | C4: Amount | D4: Disbursments | F4: Amount | H4: MONEY TRANSFER | N4: 1 | P4: ='16'!Q4 -> 0 | R4: =Q4-P4 -> 0 | S4: 50 | T4: =R4*S4 -> 0
A5: ='1'!A5:B5 -> Taxable Sale | D5: ='1'!D5:E5 -> Cash Purchases | F5: =C40 -> 0 | H5: Company | I5: Amount | J5: Fees | K5: Commission | L5: Individual Total Amount | N5: 2 | P5: ='16'!Q5 -> 0 | R5: =Q5-P5 -> 0 | S5: 20 | T5: =R5*S5 -> 0
A6: ='1'!A6:B6 -> Comm & Fee | C6: 5 | D6: ='1'!D6:E6 -> Cash Expense | F6: =F40 -> 0 | H6: ='1'!H6 -> DINEX | L6: =SUM(I6:K6) -> 0 | N6: 3 | P6: ='16'!Q6 -> 0 | R6: =Q6-P6 -> 0 | S6: 20 | T6: =R6*S6 -> 0
A7: ='1'!A7:B7 -> Sales Tax | D7: ='1'!D7:E7 -> Check Purchases | F7: =C53 -> 0 | H7: ='1'!H7 -> INTERMEX | I7: 3277.6 | J7: 108 | L7: =SUM(I7:K7) -> 3385.6 | N7: 4 | P7: ='16'!Q7 -> 0 | R7: =Q7-P7 -> 0 | S7: 10 | T7: =R7*S7 -> 0
A8: ='1'!A8:B8 -> Money Transfers | C8: =L14 -> 11070.36 | D8: ='1'!D8:E8 -> Check Expense | F8: =F47 -> 0 | H8: ='1'!H8 -> SIGUE | L8: =SUM(I8:K8) -> 0 | N8: 5 | P8: ='16'!Q8 -> 0 | R8: =Q8-P8 -> 0 | S8: 10 | T8: =R8*S8 -> 0
A9: ='1'!A9:B9 -> Lottery Sales | C9: =S52 -> 0 | D9: ='1'!D9:E9 -> Lotto Paid Out | H9: ='1'!H9 -> AFEX | L9: =SUM(I9:K9) -> 0 | N9: 6 | P9: ='16'!Q9 -> 0 | R9: =Q9-P9 -> 0 | S9: 20 | T9: =R9*S9 -> 0
A10: ='1'!A10:B10 -> Lotto Net Sales | D10: ='1'!D10:E10 -> Lottery Paid Out | H10: ='1'!H10 -> MONEYGRAM | L10: =SUM(I10:K10) -> 0 | N10: 7 | P10: ='16'!Q10 -> 0 | R10: =Q10-P10 -> 0 | S10: 20 | T10: =R10*S10 -> 0
A11: ='1'!A11:B11 -> PhoneCard | D11: ='1'!D11:E11 -> ATM Drop | H11: ='1'!H11 -> BARRI | I11: 3030 | J11: 40 | L11: =SUM(I11:K11) -> 3070 | N11: 8 | P11: ='16'!Q11 -> 0 | R11: =Q11-P11 -> 0 | S11: 20 | T11: =R11*S11 -> 0
A12: ='1'!A12:B12 -> Boss Revolution | D12: ='1'!D12:E12 -> Credit Card | H12: ='1'!H12 -> MAXI | I12: 4463.76 | J12: 151 | L12: =SUM(I12:K12) -> 4614.76 | N12: 9 | P12: ='16'!Q12 -> 0 | R12: =Q12-P12 -> 0 | S12: 10 | T12: =R12*S12 -> 0
A13: ='1'!A13:B13 -> Bill Payment | D13: ='1'!D13:E13 -> Outside Cash & Drops | F13: =L40 -> 10902 | H13: ='1'!H13 -> AMIGO SIN PIN | L13: =SUM(I13:K13) -> 0 | N13: 10 | P13: ='16'!Q13 -> 0 | R13: =Q13-P13 -> 0 | S13: 10 | T13: =R13*S13 -> 0
A14: ='1'!A14:B14 -> VidaPay | D14: ='1'!D14:E14 -> Cash Deposit | H14: TOTAL | I14: =SUM(I6:I13) -> 10771.36 | J14: =SUM(J6:J13) -> 299 | K14: =SUM(K6:K13) -> 0 | L14: =SUM(L6:M13) -> 11070.36 | N14: 11 | P14: ='16'!Q14 -> 0 | R14: =Q14-P14 -> 0 | S14: 5 | T14: =R14*S14 -> 0
A15: ='1'!A15:B15 -> Boost Epay | D15: ='1'!D15:E15 -> Money Gram Payment | N15: 12 | P15: ='16'!Q15 -> 0 | R15: =Q15-P15 -> 0 | S15: 5 | T15: =R15*S15 -> 0
A16: ='1'!A16:B16 -> Epay | D16: ='1'!D16:E16 -> Vigo Payment | N16: 13 | P16: ='16'!Q16 -> 0 | R16: =Q16-P16 -> 0 | S16: 5 | T16: =R16*S16 -> 0
A17: ='1'!A17:B17 -> Check Cashing Fees | C17: 485.96 | D17: ='1'!D17:E17 -> Ria Payment | N17: 14 | P17: ='16'!Q17 -> 0 | R17: =Q17-P17 -> 0 | S17: 5 | T17: =R17*S17 -> 0
A18: ='1'!A18:B18 -> Money Order | C18: 1709.38 | D18: ='1'!D18:E18 -> Checks Deposit | F18: =J25 -> 60702.68 | H18: CHECK DEPOSITS | K18: DROPS | L18: AMOUNT | M18: TIME | N18: 15 | P18: ='16'!Q18 -> 0 | R18: =Q18-P18 -> 0 | S18: 5 | T18: =R18*S18 -> 0
A19: ='1'!A19:B19 -> Return Check Paid | C19: =F33 -> 1435 | D19: ='1'!D19:E19 -> Safe Balance | F19: 45763 | H19: CHECK DEPOSITS TO BANK | J19: AMOUNT | K19: 1 | L19: 1705 | M19: 1:50PM | N19: 16 | P19: ='16'!Q19 -> 0 | R19: =Q19-P19 -> 0 | S19: 5 | T19: =R19*S19 -> 0
A20: ='1'!A20:B20 -> Forward Balance | C20: ='16'!F19+'16'!F13 -> 62495 | D20: ='1'!D20:E20 -> Payroll Expense | F20: =J40 -> 0 | H20: NIZARI (10 Checks) | J20: 24671.37 | K20: 2 | L20: 4580 | M20: 7:55PM | N20: 17 | P20: ='16'!Q20 -> 0 | R20: =Q20-P20 -> 0 | S20: 5 | T20: =R20*S20 -> 0
A21: ='1'!A21:B21 -> Cash From Bank | C21: 78300 | D21: ='1'!D21:E21 -> Other Cash Out | F21: =M53 -> 42150 | H21: NIZARI (35 Checks) | J21: 36031.31 | K21: 3 | L21: 4500 | M21: 5:42PM | N21: 18 | P21: ='16'!Q21 -> 0 | R21: =Q21-P21 -> 0 | S21: 5 | T21: =R21*S21 -> 0
A22: ='1'!A22:B22 -> Other Cash In | C22: =J53 -> 4016 | D22: TOTAL PAYOUTS | F22: =SUM(F5:F21)-F7-F8 -> 159517.68 | K22: 4 | L22: 117 | M22: 8:45PM | N22: 19 | P22: ='16'!Q22 -> 0 | R22: =Q22-P22 -> 0 | S22: 5 | T22: =R22*S22 -> 0
A23: ='1'!A23:B23 -> Rebates & Commissions | C23: =F53 -> 0 | D23: Inside Over - (Short) | F23: =(F11+F14+F15+F16+F17+F18+F19+F20+F21+F5+F6)-(C17+C19+C20+C21+C22+C23) -> 1883.72 | K23: 5 | N23: 20 | P23: ='16'!Q23 -> 0 | R23: =Q23-P23 -> 0 | S23: 5 | T23: =R23*S23 -> 0
A24: TOTAL RECEIPTS | C24: =SUM(C5:C23) -> 159516.7 | D24: Over All Over - (Short) | F24: =SUM(F22-C24) -> 0.98 | K24: 6 | N24: 21 | P24: ='16'!Q24 -> 0 | R24: =Q24-P24 -> 0 | S24: 5 | T24: =R24*S24 -> 0
A25: Out Side Over - (Short) | C25: =(F9+F10+F12+F13)-(C5+C6+C7+C8+C9+C10+C11+C12+C13+C14+C15+C16+C18) -> -1882.74 | H25: TOTAL | J25: =SUM(J20:J24) -> 60702.68 | K25: 7 | N25: 22 | P25: ='16'!Q25 -> 0 | R25: =Q25-P25 -> 0 | S25: 5 | T25: =R25*S25 -> 0
A26: Cash Purchases | D26: Return Check Paid | K26: 8 | N26: 23 | P26: ='16'!Q26 -> 0 | R26: =Q26-P26 -> 0 | S26: 3 | T26: =R26*S26 -> 0
A27: Description | C27: Amount | D27: Description | F27: Amount | K27: 9 | N27: 24 | P27: ='16'!Q27 -> 0 | R27: =Q27-P27 -> 0 | S27: 3 | T27: =R27*S27 -> 0
D28: Vicks Tree #117 | F28: 1435 | H28: CASH PAYROLL EXPENSE | K28: 10 | N28: 25 | P28: ='16'!Q28 -> 0 | R28: =Q28-P28 -> 0 | S28: 2 | T28: =R28*S28 -> 0
H29: CASH PAYROLL PAID TO | J29: AMOUNT | K29: 11 | N29: 26 | P29: ='16'!Q29 -> 0 | R29: =Q29-P29 -> 0 | S29: 5 | T29: =R29*S29 -> 0
K30: 12 | N30: 27 | P30: ='16'!Q30 -> 0 | R30: =Q30-P30 -> 0 | S30: 3 | T30: =R30*S30 -> 0
K31: 13 | N31: 28 | P31: ='16'!Q31 -> 0 | R31: =Q31-P31 -> 0 | S31: 3 | T31: =R31*S31 -> 0
K32: 14 | N32: 29 | P32: ='16'!Q32 -> 0 | R32: =Q32-P32 -> 0 | S32: 2 | T32: =R32*S32 -> 0
D33: Total | F33: =SUM(F28:F32) -> 1435 | K33: 15 | N33: 30 | P33: ='16'!Q33 -> 0 | R33: =Q33-P33 -> 0 | S33: 2 | T33: =R33*S33 -> 0
D34: Cash Expense | K34: 16 | N34: 31 | P34: ='16'!Q34 -> 0 | R34: =Q34-P34 -> 0 | S34: 2 | T34: =R34*S34 -> 0
D35: Description | F35: Amount | K35: 17 | N35: 32 | P35: ='16'!Q35 -> 0 | R35: =Q35-P35 -> 0 | S35: 2 | T35: =R35*S35 -> 0
K36: 18 | N36: 33 | P36: ='16'!Q36 -> 0 | R36: =Q36-P36 -> 0 | S36: 2 | T36: =R36*S36 -> 0
K37: 19 | N37: 34 | P37: ='16'!Q37 -> 0 | R37: =Q37-P37 -> 0 | S37: 1 | T37: =R37*S37 -> 0
K38: 20 | N38: 35 | P38: ='16'!Q38 -> 0 | R38: =Q38-P38 -> 0 | S38: 1 | T38: =R38*S38 -> 0
K39: 21 | N39: 36 | P39: ='16'!Q39 -> 0 | R39: =Q39-P39 -> 0 | S39: 2 | T39: =R39*S39 -> 0
A40: Total | C40: =SUM(C28:C39) -> 0 | D40: Total | F40: =SUM(F36:F39) -> 0 | H40: TOTAL | J40: =SUM(J30:J39) -> 0 | K40: TOTAL | L40: =SUM(L19:L39) -> 10902 | N40: 37 | P40: ='16'!Q40 -> 0 | R40: =Q40-P40 -> 0 | S40: 2 | T40: =R40*S40 -> 0
N41: 38 | P41: ='16'!Q41 -> 0 | R41: =Q41-P41 -> 0 | S41: 2 | T41: =R41*S41 -> 0
A42: Check Purchases | D42: Check Expenses | N42: 39 | P42: ='16'!Q42 -> 0 | R42: =Q42-P42 -> 0 | S42: 1 | T42: =R42*S42 -> 0
A43: Description | B43: Check | C43: Amount | D43: Description | E43: Check | F43: Amount | H43: CASH IN | K43: CASH OUT TO OTHER | N43: 40 | P43: ='16'!Q43 -> 0 | R43: =Q43-P43 -> 0 | S43: 1 | T43: =R43*S43 -> 0
H44: CASH IN FROM | J44: AMOUNT | K44: OTHER CASH OUT | M44: AMOUNT | N44: 41 | P44: ='16'!Q44 -> 0 | R44: =Q44-P44 -> 0 | S44: 10 | T44: =R44*S44 -> 0
H45: LED Check | J45: 3510 | K45: ATM Main Office Out | M45: 2000 | N45: 42 | P45: ='16'!Q45 -> 0 | R45: =Q45-P45 -> 0 | S45: 1 | T45: =R45*S45 -> 0
H46: Side Expense In | J46: 506 | K46: Maxi Re-Envios (#6139) | M46: 150 | N46: 43 | P46: ='16'!Q46 -> 0 | R46: =Q46-P46 -> 0 | S46: 1 | T46: =R46*S46 -> 0
D47: Total | F47: =SUM(F44:F46) -> 0 | K47: LED Logistics LLC (23 Checks) | M47: 40000 | N47: 44 | P47: ='16'!Q47 -> 0 | R47: =Q47-P47 -> 0 | S47: 1 | T47: =R47*S47 -> 0
D48: Rebates and Commissions | N48: 45 | P48: ='16'!Q48 -> 0 | R48: =Q48-P48 -> 0 | S48: 1 | T48: =R48*S48 -> 0
D49: Description | F49: Amount | N49: 46 | P49: ='16'!Q49 -> 0 | R49: =Q49-P49 -> 0 | S49: 1 | T49: =R49*S49 -> 0
N50: 47 | P50: ='16'!Q50 -> 0 | R50: =Q50-P50 -> 0 | S50: 1 | T50: =R50*S50 -> 0
N51: 48 | P51: ='16'!Q51 -> 0 | R51: =Q51-P51 -> 0 | S51: 1 | T51: =R51*S51 -> 0
O52: Total Lottery Sale | S52: =SUM(T4:T51) -> 0
A53: Total | C53: =SUM(C44:C52) -> 0 | D53: Total | F53: =SUM(F50:F52) -> 0 | H53: TOTAL | J53: =SUM(J45:J52) -> 4016 | K53: TOTAL | M53: =SUM(M45:M52) -> 42150

Sheet 18
A1: ='1'!A1:F1 -> DINERO EXPRESS #8 (512) 8015655 | H1: =A1 -> DINERO EXPRESS #8 (512) 8015655 | M1: DATE
A2: Daily Report | D2: Date: | F2: ='17'!F2+1 -> 17 | H2: OTHER REPORTS | M2: =F2 -> 17 | O2: Lottery Sale
D3: Day: | M3: =F3 -> 0 | O3: Game # | P3: Open | Q3: Close | R3: Tic.Sold | S3: $ Value | T3: T. Sale
A4: Reciepts | C4: Amount | D4: Disbursments | F4: Amount | H4: MONEY TRANSFER | N4: 1 | P4: ='17'!Q4 -> 0 | R4: =Q4-P4 -> 0 | S4: 50 | T4: =R4*S4 -> 0
A5: ='1'!A5:B5 -> Taxable Sale | C5: 6 | D5: ='1'!D5:E5 -> Cash Purchases | F5: =C40 -> 0 | H5: Company | I5: Amount | J5: Fees | K5: Commission | L5: Individual Total Amount | N5: 2 | P5: ='17'!Q5 -> 0 | R5: =Q5-P5 -> 0 | S5: 20 | T5: =R5*S5 -> 0
A6: ='1'!A6:B6 -> Comm & Fee | D6: ='1'!D6:E6 -> Cash Expense | F6: =F40 -> 0 | H6: ='1'!H6 -> DINEX | L6: =SUM(I6:K6) -> 0 | N6: 3 | P6: ='17'!Q6 -> 0 | R6: =Q6-P6 -> 0 | S6: 20 | T6: =R6*S6 -> 0
A7: ='1'!A7:B7 -> Sales Tax | D7: ='1'!D7:E7 -> Check Purchases | F7: =C53 -> 0 | H7: ='1'!H7 -> INTERMEX | I7: 12691.4 | J7: 239 | L7: =SUM(I7:K7) -> 12930.4 | N7: 4 | P7: ='17'!Q7 -> 0 | R7: =Q7-P7 -> 0 | S7: 10 | T7: =R7*S7 -> 0
A8: ='1'!A8:B8 -> Money Transfers | C8: =L14 -> 17322.5 | D8: ='1'!D8:E8 -> Check Expense | F8: =F47 -> 0 | H8: ='1'!H8 -> SIGUE | L8: =SUM(I8:K8) -> 0 | N8: 5 | P8: ='17'!Q8 -> 0 | R8: =Q8-P8 -> 0 | S8: 10 | T8: =R8*S8 -> 0
A9: ='1'!A9:B9 -> Lottery Sales | C9: =S52 -> 0 | D9: ='1'!D9:E9 -> Lotto Paid Out | H9: ='1'!H9 -> AFEX | L9: =SUM(I9:K9) -> 0 | N9: 6 | P9: ='17'!Q9 -> 0 | R9: =Q9-P9 -> 0 | S9: 20 | T9: =R9*S9 -> 0
A10: ='1'!A10:B10 -> Lotto Net Sales | D10: ='1'!D10:E10 -> Lottery Paid Out | H10: ='1'!H10 -> MONEYGRAM | L10: =SUM(I10:K10) -> 0 | N10: 7 | P10: ='17'!Q10 -> 0 | R10: =Q10-P10 -> 0 | S10: 20 | T10: =R10*S10 -> 0
A11: ='1'!A11:B11 -> PhoneCard | D11: ='1'!D11:E11 -> ATM Drop | H11: ='1'!H11 -> BARRI | I11: 1420 | J11: 40 | L11: =SUM(I11:K11) -> 1460 | N11: 8 | P11: ='17'!Q11 -> 0 | R11: =Q11-P11 -> 0 | S11: 20 | T11: =R11*S11 -> 0
A12: ='1'!A12:B12 -> Boss Revolution | D12: ='1'!D12:E12 -> Credit Card | H12: ='1'!H12 -> MAXI | I12: 2851.1 | J12: 81 | L12: =SUM(I12:K12) -> 2932.1 | N12: 9 | P12: ='17'!Q12 -> 0 | R12: =Q12-P12 -> 0 | S12: 10 | T12: =R12*S12 -> 0
A13: ='1'!A13:B13 -> Bill Payment | D13: ='1'!D13:E13 -> Outside Cash & Drops | F13: =L40 -> 17325 | H13: ='1'!H13 -> AMIGO SIN PIN | L13: =SUM(I13:K13) -> 0 | N13: 10 | P13: ='17'!Q13 -> 0 | R13: =Q13-P13 -> 0 | S13: 10 | T13: =R13*S13 -> 0
A14: ='1'!A14:B14 -> VidaPay | D14: ='1'!D14:E14 -> Cash Deposit | H14: TOTAL | I14: =SUM(I6:I13) -> 16962.5 | J14: =SUM(J6:J13) -> 360 | K14: =SUM(K6:K13) -> 0 | L14: =SUM(L6:M13) -> 17322.5 | N14: 11 | P14: ='17'!Q14 -> 0 | R14: =Q14-P14 -> 0 | S14: 5 | T14: =R14*S14 -> 0
A15: ='1'!A15:B15 -> Boost Epay | D15: ='1'!D15:E15 -> Money Gram Payment | N15: 12 | P15: ='17'!Q15 -> 0 | R15: =Q15-P15 -> 0 | S15: 5 | T15: =R15*S15 -> 0
A16: ='1'!A16:B16 -> Epay | D16: ='1'!D16:E16 -> Vigo Payment | N16: 13 | P16: ='17'!Q16 -> 0 | R16: =Q16-P16 -> 0 | S16: 5 | T16: =R16*S16 -> 0
A17: ='1'!A17:B17 -> Check Cashing Fees | C17: 181.65 | D17: ='1'!D17:E17 -> Ria Payment | N17: 14 | P17: ='17'!Q17 -> 0 | R17: =Q17-P17 -> 0 | S17: 5 | T17: =R17*S17 -> 0
A18: ='1'!A18:B18 -> Money Order | D18: ='1'!D18:E18 -> Checks Deposit | F18: =J25 -> 34829.38 | H18: CHECK DEPOSITS | K18: DROPS | L18: AMOUNT | M18: TIME | N18: 15 | P18: ='17'!Q18 -> 0 | R18: =Q18-P18 -> 0 | S18: 5 | T18: =R18*S18 -> 0
A19: ='1'!A19:B19 -> Return Check Paid | C19: =F33 -> 0 | D19: ='1'!D19:E19 -> Safe Balance | F19: 62202 | H19: CHECK DEPOSITS TO BANK | J19: AMOUNT | K19: 1 | L19: 5610 | M19: 3:06PM | N19: 16 | P19: ='17'!Q19 -> 0 | R19: =Q19-P19 -> 0 | S19: 5 | T19: =R19*S19 -> 0
A20: ='1'!A20:B20 -> Forward Balance | C20: ='17'!F19+'17'!F13 -> 56665 | D20: ='1'!D20:E20 -> Payroll Expense | F20: =J40 -> 0 | H20: NIZARI (7 Checks) | J20: 5553.95 | K20: 2 | L20: 3200 | M20: 4:05PM | N20: 17 | P20: ='17'!Q20 -> 0 | R20: =Q20-P20 -> 0 | S20: 5 | T20: =R20*S20 -> 0
A21: ='1'!A21:B21 -> Cash From Bank | C21: 41000 | D21: ='1'!D21:E21 -> Other Cash Out | F21: =M53 -> 3000 | H21: NIZARI (4 Checks) | J21: 3089.27 | K21: 3 | L21: 4560 | M21: 6:46PM | N21: 18 | P21: ='17'!Q21 -> 0 | R21: =Q21-P21 -> 0 | S21: 5 | T21: =R21*S21 -> 0
A22: ='1'!A22:B22 -> Other Cash In | C22: =J53 -> 2181 | D22: TOTAL PAYOUTS | F22: =SUM(F5:F21)-F7-F8 -> 117356.38 | H22: NIZARI (23 Checks) | J22: 26186.16 | K22: 4 | L22: 3955 | M22: 8:51PM | N22: 19 | P22: ='17'!Q22 -> 0 | R22: =Q22-P22 -> 0 | S22: 5 | T22: =R22*S22 -> 0
A23: ='1'!A23:B23 -> Rebates & Commissions | C23: =F53 -> 0 | D23: Inside Over - (Short) | F23: =(F11+F14+F15+F16+F17+F18+F19+F20+F21+F5+F6)-(C17+C19+C20+C21+C22+C23) -> 3.73 | K23: 5 | N23: 20 | P23: ='17'!Q23 -> 0 | R23: =Q23-P23 -> 0 | S23: 5 | T23: =R23*S23 -> 0
A24: TOTAL RECEIPTS | C24: =SUM(C5:C23) -> 117356.15 | D24: Over All Over - (Short) | F24: =SUM(F22-C24) -> 0.23 | K24: 6 | N24: 21 | P24: ='17'!Q24 -> 0 | R24: =Q24-P24 -> 0 | S24: 5 | T24: =R24*S24 -> 0
A25: Out Side Over - (Short) | C25: =(F9+F10+F12+F13)-(C5+C6+C7+C8+C9+C10+C11+C12+C13+C14+C15+C16+C18) -> -3.5 | H25: TOTAL | J25: =SUM(J20:J24) -> 34829.38 | K25: 7 | N25: 22 | P25: ='17'!Q25 -> 0 | R25: =Q25-P25 -> 0 | S25: 5 | T25: =R25*S25 -> 0
A26: Cash Purchases | D26: Return Check Paid | K26: 8 | N26: 23 | P26: ='17'!Q26 -> 0 | R26: =Q26-P26 -> 0 | S26: 3 | T26: =R26*S26 -> 0
A27: Description | C27: Amount | D27: Description | F27: Amount | K27: 9 | N27: 24 | P27: ='17'!Q27 -> 0 | R27: =Q27-P27 -> 0 | S27: 3 | T27: =R27*S27 -> 0
H28: CASH PAYROLL EXPENSE | K28: 10 | N28: 25 | P28: ='17'!Q28 -> 0 | R28: =Q28-P28 -> 0 | S28: 2 | T28: =R28*S28 -> 0
H29: CASH PAYROLL PAID TO | J29: AMOUNT | K29: 11 | N29: 26 | P29: ='17'!Q29 -> 0 | R29: =Q29-P29 -> 0 | S29: 5 | T29: =R29*S29 -> 0
K30: 12 | N30: 27 | P30: ='17'!Q30 -> 0 | R30: =Q30-P30 -> 0 | S30: 3 | T30: =R30*S30 -> 0
K31: 13 | N31: 28 | P31: ='17'!Q31 -> 0 | R31: =Q31-P31 -> 0 | S31: 3 | T31: =R31*S31 -> 0
K32: 14 | N32: 29 | P32: ='17'!Q32 -> 0 | R32: =Q32-P32 -> 0 | S32: 2 | T32: =R32*S32 -> 0
D33: Total | F33: =SUM(F28:F32) -> 0 | K33: 15 | N33: 30 | P33: ='17'!Q33 -> 0 | R33: =Q33-P33 -> 0 | S33: 2 | T33: =R33*S33 -> 0
D34: Cash Expense | K34: 16 | N34: 31 | P34: ='17'!Q34 -> 0 | R34: =Q34-P34 -> 0 | S34: 2 | T34: =R34*S34 -> 0
D35: Description | F35: Amount | K35: 17 | N35: 32 | P35: ='17'!Q35 -> 0 | R35: =Q35-P35 -> 0 | S35: 2 | T35: =R35*S35 -> 0
K36: 18 | N36: 33 | P36: ='17'!Q36 -> 0 | R36: =Q36-P36 -> 0 | S36: 2 | T36: =R36*S36 -> 0
K37: 19 | N37: 34 | P37: ='17'!Q37 -> 0 | R37: =Q37-P37 -> 0 | S37: 1 | T37: =R37*S37 -> 0
K38: 20 | N38: 35 | P38: ='17'!Q38 -> 0 | R38: =Q38-P38 -> 0 | S38: 1 | T38: =R38*S38 -> 0
K39: 21 | N39: 36 | P39: ='17'!Q39 -> 0 | R39: =Q39-P39 -> 0 | S39: 2 | T39: =R39*S39 -> 0
A40: Total | C40: =SUM(C28:C39) -> 0 | D40: Total | F40: =SUM(F36:F39) -> 0 | H40: TOTAL | J40: =SUM(J30:J39) -> 0 | K40: TOTAL | L40: =SUM(L19:L39) -> 17325 | N40: 37 | P40: ='17'!Q40 -> 0 | R40: =Q40-P40 -> 0 | S40: 2 | T40: =R40*S40 -> 0
N41: 38 | P41: ='17'!Q41 -> 0 | R41: =Q41-P41 -> 0 | S41: 2 | T41: =R41*S41 -> 0
A42: Check Purchases | D42: Check Expenses | N42: 39 | P42: ='17'!Q42 -> 0 | R42: =Q42-P42 -> 0 | S42: 1 | T42: =R42*S42 -> 0
A43: Description | B43: Check | C43: Amount | D43: Description | E43: Check | F43: Amount | H43: CASH IN | K43: CASH OUT TO OTHER | N43: 40 | P43: ='17'!Q43 -> 0 | R43: =Q43-P43 -> 0 | S43: 1 | T43: =R43*S43 -> 0
H44: CASH IN FROM | J44: AMOUNT | K44: OTHER CASH OUT | M44: AMOUNT | N44: 41 | P44: ='17'!Q44 -> 0 | R44: =Q44-P44 -> 0 | S44: 10 | T44: =R44*S44 -> 0
H45: Take ATM $2K | J45: 2000 | K45: Coin Withdrawal for Main Office | M45: 1500 | N45: 42 | P45: ='17'!Q45 -> 0 | R45: =Q45-P45 -> 0 | S45: 1 | T45: =R45*S45 -> 0
H46: Side Expense Out | J46: 181 | K46: LED Logistics LLC (1 Check) | M46: 1500 | N46: 43 | P46: ='17'!Q46 -> 0 | R46: =Q46-P46 -> 0 | S46: 1 | T46: =R46*S46 -> 0
D47: Total | F47: =SUM(F44:F46) -> 0 | N47: 44 | P47: ='17'!Q47 -> 0 | R47: =Q47-P47 -> 0 | S47: 1 | T47: =R47*S47 -> 0
D48: Rebates and Commissions | N48: 45 | P48: ='17'!Q48 -> 0 | R48: =Q48-P48 -> 0 | S48: 1 | T48: =R48*S48 -> 0
D49: Description | F49: Amount | N49: 46 | P49: ='17'!Q49 -> 0 | R49: =Q49-P49 -> 0 | S49: 1 | T49: =R49*S49 -> 0
N50: 47 | P50: ='17'!Q50 -> 0 | R50: =Q50-P50 -> 0 | S50: 1 | T50: =R50*S50 -> 0
N51: 48 | P51: ='17'!Q51 -> 0 | R51: =Q51-P51 -> 0 | S51: 1 | T51: =R51*S51 -> 0
O52: Total Lottery Sale | S52: =SUM(T4:T51) -> 0
A53: Total | C53: =SUM(C44:C52) -> 0 | D53: Total | F53: =SUM(F50:F52) -> 0 | H53: TOTAL | J53: =SUM(J45:J52) -> 2181 | K53: TOTAL | M53: =SUM(M45:M52) -> 3000

Sheet 19
A1: ='1'!A1:F1 -> DINERO EXPRESS #8 (512) 8015655 | H1: =A1 -> DINERO EXPRESS #8 (512) 8015655 | M1: DATE
A2: Daily Report | D2: Date: | F2: ='18'!F2+1 -> 18 | H2: OTHER REPORTS | M2: =F2 -> 18 | O2: Lottery Sale
D3: Day: | M3: =F3 -> 0 | O3: Game # | P3: Open | Q3: Close | R3: Tic.Sold | S3: $ Value | T3: T. Sale
A4: Reciepts | C4: Amount | D4: Disbursments | F4: Amount | H4: MONEY TRANSFER | N4: 1 | P4: ='18'!Q4 -> 0 | R4: =Q4-P4 -> 0 | S4: 50 | T4: =R4*S4 -> 0
A5: ='1'!A5:B5 -> Taxable Sale | C5: 31 | D5: ='1'!D5:E5 -> Cash Purchases | F5: =C40 -> 0 | H5: Company | I5: Amount | J5: Fees | K5: Commission | L5: Individual Total Amount | N5: 2 | P5: ='18'!Q5 -> 0 | R5: =Q5-P5 -> 0 | S5: 20 | T5: =R5*S5 -> 0
A6: ='1'!A6:B6 -> Comm & Fee | C6: 5 | D6: ='1'!D6:E6 -> Cash Expense | F6: =F40 -> 0 | H6: ='1'!H6 -> DINEX | L6: =SUM(I6:K6) -> 0 | N6: 3 | P6: ='18'!Q6 -> 0 | R6: =Q6-P6 -> 0 | S6: 20 | T6: =R6*S6 -> 0
A7: ='1'!A7:B7 -> Sales Tax | D7: ='1'!D7:E7 -> Check Purchases | F7: =C53 -> 0 | H7: ='1'!H7 -> INTERMEX | I7: 5051.07 | J7: 133 | L7: =SUM(I7:K7) -> 5184.07 | N7: 4 | P7: ='18'!Q7 -> 0 | R7: =Q7-P7 -> 0 | S7: 10 | T7: =R7*S7 -> 0
A8: ='1'!A8:B8 -> Money Transfers | C8: =L14 -> 24007.87 | D8: ='1'!D8:E8 -> Check Expense | F8: =F47 -> 0 | H8: ='1'!H8 -> SIGUE | L8: =SUM(I8:K8) -> 0 | N8: 5 | P8: ='18'!Q8 -> 0 | R8: =Q8-P8 -> 0 | S8: 10 | T8: =R8*S8 -> 0
A9: ='1'!A9:B9 -> Lottery Sales | C9: =S52 -> 0 | D9: ='1'!D9:E9 -> Lotto Paid Out | H9: ='1'!H9 -> AFEX | L9: =SUM(I9:K9) -> 0 | N9: 6 | P9: ='18'!Q9 -> 0 | R9: =Q9-P9 -> 0 | S9: 20 | T9: =R9*S9 -> 0
A10: ='1'!A10:B10 -> Lotto Net Sales | D10: ='1'!D10:E10 -> Lottery Paid Out | H10: ='1'!H10 -> MONEYGRAM | L10: =SUM(I10:K10) -> 0 | N10: 7 | P10: ='18'!Q10 -> 0 | R10: =Q10-P10 -> 0 | S10: 20 | T10: =R10*S10 -> 0
A11: ='1'!A11:B11 -> PhoneCard | D11: ='1'!D11:E11 -> ATM Drop | H11: ='1'!H11 -> BARRI | I11: 4000.39 | J11: 49.61 | L11: =SUM(I11:K11) -> 4050 | N11: 8 | P11: ='18'!Q11 -> 0 | R11: =Q11-P11 -> 0 | S11: 20 | T11: =R11*S11 -> 0
A12: ='1'!A12:B12 -> Boss Revolution | D12: ='1'!D12:E12 -> Credit Card | H12: ='1'!H12 -> MAXI | I12: 14532.8 | J12: 241 | L12: =SUM(I12:K12) -> 14773.8 | N12: 9 | P12: ='18'!Q12 -> 0 | R12: =Q12-P12 -> 0 | S12: 10 | T12: =R12*S12 -> 0
A13: ='1'!A13:B13 -> Bill Payment | D13: ='1'!D13:E13 -> Outside Cash & Drops | F13: =L40 -> 24010 | H13: ='1'!H13 -> AMIGO SIN PIN | L13: =SUM(I13:K13) -> 0 | N13: 10 | P13: ='18'!Q13 -> 0 | R13: =Q13-P13 -> 0 | S13: 10 | T13: =R13*S13 -> 0
A14: ='1'!A14:B14 -> VidaPay | D14: ='1'!D14:E14 -> Cash Deposit | H14: TOTAL | I14: =SUM(I6:I13) -> 23584.26 | J14: =SUM(J6:J13) -> 423.61 | K14: =SUM(K6:K13) -> 0 | L14: =SUM(L6:M13) -> 24007.87 | N14: 11 | P14: ='18'!Q14 -> 0 | R14: =Q14-P14 -> 0 | S14: 5 | T14: =R14*S14 -> 0
A15: ='1'!A15:B15 -> Boost Epay | D15: ='1'!D15:E15 -> Money Gram Payment | N15: 12 | P15: ='18'!Q15 -> 0 | R15: =Q15-P15 -> 0 | S15: 5 | T15: =R15*S15 -> 0
A16: ='1'!A16:B16 -> Epay | D16: ='1'!D16:E16 -> Vigo Payment | N16: 13 | P16: ='18'!Q16 -> 0 | R16: =Q16-P16 -> 0 | S16: 5 | T16: =R16*S16 -> 0
A17: ='1'!A17:B17 -> Check Cashing Fees | C17: 169.31 | D17: ='1'!D17:E17 -> Ria Payment | N17: 14 | P17: ='18'!Q17 -> 0 | R17: =Q17-P17 -> 0 | S17: 5 | T17: =R17*S17 -> 0
A18: ='1'!A18:B18 -> Money Order | C18: 1030 | D18: ='1'!D18:E18 -> Checks Deposit | F18: =J25 -> 33661.14 | H18: CHECK DEPOSITS | K18: DROPS | L18: AMOUNT | M18: TIME | N18: 15 | P18: ='18'!Q18 -> 0 | R18: =Q18-P18 -> 0 | S18: 5 | T18: =R18*S18 -> 0
A19: ='1'!A19:B19 -> Return Check Paid | C19: =F33 -> 0 | D19: ='1'!D19:E19 -> Safe Balance | F19: 47097 | H19: CHECK DEPOSITS TO BANK | J19: AMOUNT | K19: 1 | L19: 2740 | M19: 11:57AM | N19: 16 | P19: ='18'!Q19 -> 0 | R19: =Q19-P19 -> 0 | S19: 5 | T19: =R19*S19 -> 0
A20: ='1'!A20:B20 -> Forward Balance | C20: ='18'!F19+'18'!F13 -> 79527 | D20: ='1'!D20:E20 -> Payroll Expense | F20: =J40 -> 0 | H20: NIZARI (28 Checks) | J20: 33661.14 | K20: 2 | L20: 3276 | M20: 1:49PM | N20: 17 | P20: ='18'!Q20 -> 0 | R20: =Q20-P20 -> 0 | S20: 5 | T20: =R20*S20 -> 0
A21: ='1'!A21:B21 -> Cash From Bank | D21: ='1'!D21:E21 -> Other Cash Out | F21: =M53 -> 200 | K21: 3 | L21: 4550 | M21: 5:04PM | N21: 18 | P21: ='18'!Q21 -> 0 | R21: =Q21-P21 -> 0 | S21: 5 | T21: =R21*S21 -> 0
A22: ='1'!A22:B22 -> Other Cash In | C22: =J53 -> 197 | D22: TOTAL PAYOUTS | F22: =SUM(F5:F21)-F7-F8 -> 104968.14 | K22: 4 | L22: 5770 | M22: 3:08PM | N22: 19 | P22: ='18'!Q22 -> 0 | R22: =Q22-P22 -> 0 | S22: 5 | T22: =R22*S22 -> 0
A23: ='1'!A23:B23 -> Rebates & Commissions | C23: =F53 -> 0 | D23: Inside Over - (Short) | F23: =(F11+F14+F15+F16+F17+F18+F19+F20+F21+F5+F6)-(C17+C19+C20+C21+C22+C23) -> 1064.83 | K23: 5 | L23: 2520 | M23: 7:32PM | N23: 20 | P23: ='18'!Q23 -> 0 | R23: =Q23-P23 -> 0 | S23: 5 | T23: =R23*S23 -> 0
A24: TOTAL RECEIPTS | C24: =SUM(C5:C23) -> 104967.18 | D24: Over All Over - (Short) | F24: =SUM(F22-C24) -> 0.96 | K24: 6 | L24: 3850 | M24: 8:06PM | N24: 21 | P24: ='18'!Q24 -> 0 | R24: =Q24-P24 -> 0 | S24: 5 | T24: =R24*S24 -> 0
A25: Out Side Over - (Short) | C25: =(F9+F10+F12+F13)-(C5+C6+C7+C8+C9+C10+C11+C12+C13+C14+C15+C16+C18) -> -1063.87 | H25: TOTAL | J25: =SUM(J20:J24) -> 33661.14 | K25: 7 | L25: 1175 | M25: 9:00PM | N25: 22 | P25: ='18'!Q25 -> 0 | R25: =Q25-P25 -> 0 | S25: 5 | T25: =R25*S25 -> 0
A26: Cash Purchases | D26: Return Check Paid | K26: 8 | L26: 129 | M26: 9:20PM | N26: 23 | P26: ='18'!Q26 -> 0 | R26: =Q26-P26 -> 0 | S26: 3 | T26: =R26*S26 -> 0
A27: Description | C27: Amount | D27: Description | F27: Amount | K27: 9 | N27: 24 | P27: ='18'!Q27 -> 0 | R27: =Q27-P27 -> 0 | S27: 3 | T27: =R27*S27 -> 0
H28: CASH PAYROLL EXPENSE | K28: 10 | N28: 25 | P28: ='18'!Q28 -> 0 | R28: =Q28-P28 -> 0 | S28: 2 | T28: =R28*S28 -> 0
H29: CASH PAYROLL PAID TO | J29: AMOUNT | K29: 11 | N29: 26 | P29: ='18'!Q29 -> 0 | R29: =Q29-P29 -> 0 | S29: 5 | T29: =R29*S29 -> 0
K30: 12 | N30: 27 | P30: ='18'!Q30 -> 0 | R30: =Q30-P30 -> 0 | S30: 3 | T30: =R30*S30 -> 0
K31: 13 | N31: 28 | P31: ='18'!Q31 -> 0 | R31: =Q31-P31 -> 0 | S31: 3 | T31: =R31*S31 -> 0
K32: 14 | N32: 29 | P32: ='18'!Q32 -> 0 | R32: =Q32-P32 -> 0 | S32: 2 | T32: =R32*S32 -> 0
D33: Total | F33: =SUM(F28:F32) -> 0 | K33: 15 | N33: 30 | P33: ='18'!Q33 -> 0 | R33: =Q33-P33 -> 0 | S33: 2 | T33: =R33*S33 -> 0
D34: Cash Expense | K34: 16 | N34: 31 | P34: ='18'!Q34 -> 0 | R34: =Q34-P34 -> 0 | S34: 2 | T34: =R34*S34 -> 0
D35: Description | F35: Amount | K35: 17 | N35: 32 | P35: ='18'!Q35 -> 0 | R35: =Q35-P35 -> 0 | S35: 2 | T35: =R35*S35 -> 0
K36: 18 | N36: 33 | P36: ='18'!Q36 -> 0 | R36: =Q36-P36 -> 0 | S36: 2 | T36: =R36*S36 -> 0
K37: 19 | N37: 34 | P37: ='18'!Q37 -> 0 | R37: =Q37-P37 -> 0 | S37: 1 | T37: =R37*S37 -> 0
K38: 20 | N38: 35 | P38: ='18'!Q38 -> 0 | R38: =Q38-P38 -> 0 | S38: 1 | T38: =R38*S38 -> 0
K39: 21 | N39: 36 | P39: ='18'!Q39 -> 0 | R39: =Q39-P39 -> 0 | S39: 2 | T39: =R39*S39 -> 0
A40: Total | C40: =SUM(C28:C39) -> 0 | D40: Total | F40: =SUM(F36:F39) -> 0 | H40: TOTAL | J40: =SUM(J30:J39) -> 0 | K40: TOTAL | L40: =SUM(L19:L39) -> 24010 | N40: 37 | P40: ='18'!Q40 -> 0 | R40: =Q40-P40 -> 0 | S40: 2 | T40: =R40*S40 -> 0
N41: 38 | P41: ='18'!Q41 -> 0 | R41: =Q41-P41 -> 0 | S41: 2 | T41: =R41*S41 -> 0
A42: Check Purchases | D42: Check Expenses | N42: 39 | P42: ='18'!Q42 -> 0 | R42: =Q42-P42 -> 0 | S42: 1 | T42: =R42*S42 -> 0
A43: Description | B43: Check | C43: Amount | D43: Description | E43: Check | F43: Amount | H43: CASH IN | K43: CASH OUT TO OTHER | N43: 40 | P43: ='18'!Q43 -> 0 | R43: =Q43-P43 -> 0 | S43: 1 | T43: =R43*S43 -> 0
H44: CASH IN FROM | J44: AMOUNT | K44: OTHER CASH OUT | M44: AMOUNT | N44: 41 | P44: ='18'!Q44 -> 0 | R44: =Q44-P44 -> 0 | S44: 10 | T44: =R44*S44 -> 0
H45: Side Expense In | J45: 197 | K45: LED Logistics LLC (1 Check) | M45: 200 | N45: 42 | P45: ='18'!Q45 -> 0 | R45: =Q45-P45 -> 0 | S45: 1 | T45: =R45*S45 -> 0
N46: 43 | P46: ='18'!Q46 -> 0 | R46: =Q46-P46 -> 0 | S46: 1 | T46: =R46*S46 -> 0
D47: Total | F47: =SUM(F44:F46) -> 0 | N47: 44 | P47: ='18'!Q47 -> 0 | R47: =Q47-P47 -> 0 | S47: 1 | T47: =R47*S47 -> 0
D48: Rebates and Commissions | N48: 45 | P48: ='18'!Q48 -> 0 | R48: =Q48-P48 -> 0 | S48: 1 | T48: =R48*S48 -> 0
D49: Description | F49: Amount | N49: 46 | P49: ='18'!Q49 -> 0 | R49: =Q49-P49 -> 0 | S49: 1 | T49: =R49*S49 -> 0
N50: 47 | P50: ='18'!Q50 -> 0 | R50: =Q50-P50 -> 0 | S50: 1 | T50: =R50*S50 -> 0
N51: 48 | P51: ='18'!Q51 -> 0 | R51: =Q51-P51 -> 0 | S51: 1 | T51: =R51*S51 -> 0
O52: Total Lottery Sale | S52: =SUM(T4:T51) -> 0
A53: Total | C53: =SUM(C44:C52) -> 0 | D53: Total | F53: =SUM(F50:F52) -> 0 | H53: TOTAL | J53: =SUM(J45:J52) -> 197 | K53: TOTAL | M53: =SUM(M45:M52) -> 200

Sheet 20
A1: ='1'!A1:F1 -> DINERO EXPRESS #8 (512) 8015655 | H1: =A1 -> DINERO EXPRESS #8 (512) 8015655 | M1: DATE
A2: Daily Report | D2: Date: | F2: ='19'!F2+1 -> 19 | H2: OTHER REPORTS | M2: =F2 -> 19 | O2: Lottery Sale
D3: Day: | M3: =F3 -> 0 | O3: Game # | P3: Open | Q3: Close | R3: Tic.Sold | S3: $ Value | T3: T. Sale
A4: Reciepts | C4: Amount | D4: Disbursments | F4: Amount | H4: MONEY TRANSFER | N4: 1 | P4: ='19'!Q4 -> 0 | R4: =Q4-P4 -> 0 | S4: 50 | T4: =R4*S4 -> 0
A5: ='1'!A5:B5 -> Taxable Sale | D5: ='1'!D5:E5 -> Cash Purchases | F5: =C40 -> 0 | H5: Company | I5: Amount | J5: Fees | K5: Commission | L5: Individual Total Amount | N5: 2 | P5: ='19'!Q5 -> 0 | R5: =Q5-P5 -> 0 | S5: 20 | T5: =R5*S5 -> 0
A6: ='1'!A6:B6 -> Comm & Fee | D6: ='1'!D6:E6 -> Cash Expense | F6: =F40 -> 0 | H6: ='1'!H6 -> DINEX | L6: =SUM(I6:K6) -> 0 | N6: 3 | P6: ='19'!Q6 -> 0 | R6: =Q6-P6 -> 0 | S6: 20 | T6: =R6*S6 -> 0
A7: ='1'!A7:B7 -> Sales Tax | D7: ='1'!D7:E7 -> Check Purchases | F7: =C53 -> 0 | H7: ='1'!H7 -> INTERMEX | L7: =SUM(I7:K7) -> 0 | N7: 4 | P7: ='19'!Q7 -> 0 | R7: =Q7-P7 -> 0 | S7: 10 | T7: =R7*S7 -> 0
A8: ='1'!A8:B8 -> Money Transfers | C8: =L14 -> 0 | D8: ='1'!D8:E8 -> Check Expense | F8: =F47 -> 0 | H8: ='1'!H8 -> SIGUE | L8: =SUM(I8:K8) -> 0 | N8: 5 | P8: ='19'!Q8 -> 0 | R8: =Q8-P8 -> 0 | S8: 10 | T8: =R8*S8 -> 0
A9: ='1'!A9:B9 -> Lottery Sales | C9: =S52 -> 0 | D9: ='1'!D9:E9 -> Lotto Paid Out | H9: ='1'!H9 -> AFEX | L9: =SUM(I9:K9) -> 0 | N9: 6 | P9: ='19'!Q9 -> 0 | R9: =Q9-P9 -> 0 | S9: 20 | T9: =R9*S9 -> 0
A10: ='1'!A10:B10 -> Lotto Net Sales | D10: ='1'!D10:E10 -> Lottery Paid Out | H10: ='1'!H10 -> MONEYGRAM | L10: =SUM(I10:K10) -> 0 | N10: 7 | P10: ='19'!Q10 -> 0 | R10: =Q10-P10 -> 0 | S10: 20 | T10: =R10*S10 -> 0
A11: ='1'!A11:B11 -> PhoneCard | D11: ='1'!D11:E11 -> ATM Drop | H11: ='1'!H11 -> BARRI | L11: =SUM(I11:K11) -> 0 | N11: 8 | P11: ='19'!Q11 -> 0 | R11: =Q11-P11 -> 0 | S11: 20 | T11: =R11*S11 -> 0
A12: ='1'!A12:B12 -> Boss Revolution | D12: ='1'!D12:E12 -> Credit Card | H12: ='1'!H12 -> MAXI | L12: =SUM(I12:K12) -> 0 | N12: 9 | P12: ='19'!Q12 -> 0 | R12: =Q12-P12 -> 0 | S12: 10 | T12: =R12*S12 -> 0
A13: ='1'!A13:B13 -> Bill Payment | D13: ='1'!D13:E13 -> Outside Cash & Drops | F13: =L40 -> 0 | H13: ='1'!H13 -> AMIGO SIN PIN | L13: =SUM(I13:K13) -> 0 | N13: 10 | P13: ='19'!Q13 -> 0 | R13: =Q13-P13 -> 0 | S13: 10 | T13: =R13*S13 -> 0
A14: ='1'!A14:B14 -> VidaPay | D14: ='1'!D14:E14 -> Cash Deposit | H14: TOTAL | I14: =SUM(I6:I13) -> 0 | J14: =SUM(J6:J13) -> 0 | K14: =SUM(K6:K13) -> 0 | L14: =SUM(L6:M13) -> 0 | N14: 11 | P14: ='19'!Q14 -> 0 | R14: =Q14-P14 -> 0 | S14: 5 | T14: =R14*S14 -> 0
A15: ='1'!A15:B15 -> Boost Epay | D15: ='1'!D15:E15 -> Money Gram Payment | N15: 12 | P15: ='19'!Q15 -> 0 | R15: =Q15-P15 -> 0 | S15: 5 | T15: =R15*S15 -> 0
A16: ='1'!A16:B16 -> Epay | D16: ='1'!D16:E16 -> Vigo Payment | N16: 13 | P16: ='19'!Q16 -> 0 | R16: =Q16-P16 -> 0 | S16: 5 | T16: =R16*S16 -> 0
A17: ='1'!A17:B17 -> Check Cashing Fees | D17: ='1'!D17:E17 -> Ria Payment | N17: 14 | P17: ='19'!Q17 -> 0 | R17: =Q17-P17 -> 0 | S17: 5 | T17: =R17*S17 -> 0
A18: ='1'!A18:B18 -> Money Order | D18: ='1'!D18:E18 -> Checks Deposit | F18: =J25 -> 0 | H18: CHECK DEPOSITS | K18: DROPS | L18: AMOUNT | M18: TIME | N18: 15 | P18: ='19'!Q18 -> 0 | R18: =Q18-P18 -> 0 | S18: 5 | T18: =R18*S18 -> 0
A19: ='1'!A19:B19 -> Return Check Paid | C19: =F33 -> 0 | D19: ='1'!D19:E19 -> Safe Balance | H19: CHECK DEPOSITS TO BANK | J19: AMOUNT | K19: 1 | N19: 16 | P19: ='19'!Q19 -> 0 | R19: =Q19-P19 -> 0 | S19: 5 | T19: =R19*S19 -> 0
A20: ='1'!A20:B20 -> Forward Balance | C20: ='19'!F19+'19'!F13 -> 71107 | D20: ='1'!D20:E20 -> Payroll Expense | F20: =J40 -> 0 | H20: PIONEER | K20: 2 | N20: 17 | P20: ='19'!Q20 -> 0 | R20: =Q20-P20 -> 0 | S20: 5 | T20: =R20*S20 -> 0
A21: ='1'!A21:B21 -> Cash From Bank | D21: ='1'!D21:E21 -> Other Cash Out | F21: =M53 -> 0 | H21: PIONEER | K21: 3 | N21: 18 | P21: ='19'!Q21 -> 0 | R21: =Q21-P21 -> 0 | S21: 5 | T21: =R21*S21 -> 0
A22: ='1'!A22:B22 -> Other Cash In | C22: =J53 -> 0 | D22: TOTAL PAYOUTS | F22: =SUM(F5:F21)-F7-F8 -> 0 | K22: 4 | N22: 19 | P22: ='19'!Q22 -> 0 | R22: =Q22-P22 -> 0 | S22: 5 | T22: =R22*S22 -> 0
A23: ='1'!A23:B23 -> Rebates & Commissions | C23: =F53 -> 0 | D23: Inside Over - (Short) | F23: =(F11+F14+F15+F16+F17+F18+F19+F20+F21+F5+F6)-(C17+C19+C20+C21+C22+C23) -> -71107 | K23: 5 | N23: 20 | P23: ='19'!Q23 -> 0 | R23: =Q23-P23 -> 0 | S23: 5 | T23: =R23*S23 -> 0
A24: TOTAL RECEIPTS | C24: =SUM(C5:C23) -> 71107 | D24: Over All Over - (Short) | F24: =SUM(F22-C24) -> -71107 | K24: 6 | N24: 21 | P24: ='19'!Q24 -> 0 | R24: =Q24-P24 -> 0 | S24: 5 | T24: =R24*S24 -> 0
A25: Out Side Over - (Short) | C25: =(F9+F10+F12+F13)-(C5+C6+C7+C8+C9+C10+C11+C12+C13+C14+C15+C16+C18) -> 0 | H25: TOTAL | J25: =SUM(J20:J24) -> 0 | K25: 7 | N25: 22 | P25: ='19'!Q25 -> 0 | R25: =Q25-P25 -> 0 | S25: 5 | T25: =R25*S25 -> 0
A26: Cash Purchases | D26: Return Check Paid | K26: 8 | N26: 23 | P26: ='19'!Q26 -> 0 | R26: =Q26-P26 -> 0 | S26: 3 | T26: =R26*S26 -> 0
A27: Description | C27: Amount | D27: Description | F27: Amount | K27: 9 | N27: 24 | P27: ='19'!Q27 -> 0 | R27: =Q27-P27 -> 0 | S27: 3 | T27: =R27*S27 -> 0
H28: CASH PAYROLL EXPENSE | K28: 10 | N28: 25 | P28: ='19'!Q28 -> 0 | R28: =Q28-P28 -> 0 | S28: 2 | T28: =R28*S28 -> 0
H29: CASH PAYROLL PAID TO | J29: AMOUNT | K29: 11 | N29: 26 | P29: ='19'!Q29 -> 0 | R29: =Q29-P29 -> 0 | S29: 5 | T29: =R29*S29 -> 0
K30: 12 | N30: 27 | P30: ='19'!Q30 -> 0 | R30: =Q30-P30 -> 0 | S30: 3 | T30: =R30*S30 -> 0
K31: 13 | N31: 28 | P31: ='19'!Q31 -> 0 | R31: =Q31-P31 -> 0 | S31: 3 | T31: =R31*S31 -> 0
K32: 14 | N32: 29 | P32: ='19'!Q32 -> 0 | R32: =Q32-P32 -> 0 | S32: 2 | T32: =R32*S32 -> 0
D33: Total | F33: =SUM(F28:F32) -> 0 | K33: 15 | N33: 30 | P33: ='19'!Q33 -> 0 | R33: =Q33-P33 -> 0 | S33: 2 | T33: =R33*S33 -> 0
D34: Cash Expense | K34: 16 | N34: 31 | P34: ='19'!Q34 -> 0 | R34: =Q34-P34 -> 0 | S34: 2 | T34: =R34*S34 -> 0
D35: Description | F35: Amount | K35: 17 | N35: 32 | P35: ='19'!Q35 -> 0 | R35: =Q35-P35 -> 0 | S35: 2 | T35: =R35*S35 -> 0
K36: 18 | N36: 33 | P36: ='19'!Q36 -> 0 | R36: =Q36-P36 -> 0 | S36: 2 | T36: =R36*S36 -> 0
K37: 19 | N37: 34 | P37: ='19'!Q37 -> 0 | R37: =Q37-P37 -> 0 | S37: 1 | T37: =R37*S37 -> 0
K38: 20 | N38: 35 | P38: ='19'!Q38 -> 0 | R38: =Q38-P38 -> 0 | S38: 1 | T38: =R38*S38 -> 0
K39: 21 | N39: 36 | P39: ='19'!Q39 -> 0 | R39: =Q39-P39 -> 0 | S39: 2 | T39: =R39*S39 -> 0
A40: Total | C40: =SUM(C28:C39) -> 0 | D40: Total | F40: =SUM(F36:F39) -> 0 | H40: TOTAL | J40: =SUM(J30:J39) -> 0 | K40: TOTAL | L40: =SUM(L19:L39) -> 0 | N40: 37 | P40: ='19'!Q40 -> 0 | R40: =Q40-P40 -> 0 | S40: 2 | T40: =R40*S40 -> 0
N41: 38 | P41: ='19'!Q41 -> 0 | R41: =Q41-P41 -> 0 | S41: 2 | T41: =R41*S41 -> 0
A42: Check Purchases | D42: Check Expenses | N42: 39 | P42: ='19'!Q42 -> 0 | R42: =Q42-P42 -> 0 | S42: 1 | T42: =R42*S42 -> 0
A43: Description | B43: Check | C43: Amount | D43: Description | E43: Check | F43: Amount | H43: CASH IN | K43: CASH OUT TO OTHER | N43: 40 | P43: ='19'!Q43 -> 0 | R43: =Q43-P43 -> 0 | S43: 1 | T43: =R43*S43 -> 0
H44: CASH IN FROM | J44: AMOUNT | K44: OTHER CASH OUT | M44: AMOUNT | N44: 41 | P44: ='19'!Q44 -> 0 | R44: =Q44-P44 -> 0 | S44: 10 | T44: =R44*S44 -> 0
H45: Take $1530 Coin Withdrawal | N45: 42 | P45: ='19'!Q45 -> 0 | R45: =Q45-P45 -> 0 | S45: 1 | T45: =R45*S45 -> 0
N46: 43 | P46: ='19'!Q46 -> 0 | R46: =Q46-P46 -> 0 | S46: 1 | T46: =R46*S46 -> 0
D47: Total | F47: =SUM(F44:F46) -> 0 | N47: 44 | P47: ='19'!Q47 -> 0 | R47: =Q47-P47 -> 0 | S47: 1 | T47: =R47*S47 -> 0
D48: Rebates and Commissions | N48: 45 | P48: ='19'!Q48 -> 0 | R48: =Q48-P48 -> 0 | S48: 1 | T48: =R48*S48 -> 0
D49: Description | F49: Amount | N49: 46 | P49: ='19'!Q49 -> 0 | R49: =Q49-P49 -> 0 | S49: 1 | T49: =R49*S49 -> 0
N50: 47 | P50: ='19'!Q50 -> 0 | R50: =Q50-P50 -> 0 | S50: 1 | T50: =R50*S50 -> 0
N51: 48 | P51: ='19'!Q51 -> 0 | R51: =Q51-P51 -> 0 | S51: 1 | T51: =R51*S51 -> 0
O52: Total Lottery Sale | S52: =SUM(T4:T51) -> 0
A53: Total | C53: =SUM(C44:C52) -> 0 | D53: Total | F53: =SUM(F50:F52) -> 0 | H53: TOTAL | J53: =SUM(J45:J52) -> 0 | K53: TOTAL | M53: =SUM(M45:M52) -> 0

Sheet 21
A1: ='1'!A1:F1 -> DINERO EXPRESS #8 (512) 8015655 | H1: =A1 -> DINERO EXPRESS #8 (512) 8015655 | M1: DATE
A2: Daily Report | D2: Date: | F2: ='20'!F2+1 -> 20 | H2: OTHER REPORTS | M2: =F2 -> 20 | O2: Lottery Sale
D3: Day: | M3: =F3 -> 0 | O3: Game # | P3: Open | Q3: Close | R3: Tic.Sold | S3: $ Value | T3: T. Sale
A4: Reciepts | C4: Amount | D4: Disbursments | F4: Amount | H4: MONEY TRANSFER | N4: 1 | P4: ='20'!Q4 -> 0 | R4: =Q4-P4 -> 0 | S4: 50 | T4: =R4*S4 -> 0
A5: ='1'!A5:B5 -> Taxable Sale | D5: ='1'!D5:E5 -> Cash Purchases | F5: =C40 -> 0 | H5: Company | I5: Amount | J5: Fees | K5: Commission | L5: Individual Total Amount | N5: 2 | P5: ='20'!Q5 -> 0 | R5: =Q5-P5 -> 0 | S5: 20 | T5: =R5*S5 -> 0
A6: ='1'!A6:B6 -> Comm & Fee | D6: ='1'!D6:E6 -> Cash Expense | F6: =F40 -> 0 | H6: ='1'!H6 -> DINEX | L6: =SUM(I6:K6) -> 0 | N6: 3 | P6: ='20'!Q6 -> 0 | R6: =Q6-P6 -> 0 | S6: 20 | T6: =R6*S6 -> 0
A7: ='1'!A7:B7 -> Sales Tax | D7: ='1'!D7:E7 -> Check Purchases | F7: =C53 -> 0 | H7: ='1'!H7 -> INTERMEX | L7: =SUM(I7:K7) -> 0 | N7: 4 | P7: ='20'!Q7 -> 0 | R7: =Q7-P7 -> 0 | S7: 10 | T7: =R7*S7 -> 0
A8: ='1'!A8:B8 -> Money Transfers | C8: =L14 -> 0 | D8: ='1'!D8:E8 -> Check Expense | F8: =F47 -> 0 | H8: ='1'!H8 -> SIGUE | L8: =SUM(I8:K8) -> 0 | N8: 5 | P8: ='20'!Q8 -> 0 | R8: =Q8-P8 -> 0 | S8: 10 | T8: =R8*S8 -> 0
A9: ='1'!A9:B9 -> Lottery Sales | C9: =S52 -> 0 | D9: ='1'!D9:E9 -> Lotto Paid Out | H9: ='1'!H9 -> AFEX | L9: =SUM(I9:K9) -> 0 | N9: 6 | P9: ='20'!Q9 -> 0 | R9: =Q9-P9 -> 0 | S9: 20 | T9: =R9*S9 -> 0
A10: ='1'!A10:B10 -> Lotto Net Sales | D10: ='1'!D10:E10 -> Lottery Paid Out | H10: ='1'!H10 -> MONEYGRAM | L10: =SUM(I10:K10) -> 0 | N10: 7 | P10: ='20'!Q10 -> 0 | R10: =Q10-P10 -> 0 | S10: 20 | T10: =R10*S10 -> 0
A11: ='1'!A11:B11 -> PhoneCard | D11: ='1'!D11:E11 -> ATM Drop | H11: ='1'!H11 -> BARRI | L11: =SUM(I11:K11) -> 0 | N11: 8 | P11: ='20'!Q11 -> 0 | R11: =Q11-P11 -> 0 | S11: 20 | T11: =R11*S11 -> 0
A12: ='1'!A12:B12 -> Boss Revolution | D12: ='1'!D12:E12 -> Credit Card | H12: ='1'!H12 -> MAXI | L12: =SUM(I12:K12) -> 0 | N12: 9 | P12: ='20'!Q12 -> 0 | R12: =Q12-P12 -> 0 | S12: 10 | T12: =R12*S12 -> 0
A13: ='1'!A13:B13 -> Bill Payment | D13: ='1'!D13:E13 -> Outside Cash & Drops | F13: =L40 -> 0 | H13: ='1'!H13 -> AMIGO SIN PIN | L13: =SUM(I13:K13) -> 0 | N13: 10 | P13: ='20'!Q13 -> 0 | R13: =Q13-P13 -> 0 | S13: 10 | T13: =R13*S13 -> 0
A14: ='1'!A14:B14 -> VidaPay | D14: ='1'!D14:E14 -> Cash Deposit | H14: TOTAL | I14: =SUM(I6:I13) -> 0 | J14: =SUM(J6:J13) -> 0 | K14: =SUM(K6:K13) -> 0 | L14: =SUM(L6:M13) -> 0 | N14: 11 | P14: ='20'!Q14 -> 0 | R14: =Q14-P14 -> 0 | S14: 5 | T14: =R14*S14 -> 0
A15: ='1'!A15:B15 -> Boost Epay | D15: ='1'!D15:E15 -> Money Gram Payment | N15: 12 | P15: ='20'!Q15 -> 0 | R15: =Q15-P15 -> 0 | S15: 5 | T15: =R15*S15 -> 0
A16: ='1'!A16:B16 -> Epay | D16: ='1'!D16:E16 -> Vigo Payment | N16: 13 | P16: ='20'!Q16 -> 0 | R16: =Q16-P16 -> 0 | S16: 5 | T16: =R16*S16 -> 0
A17: ='1'!A17:B17 -> Check Cashing Fees | D17: ='1'!D17:E17 -> Ria Payment | N17: 14 | P17: ='20'!Q17 -> 0 | R17: =Q17-P17 -> 0 | S17: 5 | T17: =R17*S17 -> 0
A18: ='1'!A18:B18 -> Money Order | D18: ='1'!D18:E18 -> Checks Deposit | F18: =J25 -> 0 | H18: CHECK DEPOSITS | K18: DROPS | L18: AMOUNT | M18: TIME | N18: 15 | P18: ='20'!Q18 -> 0 | R18: =Q18-P18 -> 0 | S18: 5 | T18: =R18*S18 -> 0
A19: ='1'!A19:B19 -> Return Check Paid | C19: =F33 -> 0 | D19: ='1'!D19:E19 -> Safe Balance | H19: CHECK DEPOSITS TO BANK | J19: AMOUNT | K19: 1 | N19: 16 | P19: ='20'!Q19 -> 0 | R19: =Q19-P19 -> 0 | S19: 5 | T19: =R19*S19 -> 0
A20: ='1'!A20:B20 -> Forward Balance | C20: ='20'!F19+'20'!F13 -> 0 | D20: ='1'!D20:E20 -> Payroll Expense | F20: =J40 -> 0 | H20: PIONEER | K20: 2 | N20: 17 | P20: ='20'!Q20 -> 0 | R20: =Q20-P20 -> 0 | S20: 5 | T20: =R20*S20 -> 0
A21: ='1'!A21:B21 -> Cash From Bank | D21: ='1'!D21:E21 -> Other Cash Out | F21: =M53 -> 0 | H21: PIONEER | K21: 3 | N21: 18 | P21: ='20'!Q21 -> 0 | R21: =Q21-P21 -> 0 | S21: 5 | T21: =R21*S21 -> 0
A22: ='1'!A22:B22 -> Other Cash In | C22: =J53 -> 0 | D22: TOTAL PAYOUTS | F22: =SUM(F5:F21)-F7-F8 -> 0 | K22: 4 | N22: 19 | P22: ='20'!Q22 -> 0 | R22: =Q22-P22 -> 0 | S22: 5 | T22: =R22*S22 -> 0
A23: ='1'!A23:B23 -> Rebates & Commissions | C23: =F53 -> 0 | D23: Inside Over - (Short) | F23: =(F11+F14+F15+F16+F17+F18+F19+F20+F21+F5+F6)-(C17+C19+C20+C21+C22+C23) -> 0 | K23: 5 | N23: 20 | P23: ='20'!Q23 -> 0 | R23: =Q23-P23 -> 0 | S23: 5 | T23: =R23*S23 -> 0
A24: TOTAL RECEIPTS | C24: =SUM(C5:C23) -> 0 | D24: Over All Over - (Short) | F24: =SUM(F22-C24) -> 0 | K24: 6 | N24: 21 | P24: ='20'!Q24 -> 0 | R24: =Q24-P24 -> 0 | S24: 5 | T24: =R24*S24 -> 0
A25: Out Side Over - (Short) | C25: =(F9+F10+F12+F13)-(C5+C6+C7+C8+C9+C10+C11+C12+C13+C14+C15+C16+C18) -> 0 | H25: TOTAL | J25: =SUM(J20:J24) -> 0 | K25: 7 | N25: 22 | P25: ='20'!Q25 -> 0 | R25: =Q25-P25 -> 0 | S25: 5 | T25: =R25*S25 -> 0
A26: Cash Purchases | D26: Return Check Paid | K26: 8 | N26: 23 | P26: ='20'!Q26 -> 0 | R26: =Q26-P26 -> 0 | S26: 3 | T26: =R26*S26 -> 0
A27: Description | C27: Amount | D27: Description | F27: Amount | K27: 9 | N27: 24 | P27: ='20'!Q27 -> 0 | R27: =Q27-P27 -> 0 | S27: 3 | T27: =R27*S27 -> 0
H28: CASH PAYROLL EXPENSE | K28: 10 | N28: 25 | P28: ='20'!Q28 -> 0 | R28: =Q28-P28 -> 0 | S28: 2 | T28: =R28*S28 -> 0
H29: CASH PAYROLL PAID TO | J29: AMOUNT | K29: 11 | N29: 26 | P29: ='20'!Q29 -> 0 | R29: =Q29-P29 -> 0 | S29: 5 | T29: =R29*S29 -> 0
K30: 12 | N30: 27 | P30: ='20'!Q30 -> 0 | R30: =Q30-P30 -> 0 | S30: 3 | T30: =R30*S30 -> 0
K31: 13 | N31: 28 | P31: ='20'!Q31 -> 0 | R31: =Q31-P31 -> 0 | S31: 3 | T31: =R31*S31 -> 0
K32: 14 | N32: 29 | P32: ='20'!Q32 -> 0 | R32: =Q32-P32 -> 0 | S32: 2 | T32: =R32*S32 -> 0
D33: Total | F33: =SUM(F28:F32) -> 0 | K33: 15 | N33: 30 | P33: ='20'!Q33 -> 0 | R33: =Q33-P33 -> 0 | S33: 2 | T33: =R33*S33 -> 0
D34: Cash Expense | K34: 16 | N34: 31 | P34: ='20'!Q34 -> 0 | R34: =Q34-P34 -> 0 | S34: 2 | T34: =R34*S34 -> 0
D35: Description | F35: Amount | K35: 17 | N35: 32 | P35: ='20'!Q35 -> 0 | R35: =Q35-P35 -> 0 | S35: 2 | T35: =R35*S35 -> 0
K36: 18 | N36: 33 | P36: ='20'!Q36 -> 0 | R36: =Q36-P36 -> 0 | S36: 2 | T36: =R36*S36 -> 0
K37: 19 | N37: 34 | P37: ='20'!Q37 -> 0 | R37: =Q37-P37 -> 0 | S37: 1 | T37: =R37*S37 -> 0
K38: 20 | N38: 35 | P38: ='20'!Q38 -> 0 | R38: =Q38-P38 -> 0 | S38: 1 | T38: =R38*S38 -> 0
K39: 21 | N39: 36 | P39: ='20'!Q39 -> 0 | R39: =Q39-P39 -> 0 | S39: 2 | T39: =R39*S39 -> 0
A40: Total | C40: =SUM(C28:C39) -> 0 | D40: Total | F40: =SUM(F36:F39) -> 0 | H40: TOTAL | J40: =SUM(J30:J39) -> 0 | K40: TOTAL | L40: =SUM(L19:L39) -> 0 | N40: 37 | P40: ='20'!Q40 -> 0 | R40: =Q40-P40 -> 0 | S40: 2 | T40: =R40*S40 -> 0
N41: 38 | P41: ='20'!Q41 -> 0 | R41: =Q41-P41 -> 0 | S41: 2 | T41: =R41*S41 -> 0
A42: Check Purchases | D42: Check Expenses | N42: 39 | P42: ='20'!Q42 -> 0 | R42: =Q42-P42 -> 0 | S42: 1 | T42: =R42*S42 -> 0
A43: Description | B43: Check | C43: Amount | D43: Description | E43: Check | F43: Amount | H43: CASH IN | K43: CASH OUT TO OTHER | N43: 40 | P43: ='20'!Q43 -> 0 | R43: =Q43-P43 -> 0 | S43: 1 | T43: =R43*S43 -> 0
H44: CASH IN FROM | J44: AMOUNT | K44: OTHER CASH OUT | M44: AMOUNT | N44: 41 | P44: ='20'!Q44 -> 0 | R44: =Q44-P44 -> 0 | S44: 10 | T44: =R44*S44 -> 0
N45: 42 | P45: ='20'!Q45 -> 0 | R45: =Q45-P45 -> 0 | S45: 1 | T45: =R45*S45 -> 0
N46: 43 | P46: ='20'!Q46 -> 0 | R46: =Q46-P46 -> 0 | S46: 1 | T46: =R46*S46 -> 0
D47: Total | F47: =SUM(F44:F46) -> 0 | N47: 44 | P47: ='20'!Q47 -> 0 | R47: =Q47-P47 -> 0 | S47: 1 | T47: =R47*S47 -> 0
D48: Rebates and Commissions | N48: 45 | P48: ='20'!Q48 -> 0 | R48: =Q48-P48 -> 0 | S48: 1 | T48: =R48*S48 -> 0
D49: Description | F49: Amount | N49: 46 | P49: ='20'!Q49 -> 0 | R49: =Q49-P49 -> 0 | S49: 1 | T49: =R49*S49 -> 0
N50: 47 | P50: ='20'!Q50 -> 0 | R50: =Q50-P50 -> 0 | S50: 1 | T50: =R50*S50 -> 0
N51: 48 | P51: ='20'!Q51 -> 0 | R51: =Q51-P51 -> 0 | S51: 1 | T51: =R51*S51 -> 0
O52: Total Lottery Sale | S52: =SUM(T4:T51) -> 0
A53: Total | C53: =SUM(C44:C52) -> 0 | D53: Total | F53: =SUM(F50:F52) -> 0 | H53: TOTAL | J53: =SUM(J45:J52) -> 0 | K53: TOTAL | M53: =SUM(M45:M52) -> 0

Sheet 22
A1: ='1'!A1:F1 -> DINERO EXPRESS #8 (512) 8015655 | H1: =A1 -> DINERO EXPRESS #8 (512) 8015655 | M1: DATE
A2: Daily Report | D2: Date: | F2: ='21'!F2+1 -> 21 | H2: OTHER REPORTS | M2: =F2 -> 21 | O2: Lottery Sale
D3: Day: | M3: =F3 -> 0 | O3: Game # | P3: Open | Q3: Close | R3: Tic.Sold | S3: $ Value | T3: T. Sale
A4: Reciepts | C4: Amount | D4: Disbursments | F4: Amount | H4: MONEY TRANSFER | N4: 1 | P4: ='21'!Q4 -> 0 | R4: =Q4-P4 -> 0 | S4: 50 | T4: =R4*S4 -> 0
A5: ='1'!A5:B5 -> Taxable Sale | D5: ='1'!D5:E5 -> Cash Purchases | F5: =C40 -> 0 | H5: Company | I5: Amount | J5: Fees | K5: Commission | L5: Individual Total Amount | N5: 2 | P5: ='21'!Q5 -> 0 | R5: =Q5-P5 -> 0 | S5: 20 | T5: =R5*S5 -> 0
A6: ='1'!A6:B6 -> Comm & Fee | D6: ='1'!D6:E6 -> Cash Expense | F6: =F40 -> 0 | H6: ='1'!H6 -> DINEX | L6: =SUM(I6:K6) -> 0 | N6: 3 | P6: ='21'!Q6 -> 0 | R6: =Q6-P6 -> 0 | S6: 20 | T6: =R6*S6 -> 0
A7: ='1'!A7:B7 -> Sales Tax | D7: ='1'!D7:E7 -> Check Purchases | F7: =C53 -> 0 | H7: ='1'!H7 -> INTERMEX | L7: =SUM(I7:K7) -> 0 | N7: 4 | P7: ='21'!Q7 -> 0 | R7: =Q7-P7 -> 0 | S7: 10 | T7: =R7*S7 -> 0
A8: ='1'!A8:B8 -> Money Transfers | C8: =L14 -> 0 | D8: ='1'!D8:E8 -> Check Expense | F8: =F47 -> 0 | H8: ='1'!H8 -> SIGUE | L8: =SUM(I8:K8) -> 0 | N8: 5 | P8: ='21'!Q8 -> 0 | R8: =Q8-P8 -> 0 | S8: 10 | T8: =R8*S8 -> 0
A9: ='1'!A9:B9 -> Lottery Sales | C9: =S52 -> 0 | D9: ='1'!D9:E9 -> Lotto Paid Out | H9: ='1'!H9 -> AFEX | L9: =SUM(I9:K9) -> 0 | N9: 6 | P9: ='21'!Q9 -> 0 | R9: =Q9-P9 -> 0 | S9: 20 | T9: =R9*S9 -> 0
A10: ='1'!A10:B10 -> Lotto Net Sales | D10: ='1'!D10:E10 -> Lottery Paid Out | H10: ='1'!H10 -> MONEYGRAM | L10: =SUM(I10:K10) -> 0 | N10: 7 | P10: ='21'!Q10 -> 0 | R10: =Q10-P10 -> 0 | S10: 20 | T10: =R10*S10 -> 0
A11: ='1'!A11:B11 -> PhoneCard | D11: ='1'!D11:E11 -> ATM Drop | H11: ='1'!H11 -> BARRI | L11: =SUM(I11:K11) -> 0 | N11: 8 | P11: ='21'!Q11 -> 0 | R11: =Q11-P11 -> 0 | S11: 20 | T11: =R11*S11 -> 0
A12: ='1'!A12:B12 -> Boss Revolution | D12: ='1'!D12:E12 -> Credit Card | H12: ='1'!H12 -> MAXI | L12: =SUM(I12:K12) -> 0 | N12: 9 | P12: ='21'!Q12 -> 0 | R12: =Q12-P12 -> 0 | S12: 10 | T12: =R12*S12 -> 0
A13: ='1'!A13:B13 -> Bill Payment | D13: ='1'!D13:E13 -> Outside Cash & Drops | F13: =L40 -> 0 | H13: ='1'!H13 -> AMIGO SIN PIN | L13: =SUM(I13:K13) -> 0 | N13: 10 | P13: ='21'!Q13 -> 0 | R13: =Q13-P13 -> 0 | S13: 10 | T13: =R13*S13 -> 0
A14: ='1'!A14:B14 -> VidaPay | D14: ='1'!D14:E14 -> Cash Deposit | H14: TOTAL | I14: =SUM(I6:I13) -> 0 | J14: =SUM(J6:J13) -> 0 | K14: =SUM(K6:K13) -> 0 | L14: =SUM(L6:M13) -> 0 | N14: 11 | P14: ='21'!Q14 -> 0 | R14: =Q14-P14 -> 0 | S14: 5 | T14: =R14*S14 -> 0
A15: ='1'!A15:B15 -> Boost Epay | D15: ='1'!D15:E15 -> Money Gram Payment | N15: 12 | P15: ='21'!Q15 -> 0 | R15: =Q15-P15 -> 0 | S15: 5 | T15: =R15*S15 -> 0
A16: ='1'!A16:B16 -> Epay | D16: ='1'!D16:E16 -> Vigo Payment | N16: 13 | P16: ='21'!Q16 -> 0 | R16: =Q16-P16 -> 0 | S16: 5 | T16: =R16*S16 -> 0
A17: ='1'!A17:B17 -> Check Cashing Fees | D17: ='1'!D17:E17 -> Ria Payment | N17: 14 | P17: ='21'!Q17 -> 0 | R17: =Q17-P17 -> 0 | S17: 5 | T17: =R17*S17 -> 0
A18: ='1'!A18:B18 -> Money Order | D18: ='1'!D18:E18 -> Checks Deposit | F18: =J25 -> 0 | H18: CHECK DEPOSITS | K18: DROPS | L18: AMOUNT | M18: TIME | N18: 15 | P18: ='21'!Q18 -> 0 | R18: =Q18-P18 -> 0 | S18: 5 | T18: =R18*S18 -> 0
A19: ='1'!A19:B19 -> Return Check Paid | C19: =F33 -> 0 | D19: ='1'!D19:E19 -> Safe Balance | H19: CHECK DEPOSITS TO BANK | J19: AMOUNT | K19: 1 | N19: 16 | P19: ='21'!Q19 -> 0 | R19: =Q19-P19 -> 0 | S19: 5 | T19: =R19*S19 -> 0
A20: ='1'!A20:B20 -> Forward Balance | C20: ='21'!F19+'21'!F13 -> 0 | D20: ='1'!D20:E20 -> Payroll Expense | F20: =J40 -> 0 | H20: PIONEER | K20: 2 | N20: 17 | P20: ='21'!Q20 -> 0 | R20: =Q20-P20 -> 0 | S20: 5 | T20: =R20*S20 -> 0
A21: ='1'!A21:B21 -> Cash From Bank | D21: ='1'!D21:E21 -> Other Cash Out | F21: =M53 -> 0 | H21: PIONEER | K21: 3 | N21: 18 | P21: ='21'!Q21 -> 0 | R21: =Q21-P21 -> 0 | S21: 5 | T21: =R21*S21 -> 0
A22: ='1'!A22:B22 -> Other Cash In | C22: =J53 -> 0 | D22: TOTAL PAYOUTS | F22: =SUM(F5:F21)-F7-F8 -> 0 | K22: 4 | N22: 19 | P22: ='21'!Q22 -> 0 | R22: =Q22-P22 -> 0 | S22: 5 | T22: =R22*S22 -> 0
A23: ='1'!A23:B23 -> Rebates & Commissions | C23: =F53 -> 0 | D23: Inside Over - (Short) | F23: =(F11+F14+F15+F16+F17+F18+F19+F20+F21+F5+F6)-(C17+C19+C20+C21+C22+C23) -> 0 | K23: 5 | N23: 20 | P23: ='21'!Q23 -> 0 | R23: =Q23-P23 -> 0 | S23: 5 | T23: =R23*S23 -> 0
A24: TOTAL RECEIPTS | C24: =SUM(C5:C23) -> 0 | D24: Over All Over - (Short) | F24: =SUM(F22-C24) -> 0 | K24: 6 | N24: 21 | P24: ='21'!Q24 -> 0 | R24: =Q24-P24 -> 0 | S24: 5 | T24: =R24*S24 -> 0
A25: Out Side Over - (Short) | C25: =(F9+F10+F12+F13)-(C5+C6+C7+C8+C9+C10+C11+C12+C13+C14+C15+C16+C18) -> 0 | H25: TOTAL | J25: =SUM(J20:J24) -> 0 | K25: 7 | N25: 22 | P25: ='21'!Q25 -> 0 | R25: =Q25-P25 -> 0 | S25: 5 | T25: =R25*S25 -> 0
A26: Cash Purchases | D26: Return Check Paid | K26: 8 | N26: 23 | P26: ='21'!Q26 -> 0 | R26: =Q26-P26 -> 0 | S26: 3 | T26: =R26*S26 -> 0
A27: Description | C27: Amount | D27: Description | F27: Amount | K27: 9 | N27: 24 | P27: ='21'!Q27 -> 0 | R27: =Q27-P27 -> 0 | S27: 3 | T27: =R27*S27 -> 0
H28: CASH PAYROLL EXPENSE | K28: 10 | N28: 25 | P28: ='21'!Q28 -> 0 | R28: =Q28-P28 -> 0 | S28: 2 | T28: =R28*S28 -> 0
H29: CASH PAYROLL PAID TO | J29: AMOUNT | K29: 11 | N29: 26 | P29: ='21'!Q29 -> 0 | R29: =Q29-P29 -> 0 | S29: 5 | T29: =R29*S29 -> 0
K30: 12 | N30: 27 | P30: ='21'!Q30 -> 0 | R30: =Q30-P30 -> 0 | S30: 3 | T30: =R30*S30 -> 0
K31: 13 | N31: 28 | P31: ='21'!Q31 -> 0 | R31: =Q31-P31 -> 0 | S31: 3 | T31: =R31*S31 -> 0
K32: 14 | N32: 29 | P32: ='21'!Q32 -> 0 | R32: =Q32-P32 -> 0 | S32: 2 | T32: =R32*S32 -> 0
D33: Total | F33: =SUM(F28:F32) -> 0 | K33: 15 | N33: 30 | P33: ='21'!Q33 -> 0 | R33: =Q33-P33 -> 0 | S33: 2 | T33: =R33*S33 -> 0
D34: Cash Expense | K34: 16 | N34: 31 | P34: ='21'!Q34 -> 0 | R34: =Q34-P34 -> 0 | S34: 2 | T34: =R34*S34 -> 0
D35: Description | F35: Amount | K35: 17 | N35: 32 | P35: ='21'!Q35 -> 0 | R35: =Q35-P35 -> 0 | S35: 2 | T35: =R35*S35 -> 0
K36: 18 | N36: 33 | P36: ='21'!Q36 -> 0 | R36: =Q36-P36 -> 0 | S36: 2 | T36: =R36*S36 -> 0
K37: 19 | N37: 34 | P37: ='21'!Q37 -> 0 | R37: =Q37-P37 -> 0 | S37: 1 | T37: =R37*S37 -> 0
K38: 20 | N38: 35 | P38: ='21'!Q38 -> 0 | R38: =Q38-P38 -> 0 | S38: 1 | T38: =R38*S38 -> 0
K39: 21 | N39: 36 | P39: ='21'!Q39 -> 0 | R39: =Q39-P39 -> 0 | S39: 2 | T39: =R39*S39 -> 0
A40: Total | C40: =SUM(C28:C39) -> 0 | D40: Total | F40: =SUM(F36:F39) -> 0 | H40: TOTAL | J40: =SUM(J30:J39) -> 0 | K40: TOTAL | L40: =SUM(L19:L39) -> 0 | N40: 37 | P40: ='21'!Q40 -> 0 | R40: =Q40-P40 -> 0 | S40: 2 | T40: =R40*S40 -> 0
N41: 38 | P41: ='21'!Q41 -> 0 | R41: =Q41-P41 -> 0 | S41: 2 | T41: =R41*S41 -> 0
A42: Check Purchases | D42: Check Expenses | N42: 39 | P42: ='21'!Q42 -> 0 | R42: =Q42-P42 -> 0 | S42: 1 | T42: =R42*S42 -> 0
A43: Description | B43: Check | C43: Amount | D43: Description | E43: Check | F43: Amount | H43: CASH IN | K43: CASH OUT TO OTHER | N43: 40 | P43: ='21'!Q43 -> 0 | R43: =Q43-P43 -> 0 | S43: 1 | T43: =R43*S43 -> 0
H44: CASH IN FROM | J44: AMOUNT | K44: OTHER CASH OUT | M44: AMOUNT | N44: 41 | P44: ='21'!Q44 -> 0 | R44: =Q44-P44 -> 0 | S44: 10 | T44: =R44*S44 -> 0
N45: 42 | P45: ='21'!Q45 -> 0 | R45: =Q45-P45 -> 0 | S45: 1 | T45: =R45*S45 -> 0
N46: 43 | P46: ='21'!Q46 -> 0 | R46: =Q46-P46 -> 0 | S46: 1 | T46: =R46*S46 -> 0
D47: Total | F47: =SUM(F44:F46) -> 0 | N47: 44 | P47: ='21'!Q47 -> 0 | R47: =Q47-P47 -> 0 | S47: 1 | T47: =R47*S47 -> 0
D48: Rebates and Commissions | N48: 45 | P48: ='21'!Q48 -> 0 | R48: =Q48-P48 -> 0 | S48: 1 | T48: =R48*S48 -> 0
D49: Description | F49: Amount | N49: 46 | P49: ='21'!Q49 -> 0 | R49: =Q49-P49 -> 0 | S49: 1 | T49: =R49*S49 -> 0
N50: 47 | P50: ='21'!Q50 -> 0 | R50: =Q50-P50 -> 0 | S50: 1 | T50: =R50*S50 -> 0
N51: 48 | P51: ='21'!Q51 -> 0 | R51: =Q51-P51 -> 0 | S51: 1 | T51: =R51*S51 -> 0
O52: Total Lottery Sale | S52: =SUM(T4:T51) -> 0
A53: Total | C53: =SUM(C44:C52) -> 0 | D53: Total | F53: =SUM(F50:F52) -> 0 | H53: TOTAL | J53: =SUM(J45:J52) -> 0 | K53: TOTAL | M53: =SUM(M45:M52) -> 0

Sheet 23
A1: ='1'!A1:F1 -> DINERO EXPRESS #8 (512) 8015655 | H1: =A1 -> DINERO EXPRESS #8 (512) 8015655 | M1: DATE
A2: Daily Report | D2: Date: | F2: ='22'!F2+1 -> 22 | H2: OTHER REPORTS | M2: =F2 -> 22 | O2: Lottery Sale
D3: Day: | M3: =F3 -> 0 | O3: Game # | P3: Open | Q3: Close | R3: Tic.Sold | S3: $ Value | T3: T. Sale
A4: Reciepts | C4: Amount | D4: Disbursments | F4: Amount | H4: MONEY TRANSFER | N4: 1 | P4: ='22'!Q4 -> 0 | R4: =Q4-P4 -> 0 | S4: 50 | T4: =R4*S4 -> 0
A5: ='1'!A5:B5 -> Taxable Sale | D5: ='1'!D5:E5 -> Cash Purchases | F5: =C40 -> 0 | H5: Company | I5: Amount | J5: Fees | K5: Commission | L5: Individual Total Amount | N5: 2 | P5: ='22'!Q5 -> 0 | R5: =Q5-P5 -> 0 | S5: 20 | T5: =R5*S5 -> 0
A6: ='1'!A6:B6 -> Comm & Fee | D6: ='1'!D6:E6 -> Cash Expense | F6: =F40 -> 0 | H6: ='1'!H6 -> DINEX | L6: =SUM(I6:K6) -> 0 | N6: 3 | P6: ='22'!Q6 -> 0 | R6: =Q6-P6 -> 0 | S6: 20 | T6: =R6*S6 -> 0
A7: ='1'!A7:B7 -> Sales Tax | D7: ='1'!D7:E7 -> Check Purchases | F7: =C53 -> 0 | H7: ='1'!H7 -> INTERMEX | L7: =SUM(I7:K7) -> 0 | N7: 4 | P7: ='22'!Q7 -> 0 | R7: =Q7-P7 -> 0 | S7: 10 | T7: =R7*S7 -> 0
A8: ='1'!A8:B8 -> Money Transfers | C8: =L14 -> 0 | D8: ='1'!D8:E8 -> Check Expense | F8: =F47 -> 0 | H8: ='1'!H8 -> SIGUE | L8: =SUM(I8:K8) -> 0 | N8: 5 | P8: ='22'!Q8 -> 0 | R8: =Q8-P8 -> 0 | S8: 10 | T8: =R8*S8 -> 0
A9: ='1'!A9:B9 -> Lottery Sales | C9: =S52 -> 0 | D9: ='1'!D9:E9 -> Lotto Paid Out | H9: ='1'!H9 -> AFEX | L9: =SUM(I9:K9) -> 0 | N9: 6 | P9: ='22'!Q9 -> 0 | R9: =Q9-P9 -> 0 | S9: 20 | T9: =R9*S9 -> 0
A10: ='1'!A10:B10 -> Lotto Net Sales | D10: ='1'!D10:E10 -> Lottery Paid Out | H10: ='1'!H10 -> MONEYGRAM | L10: =SUM(I10:K10) -> 0 | N10: 7 | P10: ='22'!Q10 -> 0 | R10: =Q10-P10 -> 0 | S10: 20 | T10: =R10*S10 -> 0
A11: ='1'!A11:B11 -> PhoneCard | D11: ='1'!D11:E11 -> ATM Drop | H11: ='1'!H11 -> BARRI | L11: =SUM(I11:K11) -> 0 | N11: 8 | P11: ='22'!Q11 -> 0 | R11: =Q11-P11 -> 0 | S11: 20 | T11: =R11*S11 -> 0
A12: ='1'!A12:B12 -> Boss Revolution | D12: ='1'!D12:E12 -> Credit Card | H12: ='1'!H12 -> MAXI | L12: =SUM(I12:K12) -> 0 | N12: 9 | P12: ='22'!Q12 -> 0 | R12: =Q12-P12 -> 0 | S12: 10 | T12: =R12*S12 -> 0
A13: ='1'!A13:B13 -> Bill Payment | D13: ='1'!D13:E13 -> Outside Cash & Drops | F13: =L40 -> 0 | H13: ='1'!H13 -> AMIGO SIN PIN | L13: =SUM(I13:K13) -> 0 | N13: 10 | P13: ='22'!Q13 -> 0 | R13: =Q13-P13 -> 0 | S13: 10 | T13: =R13*S13 -> 0
A14: ='1'!A14:B14 -> VidaPay | D14: ='1'!D14:E14 -> Cash Deposit | H14: TOTAL | I14: =SUM(I6:I13) -> 0 | J14: =SUM(J6:J13) -> 0 | K14: =SUM(K6:K13) -> 0 | L14: =SUM(L6:M13) -> 0 | N14: 11 | P14: ='22'!Q14 -> 0 | R14: =Q14-P14 -> 0 | S14: 5 | T14: =R14*S14 -> 0
A15: ='1'!A15:B15 -> Boost Epay | D15: ='1'!D15:E15 -> Money Gram Payment | N15: 12 | P15: ='22'!Q15 -> 0 | R15: =Q15-P15 -> 0 | S15: 5 | T15: =R15*S15 -> 0
A16: ='1'!A16:B16 -> Epay | D16: ='1'!D16:E16 -> Vigo Payment | N16: 13 | P16: ='22'!Q16 -> 0 | R16: =Q16-P16 -> 0 | S16: 5 | T16: =R16*S16 -> 0
A17: ='1'!A17:B17 -> Check Cashing Fees | D17: ='1'!D17:E17 -> Ria Payment | N17: 14 | P17: ='22'!Q17 -> 0 | R17: =Q17-P17 -> 0 | S17: 5 | T17: =R17*S17 -> 0
A18: ='1'!A18:B18 -> Money Order | D18: ='1'!D18:E18 -> Checks Deposit | F18: =J25 -> 0 | H18: CHECK DEPOSITS | K18: DROPS | L18: AMOUNT | M18: TIME | N18: 15 | P18: ='22'!Q18 -> 0 | R18: =Q18-P18 -> 0 | S18: 5 | T18: =R18*S18 -> 0
A19: ='1'!A19:B19 -> Return Check Paid | C19: =F33 -> 0 | D19: ='1'!D19:E19 -> Safe Balance | H19: CHECK DEPOSITS TO BANK | J19: AMOUNT | K19: 1 | N19: 16 | P19: ='22'!Q19 -> 0 | R19: =Q19-P19 -> 0 | S19: 5 | T19: =R19*S19 -> 0
A20: ='1'!A20:B20 -> Forward Balance | C20: ='22'!F19+'22'!F13 -> 0 | D20: ='1'!D20:E20 -> Payroll Expense | F20: =J40 -> 0 | H20: PIONEER | K20: 2 | N20: 17 | P20: ='22'!Q20 -> 0 | R20: =Q20-P20 -> 0 | S20: 5 | T20: =R20*S20 -> 0
A21: ='1'!A21:B21 -> Cash From Bank | D21: ='1'!D21:E21 -> Other Cash Out | F21: =M53 -> 0 | H21: PIONEER | K21: 3 | N21: 18 | P21: ='22'!Q21 -> 0 | R21: =Q21-P21 -> 0 | S21: 5 | T21: =R21*S21 -> 0
A22: ='1'!A22:B22 -> Other Cash In | C22: =J53 -> 0 | D22: TOTAL PAYOUTS | F22: =SUM(F5:F21)-F7-F8 -> 0 | K22: 4 | N22: 19 | P22: ='22'!Q22 -> 0 | R22: =Q22-P22 -> 0 | S22: 5 | T22: =R22*S22 -> 0
A23: ='1'!A23:B23 -> Rebates & Commissions | C23: =F53 -> 0 | D23: Inside Over - (Short) | F23: =(F11+F14+F15+F16+F17+F18+F19+F20+F21+F5+F6)-(C17+C19+C20+C21+C22+C23) -> 0 | K23: 5 | N23: 20 | P23: ='22'!Q23 -> 0 | R23: =Q23-P23 -> 0 | S23: 5 | T23: =R23*S23 -> 0
A24: TOTAL RECEIPTS | C24: =SUM(C5:C23) -> 0 | D24: Over All Over - (Short) | F24: =SUM(F22-C24) -> 0 | K24: 6 | N24: 21 | P24: ='22'!Q24 -> 0 | R24: =Q24-P24 -> 0 | S24: 5 | T24: =R24*S24 -> 0
A25: Out Side Over - (Short) | C25: =(F9+F10+F12+F13)-(C5+C6+C7+C8+C9+C10+C11+C12+C13+C14+C15+C16+C18) -> 0 | H25: TOTAL | J25: =SUM(J20:J24) -> 0 | K25: 7 | N25: 22 | P25: ='22'!Q25 -> 0 | R25: =Q25-P25 -> 0 | S25: 5 | T25: =R25*S25 -> 0
A26: Cash Purchases | D26: Return Check Paid | K26: 8 | N26: 23 | P26: ='22'!Q26 -> 0 | R26: =Q26-P26 -> 0 | S26: 3 | T26: =R26*S26 -> 0
A27: Description | C27: Amount | D27: Description | F27: Amount | K27: 9 | N27: 24 | P27: ='22'!Q27 -> 0 | R27: =Q27-P27 -> 0 | S27: 3 | T27: =R27*S27 -> 0
H28: CASH PAYROLL EXPENSE | K28: 10 | N28: 25 | P28: ='22'!Q28 -> 0 | R28: =Q28-P28 -> 0 | S28: 2 | T28: =R28*S28 -> 0
H29: CASH PAYROLL PAID TO | J29: AMOUNT | K29: 11 | N29: 26 | P29: ='22'!Q29 -> 0 | R29: =Q29-P29 -> 0 | S29: 5 | T29: =R29*S29 -> 0
K30: 12 | N30: 27 | P30: ='22'!Q30 -> 0 | R30: =Q30-P30 -> 0 | S30: 3 | T30: =R30*S30 -> 0
K31: 13 | N31: 28 | P31: ='22'!Q31 -> 0 | R31: =Q31-P31 -> 0 | S31: 3 | T31: =R31*S31 -> 0
K32: 14 | N32: 29 | P32: ='22'!Q32 -> 0 | R32: =Q32-P32 -> 0 | S32: 2 | T32: =R32*S32 -> 0
D33: Total | F33: =SUM(F28:F32) -> 0 | K33: 15 | N33: 30 | P33: ='22'!Q33 -> 0 | R33: =Q33-P33 -> 0 | S33: 2 | T33: =R33*S33 -> 0
D34: Cash Expense | K34: 16 | N34: 31 | P34: ='22'!Q34 -> 0 | R34: =Q34-P34 -> 0 | S34: 2 | T34: =R34*S34 -> 0
D35: Description | F35: Amount | K35: 17 | N35: 32 | P35: ='22'!Q35 -> 0 | R35: =Q35-P35 -> 0 | S35: 2 | T35: =R35*S35 -> 0
K36: 18 | N36: 33 | P36: ='22'!Q36 -> 0 | R36: =Q36-P36 -> 0 | S36: 2 | T36: =R36*S36 -> 0
K37: 19 | N37: 34 | P37: ='22'!Q37 -> 0 | R37: =Q37-P37 -> 0 | S37: 1 | T37: =R37*S37 -> 0
K38: 20 | N38: 35 | P38: ='22'!Q38 -> 0 | R38: =Q38-P38 -> 0 | S38: 1 | T38: =R38*S38 -> 0
K39: 21 | N39: 36 | P39: ='22'!Q39 -> 0 | R39: =Q39-P39 -> 0 | S39: 2 | T39: =R39*S39 -> 0
A40: Total | C40: =SUM(C28:C39) -> 0 | D40: Total | F40: =SUM(F36:F39) -> 0 | H40: TOTAL | J40: =SUM(J30:J39) -> 0 | K40: TOTAL | L40: =SUM(L19:L39) -> 0 | N40: 37 | P40: ='22'!Q40 -> 0 | R40: =Q40-P40 -> 0 | S40: 2 | T40: =R40*S40 -> 0
N41: 38 | P41: ='22'!Q41 -> 0 | R41: =Q41-P41 -> 0 | S41: 2 | T41: =R41*S41 -> 0
A42: Check Purchases | D42: Check Expenses | N42: 39 | P42: ='22'!Q42 -> 0 | R42: =Q42-P42 -> 0 | S42: 1 | T42: =R42*S42 -> 0
A43: Description | B43: Check | C43: Amount | D43: Description | E43: Check | F43: Amount | H43: CASH IN | K43: CASH OUT TO OTHER | N43: 40 | P43: ='22'!Q43 -> 0 | R43: =Q43-P43 -> 0 | S43: 1 | T43: =R43*S43 -> 0
H44: CASH IN FROM | J44: AMOUNT | K44: OTHER CASH OUT | M44: AMOUNT | N44: 41 | P44: ='22'!Q44 -> 0 | R44: =Q44-P44 -> 0 | S44: 10 | T44: =R44*S44 -> 0
N45: 42 | P45: ='22'!Q45 -> 0 | R45: =Q45-P45 -> 0 | S45: 1 | T45: =R45*S45 -> 0
N46: 43 | P46: ='22'!Q46 -> 0 | R46: =Q46-P46 -> 0 | S46: 1 | T46: =R46*S46 -> 0
D47: Total | F47: =SUM(F44:F46) -> 0 | N47: 44 | P47: ='22'!Q47 -> 0 | R47: =Q47-P47 -> 0 | S47: 1 | T47: =R47*S47 -> 0
D48: Rebates and Commissions | N48: 45 | P48: ='22'!Q48 -> 0 | R48: =Q48-P48 -> 0 | S48: 1 | T48: =R48*S48 -> 0
D49: Description | F49: Amount | N49: 46 | P49: ='22'!Q49 -> 0 | R49: =Q49-P49 -> 0 | S49: 1 | T49: =R49*S49 -> 0
N50: 47 | P50: ='22'!Q50 -> 0 | R50: =Q50-P50 -> 0 | S50: 1 | T50: =R50*S50 -> 0
N51: 48 | P51: ='22'!Q51 -> 0 | R51: =Q51-P51 -> 0 | S51: 1 | T51: =R51*S51 -> 0
O52: Total Lottery Sale | S52: =SUM(T4:T51) -> 0
A53: Total | C53: =SUM(C44:C52) -> 0 | D53: Total | F53: =SUM(F50:F52) -> 0 | H53: TOTAL | J53: =SUM(J45:J52) -> 0 | K53: TOTAL | M53: =SUM(M45:M52) -> 0

Sheet 24
A1: ='1'!A1:F1 -> DINERO EXPRESS #8 (512) 8015655 | H1: =A1 -> DINERO EXPRESS #8 (512) 8015655 | M1: DATE
A2: Daily Report | D2: Date: | F2: ='23'!F2+1 -> 23 | H2: OTHER REPORTS | M2: =F2 -> 23 | O2: Lottery Sale
D3: Day: | M3: =F3 -> 0 | O3: Game # | P3: Open | Q3: Close | R3: Tic.Sold | S3: $ Value | T3: T. Sale
A4: Reciepts | C4: Amount | D4: Disbursments | F4: Amount | H4: MONEY TRANSFER | N4: 1 | P4: ='23'!Q4 -> 0 | R4: =Q4-P4 -> 0 | S4: 50 | T4: =R4*S4 -> 0
A5: ='1'!A5:B5 -> Taxable Sale | D5: ='1'!D5:E5 -> Cash Purchases | F5: =C40 -> 0 | H5: Company | I5: Amount | J5: Fees | K5: Commission | L5: Individual Total Amount | N5: 2 | P5: ='23'!Q5 -> 0 | R5: =Q5-P5 -> 0 | S5: 20 | T5: =R5*S5 -> 0
A6: ='1'!A6:B6 -> Comm & Fee | D6: ='1'!D6:E6 -> Cash Expense | F6: =F40 -> 0 | H6: ='1'!H6 -> DINEX | L6: =SUM(I6:K6) -> 0 | N6: 3 | P6: ='23'!Q6 -> 0 | R6: =Q6-P6 -> 0 | S6: 20 | T6: =R6*S6 -> 0
A7: ='1'!A7:B7 -> Sales Tax | D7: ='1'!D7:E7 -> Check Purchases | F7: =C53 -> 0 | H7: ='1'!H7 -> INTERMEX | L7: =SUM(I7:K7) -> 0 | N7: 4 | P7: ='23'!Q7 -> 0 | R7: =Q7-P7 -> 0 | S7: 10 | T7: =R7*S7 -> 0
A8: ='1'!A8:B8 -> Money Transfers | C8: =L14 -> 0 | D8: ='1'!D8:E8 -> Check Expense | F8: =F47 -> 0 | H8: ='1'!H8 -> SIGUE | L8: =SUM(I8:K8) -> 0 | N8: 5 | P8: ='23'!Q8 -> 0 | R8: =Q8-P8 -> 0 | S8: 10 | T8: =R8*S8 -> 0
A9: ='1'!A9:B9 -> Lottery Sales | C9: =S52 -> 0 | D9: ='1'!D9:E9 -> Lotto Paid Out | H9: ='1'!H9 -> AFEX | L9: =SUM(I9:K9) -> 0 | N9: 6 | P9: ='23'!Q9 -> 0 | R9: =Q9-P9 -> 0 | S9: 20 | T9: =R9*S9 -> 0
A10: ='1'!A10:B10 -> Lotto Net Sales | D10: ='1'!D10:E10 -> Lottery Paid Out | H10: ='1'!H10 -> MONEYGRAM | L10: =SUM(I10:K10) -> 0 | N10: 7 | P10: ='23'!Q10 -> 0 | R10: =Q10-P10 -> 0 | S10: 20 | T10: =R10*S10 -> 0
A11: ='1'!A11:B11 -> PhoneCard | D11: ='1'!D11:E11 -> ATM Drop | H11: ='1'!H11 -> BARRI | L11: =SUM(I11:K11) -> 0 | N11: 8 | P11: ='23'!Q11 -> 0 | R11: =Q11-P11 -> 0 | S11: 20 | T11: =R11*S11 -> 0
A12: ='1'!A12:B12 -> Boss Revolution | D12: ='1'!D12:E12 -> Credit Card | H12: ='1'!H12 -> MAXI | L12: =SUM(I12:K12) -> 0 | N12: 9 | P12: ='23'!Q12 -> 0 | R12: =Q12-P12 -> 0 | S12: 10 | T12: =R12*S12 -> 0
A13: ='1'!A13:B13 -> Bill Payment | D13: ='1'!D13:E13 -> Outside Cash & Drops | F13: =L40 -> 0 | H13: ='1'!H13 -> AMIGO SIN PIN | L13: =SUM(I13:K13) -> 0 | N13: 10 | P13: ='23'!Q13 -> 0 | R13: =Q13-P13 -> 0 | S13: 10 | T13: =R13*S13 -> 0
A14: ='1'!A14:B14 -> VidaPay | D14: ='1'!D14:E14 -> Cash Deposit | H14: TOTAL | I14: =SUM(I6:I13) -> 0 | J14: =SUM(J6:J13) -> 0 | K14: =SUM(K6:K13) -> 0 | L14: =SUM(L6:M13) -> 0 | N14: 11 | P14: ='23'!Q14 -> 0 | R14: =Q14-P14 -> 0 | S14: 5 | T14: =R14*S14 -> 0
A15: ='1'!A15:B15 -> Boost Epay | D15: ='1'!D15:E15 -> Money Gram Payment | N15: 12 | P15: ='23'!Q15 -> 0 | R15: =Q15-P15 -> 0 | S15: 5 | T15: =R15*S15 -> 0
A16: ='1'!A16:B16 -> Epay | D16: ='1'!D16:E16 -> Vigo Payment | N16: 13 | P16: ='23'!Q16 -> 0 | R16: =Q16-P16 -> 0 | S16: 5 | T16: =R16*S16 -> 0
A17: ='1'!A17:B17 -> Check Cashing Fees | D17: ='1'!D17:E17 -> Ria Payment | N17: 14 | P17: ='23'!Q17 -> 0 | R17: =Q17-P17 -> 0 | S17: 5 | T17: =R17*S17 -> 0
A18: ='1'!A18:B18 -> Money Order | D18: ='1'!D18:E18 -> Checks Deposit | F18: =J25 -> 0 | H18: CHECK DEPOSITS | K18: DROPS | L18: AMOUNT | M18: TIME | N18: 15 | P18: ='23'!Q18 -> 0 | R18: =Q18-P18 -> 0 | S18: 5 | T18: =R18*S18 -> 0
A19: ='1'!A19:B19 -> Return Check Paid | C19: =F33 -> 0 | D19: ='1'!D19:E19 -> Safe Balance | H19: CHECK DEPOSITS TO BANK | J19: AMOUNT | K19: 1 | N19: 16 | P19: ='23'!Q19 -> 0 | R19: =Q19-P19 -> 0 | S19: 5 | T19: =R19*S19 -> 0
A20: ='1'!A20:B20 -> Forward Balance | C20: ='23'!F19+'23'!F13 -> 0 | D20: ='1'!D20:E20 -> Payroll Expense | F20: =J40 -> 0 | H20: PIONEER | K20: 2 | N20: 17 | P20: ='23'!Q20 -> 0 | R20: =Q20-P20 -> 0 | S20: 5 | T20: =R20*S20 -> 0
A21: ='1'!A21:B21 -> Cash From Bank | D21: ='1'!D21:E21 -> Other Cash Out | F21: =M53 -> 0 | H21: PIONEER | K21: 3 | N21: 18 | P21: ='23'!Q21 -> 0 | R21: =Q21-P21 -> 0 | S21: 5 | T21: =R21*S21 -> 0
A22: ='1'!A22:B22 -> Other Cash In | C22: =J53 -> 0 | D22: TOTAL PAYOUTS | F22: =SUM(F5:F21)-F7-F8 -> 0 | K22: 4 | N22: 19 | P22: ='23'!Q22 -> 0 | R22: =Q22-P22 -> 0 | S22: 5 | T22: =R22*S22 -> 0
A23: ='1'!A23:B23 -> Rebates & Commissions | C23: =F53 -> 0 | D23: Inside Over - (Short) | F23: =(F11+F14+F15+F16+F17+F18+F19+F20+F21+F5+F6)-(C17+C19+C20+C21+C22+C23) -> 0 | K23: 5 | N23: 20 | P23: ='23'!Q23 -> 0 | R23: =Q23-P23 -> 0 | S23: 5 | T23: =R23*S23 -> 0
A24: TOTAL RECEIPTS | C24: =SUM(C5:C23) -> 0 | D24: Over All Over - (Short) | F24: =SUM(F22-C24) -> 0 | K24: 6 | N24: 21 | P24: ='23'!Q24 -> 0 | R24: =Q24-P24 -> 0 | S24: 5 | T24: =R24*S24 -> 0
A25: Out Side Over - (Short) | C25: =(F9+F10+F12+F13)-(C5+C6+C7+C8+C9+C10+C11+C12+C13+C14+C15+C16+C18) -> 0 | H25: TOTAL | J25: =SUM(J20:J24) -> 0 | K25: 7 | N25: 22 | P25: ='23'!Q25 -> 0 | R25: =Q25-P25 -> 0 | S25: 5 | T25: =R25*S25 -> 0
A26: Cash Purchases | D26: Return Check Paid | K26: 8 | N26: 23 | P26: ='23'!Q26 -> 0 | R26: =Q26-P26 -> 0 | S26: 3 | T26: =R26*S26 -> 0
A27: Description | C27: Amount | D27: Description | F27: Amount | K27: 9 | N27: 24 | P27: ='23'!Q27 -> 0 | R27: =Q27-P27 -> 0 | S27: 3 | T27: =R27*S27 -> 0
H28: CASH PAYROLL EXPENSE | K28: 10 | N28: 25 | P28: ='23'!Q28 -> 0 | R28: =Q28-P28 -> 0 | S28: 2 | T28: =R28*S28 -> 0
H29: CASH PAYROLL PAID TO | J29: AMOUNT | K29: 11 | N29: 26 | P29: ='23'!Q29 -> 0 | R29: =Q29-P29 -> 0 | S29: 5 | T29: =R29*S29 -> 0
K30: 12 | N30: 27 | P30: ='23'!Q30 -> 0 | R30: =Q30-P30 -> 0 | S30: 3 | T30: =R30*S30 -> 0
K31: 13 | N31: 28 | P31: ='23'!Q31 -> 0 | R31: =Q31-P31 -> 0 | S31: 3 | T31: =R31*S31 -> 0
K32: 14 | N32: 29 | P32: ='23'!Q32 -> 0 | R32: =Q32-P32 -> 0 | S32: 2 | T32: =R32*S32 -> 0
D33: Total | F33: =SUM(F28:F32) -> 0 | K33: 15 | N33: 30 | P33: ='23'!Q33 -> 0 | R33: =Q33-P33 -> 0 | S33: 2 | T33: =R33*S33 -> 0
D34: Cash Expense | K34: 16 | N34: 31 | P34: ='23'!Q34 -> 0 | R34: =Q34-P34 -> 0 | S34: 2 | T34: =R34*S34 -> 0
D35: Description | F35: Amount | K35: 17 | N35: 32 | P35: ='23'!Q35 -> 0 | R35: =Q35-P35 -> 0 | S35: 2 | T35: =R35*S35 -> 0
